<?xml version="1.0" encoding="UTF-8"?>
<ColorMaps xmlns:xsi="http://www.w3.org/2001/XMLSchema-instance"
          xsi:noNamespaceSchemaLocation="http://gibs.earthdata.nasa.gov/schemas/ColorMap_v1.3.xsd">
  <ColorMap title="Surface Precipitation Rate" units="mm/hr">
    <Entries>
      <ColorMapEntry rgb="17,17,17" transparent="true" sourceValue="[0.0000,0.104603)" value="[0.0000,0.104603)" ref="0"/>
      <ColorMapEntry rgb="128,0,128" transparent="false" sourceValue="[0.104603,0.209205)" value="[0.104603,0.209205)" ref="1"/>
      <ColorMapEntry rgb="133,0,133" transparent="false" sourceValue="[0.209205,0.313808)" value="[0.209205,0.313808)" ref="2"/>
      <ColorMapEntry rgb="138,0,138" transparent="false" sourceValue="[0.313808,0.418410)" value="[0.313808,0.418410)" ref="3"/>
      <ColorMapEntry rgb="143,0,143" transparent="false" sourceValue="[0.418410,0.523013)" value="[0.418410,0.523013)" ref="4"/>
      <ColorMapEntry rgb="149,0,149" transparent="false" sourceValue="[0.523013,0.627615)" value="[0.523013,0.627615)" ref="5"/>
      <ColorMapEntry rgb="154,0,154" transparent="false" sourceValue="[0.627615,0.732218)" value="[0.627615,0.732218)" ref="6"/>
      <ColorMapEntry rgb="159,0,159" transparent="false" sourceValue="[0.732218,0.836820)" value="[0.732218,0.836820)" ref="7"/>
      <ColorMapEntry rgb="164,0,164" transparent="false" sourceValue="[0.836820,0.941423)" value="[0.836820,0.941423)" ref="8"/>
      <ColorMapEntry rgb="170,0,170" transparent="false" sourceValue="[0.941423,1.046025)" value="[0.941423,1.046025)" ref="9"/>
      <ColorMapEntry rgb="175,0,175" transparent="false" sourceValue="[1.046025,1.150628)" value="[1.046025,1.150628)" ref="10"/>
      <ColorMapEntry rgb="181,0,181" transparent="false" sourceValue="[1.150628,1.255230)" value="[1.150628,1.255230)" ref="11"/>
      <ColorMapEntry rgb="186,0,186" transparent="false" sourceValue="[1.255230,1.359833)" value="[1.255230,1.359833)" ref="12"/>
      <ColorMapEntry rgb="191,0,191" transparent="false" sourceValue="[1.359833,1.464435)" value="[1.359833,1.464435)" ref="13"/>
      <ColorMapEntry rgb="196,0,196" transparent="false" sourceValue="[1.464435,1.569038)" value="[1.464435,1.569038)" ref="14"/>
      <ColorMapEntry rgb="202,0,202" transparent="false" sourceValue="[1.569038,1.673640)" value="[1.569038,1.673640)" ref="15"/>
      <ColorMapEntry rgb="207,0,207" transparent="false" sourceValue="[1.673640,1.778243)" value="[1.673640,1.778243)" ref="16"/>
      <ColorMapEntry rgb="213,0,213" transparent="false" sourceValue="[1.778243,1.882845)" value="[1.778243,1.882845)" ref="17"/>
      <ColorMapEntry rgb="218,0,218" transparent="false" sourceValue="[1.882845,1.987448)" value="[1.882845,1.987448)" ref="18"/>
      <ColorMapEntry rgb="223,0,223" transparent="false" sourceValue="[1.987448,2.092050)" value="[1.987448,2.092050)" ref="19"/>
      <ColorMapEntry rgb="228,0,228" transparent="false" sourceValue="[2.092050,2.196653)" value="[2.092050,2.196653)" ref="20"/>
      <ColorMapEntry rgb="234,0,234" transparent="false" sourceValue="[2.196653,2.301255)" value="[2.196653,2.301255)" ref="21"/>
      <ColorMapEntry rgb="239,0,239" transparent="false" sourceValue="[2.301255,2.405858)" value="[2.301255,2.405858)" ref="22"/>
      <ColorMapEntry rgb="244,0,244" transparent="false" sourceValue="[2.405858,2.510460)" value="[2.405858,2.510460)" ref="23"/>
      <ColorMapEntry rgb="255,0,255" transparent="false" sourceValue="[2.510460,2.615063)" value="[2.510460,2.615063)" ref="24"/>
      <ColorMapEntry rgb="248,0,255" transparent="false" sourceValue="[2.615063,2.719665)" value="[2.615063,2.719665)" ref="25"/>
      <ColorMapEntry rgb="241,0,255" transparent="false" sourceValue="[2.719665,2.824268)" value="[2.719665,2.824268)" ref="26"/>
      <ColorMapEntry rgb="234,0,255" transparent="false" sourceValue="[2.824268,2.928870)" value="[2.824268,2.928870)" ref="27"/>
      <ColorMapEntry rgb="227,0,255" transparent="false" sourceValue="[2.928870,3.033473)" value="[2.928870,3.033473)" ref="28"/>
      <ColorMapEntry rgb="220,0,255" transparent="false" sourceValue="[3.033473,3.138075)" value="[3.033473,3.138075)" ref="29"/>
      <ColorMapEntry rgb="212,0,255" transparent="false" sourceValue="[3.138075,3.242678)" value="[3.138075,3.242678)" ref="30"/>
      <ColorMapEntry rgb="205,0,255" transparent="false" sourceValue="[3.242678,3.347280)" value="[3.242678,3.347280)" ref="31"/>
      <ColorMapEntry rgb="198,0,255" transparent="false" sourceValue="[3.347280,3.451883)" value="[3.347280,3.451883)" ref="32"/>
      <ColorMapEntry rgb="191,0,255" transparent="false" sourceValue="[3.451883,3.556485)" value="[3.451883,3.556485)" ref="33"/>
      <ColorMapEntry rgb="184,0,255" transparent="false" sourceValue="[3.556485,3.661088)" value="[3.556485,3.661088)" ref="34"/>
      <ColorMapEntry rgb="177,0,255" transparent="false" sourceValue="[3.661088,3.765690)" value="[3.661088,3.765690)" ref="35"/>
      <ColorMapEntry rgb="170,0,255" transparent="false" sourceValue="[3.765690,3.870293)" value="[3.765690,3.870293)" ref="36"/>
      <ColorMapEntry rgb="163,0,255" transparent="false" sourceValue="[3.870293,3.974895)" value="[3.870293,3.974895)" ref="37"/>
      <ColorMapEntry rgb="156,0,255" transparent="false" sourceValue="[3.974895,4.079498)" value="[3.974895,4.079498)" ref="38"/>
      <ColorMapEntry rgb="149,0,255" transparent="false" sourceValue="[4.079498,4.184100)" value="[4.079498,4.184100)" ref="39"/>
      <ColorMapEntry rgb="142,0,255" transparent="false" sourceValue="[4.184100,4.288703)" value="[4.184100,4.288703)" ref="40"/>
      <ColorMapEntry rgb="135,0,255" transparent="false" sourceValue="[4.288703,4.393305)" value="[4.288703,4.393305)" ref="41"/>
      <ColorMapEntry rgb="127,0,255" transparent="false" sourceValue="[4.393305,4.497908)" value="[4.393305,4.497908)" ref="42"/>
      <ColorMapEntry rgb="120,0,255" transparent="false" sourceValue="[4.497908,4.602510)" value="[4.497908,4.602510)" ref="43"/>
      <ColorMapEntry rgb="113,0,255" transparent="false" sourceValue="[4.602510,4.707113)" value="[4.602510,4.707113)" ref="44"/>
      <ColorMapEntry rgb="106,0,255" transparent="false" sourceValue="[4.707113,4.811716)" value="[4.707113,4.811716)" ref="45"/>
      <ColorMapEntry rgb="99,0,255" transparent="false" sourceValue="[4.811716,4.916318)" value="[4.811716,4.916318)" ref="46"/>
      <ColorMapEntry rgb="92,0,255" transparent="false" sourceValue="[4.916318,5.020920)" value="[4.916318,5.020920)" ref="47"/>
      <ColorMapEntry rgb="85,0,255" transparent="false" sourceValue="[5.020920,5.125523)" value="[5.020920,5.125523)" ref="48"/>
      <ColorMapEntry rgb="78,0,255" transparent="false" sourceValue="[5.125523,5.230125)" value="[5.125523,5.230125)" ref="49"/>
      <ColorMapEntry rgb="71,0,255" transparent="false" sourceValue="[5.230125,5.334728)" value="[5.230125,5.334728)" ref="50"/>
      <ColorMapEntry rgb="64,0,255" transparent="false" sourceValue="[5.334728,5.439331)" value="[5.334728,5.439331)" ref="51"/>
      <ColorMapEntry rgb="57,0,255" transparent="false" sourceValue="[5.439331,5.543933)" value="[5.439331,5.543933)" ref="52"/>
      <ColorMapEntry rgb="50,0,255" transparent="false" sourceValue="[5.543933,5.648535)" value="[5.543933,5.648535)" ref="53"/>
      <ColorMapEntry rgb="42,0,255" transparent="false" sourceValue="[5.648535,5.753138)" value="[5.648535,5.753138)" ref="54"/>
      <ColorMapEntry rgb="35,0,255" transparent="false" sourceValue="[5.753138,5.857740)" value="[5.753138,5.857740)" ref="55"/>
      <ColorMapEntry rgb="28,0,255" transparent="false" sourceValue="[5.857740,5.962343)" value="[5.857740,5.962343)" ref="56"/>
      <ColorMapEntry rgb="21,0,255" transparent="false" sourceValue="[5.962343,6.066946)" value="[5.962343,6.066946)" ref="57"/>
      <ColorMapEntry rgb="14,0,255" transparent="false" sourceValue="[6.066946,6.171548)" value="[6.066946,6.171548)" ref="58"/>
      <ColorMapEntry rgb="7,0,255" transparent="false" sourceValue="[6.171548,6.276151)" value="[6.171548,6.276151)" ref="59"/>
      <ColorMapEntry rgb="0,0,255" transparent="false" sourceValue="[6.276151,6.380753)" value="[6.276151,6.380753)" ref="60"/>
      <ColorMapEntry rgb="0,7,255" transparent="false" sourceValue="[6.380753,6.485355)" value="[6.380753,6.485355)" ref="61"/>
      <ColorMapEntry rgb="0,14,255" transparent="false" sourceValue="[6.485355,6.589958)" value="[6.485355,6.589958)" ref="62"/>
      <ColorMapEntry rgb="0,21,255" transparent="false" sourceValue="[6.589958,6.694561)" value="[6.589958,6.694561)" ref="63"/>
      <ColorMapEntry rgb="0,28,255" transparent="false" sourceValue="[6.694561,6.799163)" value="[6.694561,6.799163)" ref="64"/>
      <ColorMapEntry rgb="0,35,255" transparent="false" sourceValue="[6.799163,6.903766)" value="[6.799163,6.903766)" ref="65"/>
      <ColorMapEntry rgb="0,43,255" transparent="false" sourceValue="[6.903766,7.008368)" value="[6.903766,7.008368)" ref="66"/>
      <ColorMapEntry rgb="0,50,255" transparent="false" sourceValue="[7.008368,7.112970)" value="[7.008368,7.112970)" ref="67"/>
      <ColorMapEntry rgb="0,57,255" transparent="false" sourceValue="[7.112970,7.217573)" value="[7.112970,7.217573)" ref="68"/>
      <ColorMapEntry rgb="0,64,255" transparent="false" sourceValue="[7.217573,7.322176)" value="[7.217573,7.322176)" ref="69"/>
      <ColorMapEntry rgb="0,71,255" transparent="false" sourceValue="[7.322176,7.426778)" value="[7.322176,7.426778)" ref="70"/>
      <ColorMapEntry rgb="0,78,255" transparent="false" sourceValue="[7.426778,7.531381)" value="[7.426778,7.531381)" ref="71"/>
      <ColorMapEntry rgb="0,85,255" transparent="false" sourceValue="[7.531381,7.635983)" value="[7.531381,7.635983)" ref="72"/>
      <ColorMapEntry rgb="0,92,255" transparent="false" sourceValue="[7.635983,7.740586)" value="[7.635983,7.740586)" ref="73"/>
      <ColorMapEntry rgb="0,99,255" transparent="false" sourceValue="[7.740586,7.845188)" value="[7.740586,7.845188)" ref="74"/>
      <ColorMapEntry rgb="0,106,255" transparent="false" sourceValue="[7.845188,7.949790)" value="[7.845188,7.949790)" ref="75"/>
      <ColorMapEntry rgb="0,113,255" transparent="false" sourceValue="[7.949790,8.054393)" value="[7.949790,8.054393)" ref="76"/>
      <ColorMapEntry rgb="0,120,255" transparent="false" sourceValue="[8.054393,8.158996)" value="[8.054393,8.158996)" ref="77"/>
      <ColorMapEntry rgb="0,128,255" transparent="false" sourceValue="[8.158996,8.263598)" value="[8.158996,8.263598)" ref="78"/>
      <ColorMapEntry rgb="0,135,255" transparent="false" sourceValue="[8.263598,8.368200)" value="[8.263598,8.368200)" ref="79"/>
      <ColorMapEntry rgb="0,142,255" transparent="false" sourceValue="[8.368200,8.472803)" value="[8.368200,8.472803)" ref="80"/>
      <ColorMapEntry rgb="0,149,255" transparent="false" sourceValue="[8.472803,8.577406)" value="[8.472803,8.577406)" ref="81"/>
      <ColorMapEntry rgb="0,156,255" transparent="false" sourceValue="[8.577406,8.682008)" value="[8.577406,8.682008)" ref="82"/>
      <ColorMapEntry rgb="0,163,255" transparent="false" sourceValue="[8.682008,8.786611)" value="[8.682008,8.786611)" ref="83"/>
      <ColorMapEntry rgb="0,170,255" transparent="false" sourceValue="[8.786611,8.891213)" value="[8.786611,8.891213)" ref="84"/>
      <ColorMapEntry rgb="0,177,255" transparent="false" sourceValue="[8.891213,8.995815)" value="[8.891213,8.995815)" ref="85"/>
      <ColorMapEntry rgb="0,184,255" transparent="false" sourceValue="[8.995815,9.100418)" value="[8.995815,9.100418)" ref="86"/>
      <ColorMapEntry rgb="0,191,255" transparent="false" sourceValue="[9.100418,9.205021)" value="[9.100418,9.205021)" ref="87"/>
      <ColorMapEntry rgb="0,198,255" transparent="false" sourceValue="[9.205021,9.309623)" value="[9.205021,9.309623)" ref="88"/>
      <ColorMapEntry rgb="0,205,255" transparent="false" sourceValue="[9.309623,9.414226)" value="[9.309623,9.414226)" ref="89"/>
      <ColorMapEntry rgb="0,213,255" transparent="false" sourceValue="[9.414226,9.518828)" value="[9.414226,9.518828)" ref="90"/>
      <ColorMapEntry rgb="0,220,255" transparent="false" sourceValue="[9.518828,9.623431)" value="[9.518828,9.623431)" ref="91"/>
      <ColorMapEntry rgb="0,227,255" transparent="false" sourceValue="[9.623431,9.728033)" value="[9.623431,9.728033)" ref="92"/>
      <ColorMapEntry rgb="0,234,255" transparent="false" sourceValue="[9.728033,9.832636)" value="[9.728033,9.832636)" ref="93"/>
      <ColorMapEntry rgb="0,241,255" transparent="false" sourceValue="[9.832636,9.937239)" value="[9.832636,9.937239)" ref="94"/>
      <ColorMapEntry rgb="0,248,255" transparent="false" sourceValue="[9.937239,10.041841)" value="[9.937239,10.041841)" ref="95"/>
      <ColorMapEntry rgb="0,255,255" transparent="false" sourceValue="[10.041841,10.146443)" value="[10.041841,10.146443)" ref="96"/>
      <ColorMapEntry rgb="0,253,248" transparent="false" sourceValue="[10.146443,10.251046)" value="[10.146443,10.251046)" ref="97"/>
      <ColorMapEntry rgb="0,250,241" transparent="false" sourceValue="[10.251046,10.355648)" value="[10.251046,10.355648)" ref="98"/>
      <ColorMapEntry rgb="0,248,234" transparent="false" sourceValue="[10.355648,10.460251)" value="[10.355648,10.460251)" ref="99"/>
      <ColorMapEntry rgb="0,246,227" transparent="false" sourceValue="[10.460251,10.564854)" value="[10.460251,10.564854)" ref="100"/>
      <ColorMapEntry rgb="0,243,220" transparent="false" sourceValue="[10.564854,10.669456)" value="[10.564854,10.669456)" ref="101"/>
      <ColorMapEntry rgb="0,241,212" transparent="false" sourceValue="[10.669456,10.774058)" value="[10.669456,10.774058)" ref="102"/>
      <ColorMapEntry rgb="0,238,205" transparent="false" sourceValue="[10.774058,10.878661)" value="[10.774058,10.878661)" ref="103"/>
      <ColorMapEntry rgb="0,236,198" transparent="false" sourceValue="[10.878661,10.983263)" value="[10.878661,10.983263)" ref="104"/>
      <ColorMapEntry rgb="0,234,191" transparent="false" sourceValue="[10.983263,11.087866)" value="[10.983263,11.087866)" ref="105"/>
      <ColorMapEntry rgb="0,231,184" transparent="false" sourceValue="[11.087866,11.192469)" value="[11.087866,11.192469)" ref="106"/>
      <ColorMapEntry rgb="0,229,177" transparent="false" sourceValue="[11.192469,11.297071)" value="[11.192469,11.297071)" ref="107"/>
      <ColorMapEntry rgb="0,227,170" transparent="false" sourceValue="[11.297071,11.401673)" value="[11.297071,11.401673)" ref="108"/>
      <ColorMapEntry rgb="0,224,163" transparent="false" sourceValue="[11.401673,11.506276)" value="[11.401673,11.506276)" ref="109"/>
      <ColorMapEntry rgb="0,222,156" transparent="false" sourceValue="[11.506276,11.610878)" value="[11.506276,11.610878)" ref="110"/>
      <ColorMapEntry rgb="0,220,149" transparent="false" sourceValue="[11.610878,11.715481)" value="[11.610878,11.715481)" ref="111"/>
      <ColorMapEntry rgb="0,217,142" transparent="false" sourceValue="[11.715481,11.820084)" value="[11.715481,11.820084)" ref="112"/>
      <ColorMapEntry rgb="0,215,135" transparent="false" sourceValue="[11.820084,11.924685)" value="[11.820084,11.924685)" ref="113"/>
      <ColorMapEntry rgb="0,212,127" transparent="false" sourceValue="[11.924685,12.029288)" value="[11.924685,12.029288)" ref="114"/>
      <ColorMapEntry rgb="0,210,120" transparent="false" sourceValue="[12.029288,12.133891)" value="[12.029288,12.133891)" ref="115"/>
      <ColorMapEntry rgb="0,208,113" transparent="false" sourceValue="[12.133891,12.238494)" value="[12.133891,12.238494)" ref="116"/>
      <ColorMapEntry rgb="0,205,106" transparent="false" sourceValue="[12.238494,12.343096)" value="[12.238494,12.343096)" ref="117"/>
      <ColorMapEntry rgb="0,203,99" transparent="false" sourceValue="[12.343096,12.447699)" value="[12.343096,12.447699)" ref="118"/>
      <ColorMapEntry rgb="0,201,92" transparent="false" sourceValue="[12.447699,12.552301)" value="[12.447699,12.552301)" ref="119"/>
      <ColorMapEntry rgb="0,198,85" transparent="false" sourceValue="[12.552301,12.656903)" value="[12.552301,12.656903)" ref="120"/>
      <ColorMapEntry rgb="0,196,78" transparent="false" sourceValue="[12.656903,12.761506)" value="[12.656903,12.761506)" ref="121"/>
      <ColorMapEntry rgb="0,194,71" transparent="false" sourceValue="[12.761506,12.866109)" value="[12.761506,12.866109)" ref="122"/>
      <ColorMapEntry rgb="0,191,64" transparent="false" sourceValue="[12.866109,12.970711)" value="[12.866109,12.970711)" ref="123"/>
      <ColorMapEntry rgb="0,189,57" transparent="false" sourceValue="[12.970711,13.075314)" value="[12.970711,13.075314)" ref="124"/>
      <ColorMapEntry rgb="0,187,50" transparent="false" sourceValue="[13.075314,13.179916)" value="[13.075314,13.179916)" ref="125"/>
      <ColorMapEntry rgb="0,184,42" transparent="false" sourceValue="[13.179916,13.284518)" value="[13.179916,13.284518)" ref="126"/>
      <ColorMapEntry rgb="0,182,35" transparent="false" sourceValue="[13.284518,13.389121)" value="[13.284518,13.389121)" ref="127"/>
      <ColorMapEntry rgb="0,179,28" transparent="false" sourceValue="[13.389121,13.493724)" value="[13.389121,13.493724)" ref="128"/>
      <ColorMapEntry rgb="0,177,21" transparent="false" sourceValue="[13.493724,13.598326)" value="[13.493724,13.598326)" ref="129"/>
      <ColorMapEntry rgb="0,175,14" transparent="false" sourceValue="[13.598326,13.702929)" value="[13.598326,13.702929)" ref="130"/>
      <ColorMapEntry rgb="0,172,7" transparent="false" sourceValue="[13.702929,13.807531)" value="[13.702929,13.807531)" ref="131"/>
      <ColorMapEntry rgb="0,170,0" transparent="false" sourceValue="[13.807531,13.912133)" value="[13.807531,13.912133)" ref="132"/>
      <ColorMapEntry rgb="7,172,0" transparent="false" sourceValue="[13.912133,14.016736)" value="[13.912133,14.016736)" ref="133"/>
      <ColorMapEntry rgb="14,175,0" transparent="false" sourceValue="[14.016736,14.121339)" value="[14.016736,14.121339)" ref="134"/>
      <ColorMapEntry rgb="21,177,0" transparent="false" sourceValue="[14.121339,14.225941)" value="[14.121339,14.225941)" ref="135"/>
      <ColorMapEntry rgb="28,179,0" transparent="false" sourceValue="[14.225941,14.330544)" value="[14.225941,14.330544)" ref="136"/>
      <ColorMapEntry rgb="35,182,0" transparent="false" sourceValue="[14.330544,14.435146)" value="[14.330544,14.435146)" ref="137"/>
      <ColorMapEntry rgb="43,184,0" transparent="false" sourceValue="[14.435146,14.539748)" value="[14.435146,14.539748)" ref="138"/>
      <ColorMapEntry rgb="50,187,0" transparent="false" sourceValue="[14.539748,14.644351)" value="[14.539748,14.644351)" ref="139"/>
      <ColorMapEntry rgb="57,189,0" transparent="false" sourceValue="[14.644351,14.748954)" value="[14.644351,14.748954)" ref="140"/>
      <ColorMapEntry rgb="64,191,0" transparent="false" sourceValue="[14.748954,14.853557)" value="[14.748954,14.853557)" ref="141"/>
      <ColorMapEntry rgb="71,194,0" transparent="false" sourceValue="[14.853557,14.958158)" value="[14.853557,14.958158)" ref="142"/>
      <ColorMapEntry rgb="78,196,0" transparent="false" sourceValue="[14.958158,15.062761)" value="[14.958158,15.062761)" ref="143"/>
      <ColorMapEntry rgb="85,198,0" transparent="false" sourceValue="[15.062761,15.167364)" value="[15.062761,15.167364)" ref="144"/>
      <ColorMapEntry rgb="92,201,0" transparent="false" sourceValue="[15.167364,15.271966)" value="[15.167364,15.271966)" ref="145"/>
      <ColorMapEntry rgb="99,203,0" transparent="false" sourceValue="[15.271966,15.376569)" value="[15.271966,15.376569)" ref="146"/>
      <ColorMapEntry rgb="106,205,0" transparent="false" sourceValue="[15.376569,15.481172)" value="[15.376569,15.481172)" ref="147"/>
      <ColorMapEntry rgb="113,208,0" transparent="false" sourceValue="[15.481172,15.585773)" value="[15.481172,15.585773)" ref="148"/>
      <ColorMapEntry rgb="120,210,0" transparent="false" sourceValue="[15.585773,15.690376)" value="[15.585773,15.690376)" ref="149"/>
      <ColorMapEntry rgb="128,213,0" transparent="false" sourceValue="[15.690376,15.794979)" value="[15.690376,15.794979)" ref="150"/>
      <ColorMapEntry rgb="135,215,0" transparent="false" sourceValue="[15.794979,15.899581)" value="[15.794979,15.899581)" ref="151"/>
      <ColorMapEntry rgb="142,217,0" transparent="false" sourceValue="[15.899581,16.004183)" value="[15.899581,16.004183)" ref="152"/>
      <ColorMapEntry rgb="149,220,0" transparent="false" sourceValue="[16.004183,16.108786)" value="[16.004183,16.108786)" ref="153"/>
      <ColorMapEntry rgb="156,222,0" transparent="false" sourceValue="[16.108786,16.213388)" value="[16.108786,16.213388)" ref="154"/>
      <ColorMapEntry rgb="163,224,0" transparent="false" sourceValue="[16.213388,16.317991)" value="[16.213388,16.317991)" ref="155"/>
      <ColorMapEntry rgb="170,227,0" transparent="false" sourceValue="[16.317991,16.422594)" value="[16.317991,16.422594)" ref="156"/>
      <ColorMapEntry rgb="177,229,0" transparent="false" sourceValue="[16.422594,16.527197)" value="[16.422594,16.527197)" ref="157"/>
      <ColorMapEntry rgb="184,231,0" transparent="false" sourceValue="[16.527197,16.631800)" value="[16.527197,16.631800)" ref="158"/>
      <ColorMapEntry rgb="191,234,0" transparent="false" sourceValue="[16.631800,16.736401)" value="[16.631800,16.736401)" ref="159"/>
      <ColorMapEntry rgb="198,236,0" transparent="false" sourceValue="[16.736401,16.841003)" value="[16.736401,16.841003)" ref="160"/>
      <ColorMapEntry rgb="205,238,0" transparent="false" sourceValue="[16.841003,16.945606)" value="[16.841003,16.945606)" ref="161"/>
      <ColorMapEntry rgb="213,241,0" transparent="false" sourceValue="[16.945606,17.050209)" value="[16.945606,17.050209)" ref="162"/>
      <ColorMapEntry rgb="220,243,0" transparent="false" sourceValue="[17.050209,17.154812)" value="[17.050209,17.154812)" ref="163"/>
      <ColorMapEntry rgb="227,246,0" transparent="false" sourceValue="[17.154812,17.259415)" value="[17.154812,17.259415)" ref="164"/>
      <ColorMapEntry rgb="234,248,0" transparent="false" sourceValue="[17.259415,17.364016)" value="[17.259415,17.364016)" ref="165"/>
      <ColorMapEntry rgb="241,250,0" transparent="false" sourceValue="[17.364016,17.468618)" value="[17.364016,17.468618)" ref="166"/>
      <ColorMapEntry rgb="248,253,0" transparent="false" sourceValue="[17.468618,17.573221)" value="[17.468618,17.573221)" ref="167"/>
      <ColorMapEntry rgb="255,255,0" transparent="false" sourceValue="[17.573221,17.677824)" value="[17.573221,17.677824)" ref="168"/>
      <ColorMapEntry rgb="255,248,0" transparent="false" sourceValue="[17.677824,17.782427)" value="[17.677824,17.782427)" ref="169"/>
      <ColorMapEntry rgb="255,241,0" transparent="false" sourceValue="[17.782427,17.887030)" value="[17.782427,17.887030)" ref="170"/>
      <ColorMapEntry rgb="255,234,0" transparent="false" sourceValue="[17.887030,17.991631)" value="[17.887030,17.991631)" ref="171"/>
      <ColorMapEntry rgb="255,227,0" transparent="false" sourceValue="[17.991631,18.096233)" value="[17.991631,18.096233)" ref="172"/>
      <ColorMapEntry rgb="255,220,0" transparent="false" sourceValue="[18.096233,18.200836)" value="[18.096233,18.200836)" ref="173"/>
      <ColorMapEntry rgb="255,212,0" transparent="false" sourceValue="[18.200836,18.305439)" value="[18.200836,18.305439)" ref="174"/>
      <ColorMapEntry rgb="255,205,0" transparent="false" sourceValue="[18.305439,18.410042)" value="[18.305439,18.410042)" ref="175"/>
      <ColorMapEntry rgb="255,198,0" transparent="false" sourceValue="[18.410042,18.514645)" value="[18.410042,18.514645)" ref="176"/>
      <ColorMapEntry rgb="255,191,0" transparent="false" sourceValue="[18.514645,18.619246)" value="[18.514645,18.619246)" ref="177"/>
      <ColorMapEntry rgb="255,184,0" transparent="false" sourceValue="[18.619246,18.723848)" value="[18.619246,18.723848)" ref="178"/>
      <ColorMapEntry rgb="255,177,0" transparent="false" sourceValue="[18.723848,18.828451)" value="[18.723848,18.828451)" ref="179"/>
      <ColorMapEntry rgb="255,170,0" transparent="false" sourceValue="[18.828451,18.933054)" value="[18.828451,18.933054)" ref="180"/>
      <ColorMapEntry rgb="255,163,0" transparent="false" sourceValue="[18.933054,19.037657)" value="[18.933054,19.037657)" ref="181"/>
      <ColorMapEntry rgb="255,156,0" transparent="false" sourceValue="[19.037657,19.142260)" value="[19.037657,19.142260)" ref="182"/>
      <ColorMapEntry rgb="255,149,0" transparent="false" sourceValue="[19.142260,19.246862)" value="[19.142260,19.246862)" ref="183"/>
      <ColorMapEntry rgb="255,142,0" transparent="false" sourceValue="[19.246862,19.351463)" value="[19.246862,19.351463)" ref="184"/>
      <ColorMapEntry rgb="255,135,0" transparent="false" sourceValue="[19.351463,19.456066)" value="[19.351463,19.456066)" ref="185"/>
      <ColorMapEntry rgb="255,127,0" transparent="false" sourceValue="[19.456066,19.560669)" value="[19.456066,19.560669)" ref="186"/>
      <ColorMapEntry rgb="255,120,0" transparent="false" sourceValue="[19.560669,19.665272)" value="[19.560669,19.665272)" ref="187"/>
      <ColorMapEntry rgb="255,113,0" transparent="false" sourceValue="[19.665272,19.769875)" value="[19.665272,19.769875)" ref="188"/>
      <ColorMapEntry rgb="255,106,0" transparent="false" sourceValue="[19.769875,19.874477)" value="[19.769875,19.874477)" ref="189"/>
      <ColorMapEntry rgb="255,99,0" transparent="false" sourceValue="[19.874477,19.979078)" value="[19.874477,19.979078)" ref="190"/>
      <ColorMapEntry rgb="255,92,0" transparent="false" sourceValue="[19.979078,20.083681)" value="[19.979078,20.083681)" ref="191"/>
      <ColorMapEntry rgb="255,85,0" transparent="false" sourceValue="[20.083681,20.188284)" value="[20.083681,20.188284)" ref="192"/>
      <ColorMapEntry rgb="255,78,0" transparent="false" sourceValue="[20.188284,20.292887)" value="[20.188284,20.292887)" ref="193"/>
      <ColorMapEntry rgb="255,71,0" transparent="false" sourceValue="[20.292887,20.397490)" value="[20.292887,20.397490)" ref="194"/>
      <ColorMapEntry rgb="255,64,0" transparent="false" sourceValue="[20.397490,20.502092)" value="[20.397490,20.502092)" ref="195"/>
      <ColorMapEntry rgb="255,57,0" transparent="false" sourceValue="[20.502092,20.606693)" value="[20.502092,20.606693)" ref="196"/>
      <ColorMapEntry rgb="255,50,0" transparent="false" sourceValue="[20.606693,20.711296)" value="[20.606693,20.711296)" ref="197"/>
      <ColorMapEntry rgb="255,42,0" transparent="false" sourceValue="[20.711296,20.815899)" value="[20.711296,20.815899)" ref="198"/>
      <ColorMapEntry rgb="255,35,0" transparent="false" sourceValue="[20.815899,20.920502)" value="[20.815899,20.920502)" ref="199"/>
      <ColorMapEntry rgb="255,28,0" transparent="false" sourceValue="[20.920502,21.025105)" value="[20.920502,21.025105)" ref="200"/>
      <ColorMapEntry rgb="255,21,0" transparent="false" sourceValue="[21.025105,21.129707)" value="[21.025105,21.129707)" ref="201"/>
      <ColorMapEntry rgb="255,14,0" transparent="false" sourceValue="[21.129707,21.234308)" value="[21.129707,21.234308)" ref="202"/>
      <ColorMapEntry rgb="255,7,0" transparent="false" sourceValue="[21.234308,21.338911)" value="[21.234308,21.338911)" ref="203"/>
      <ColorMapEntry rgb="255,0,0" transparent="false" sourceValue="[21.338911,21.443514)" value="[21.338911,21.443514)" ref="204"/>
      <ColorMapEntry rgb="255,7,7" transparent="false" sourceValue="[21.443514,21.548117)" value="[21.443514,21.548117)" ref="205"/>
      <ColorMapEntry rgb="255,15,15" transparent="false" sourceValue="[21.548117,21.652719)" value="[21.548117,21.652719)" ref="206"/>
      <ColorMapEntry rgb="255,22,22" transparent="false" sourceValue="[21.652719,21.757322)" value="[21.652719,21.757322)" ref="207"/>
      <ColorMapEntry rgb="255,29,29" transparent="false" sourceValue="[21.757322,21.861925)" value="[21.757322,21.861925)" ref="208"/>
      <ColorMapEntry rgb="255,36,36" transparent="false" sourceValue="[21.861925,21.966526)" value="[21.861925,21.966526)" ref="209"/>
      <ColorMapEntry rgb="255,44,44" transparent="false" sourceValue="[21.966526,22.071129)" value="[21.966526,22.071129)" ref="210"/>
      <ColorMapEntry rgb="255,51,51" transparent="false" sourceValue="[22.071129,22.175732)" value="[22.071129,22.175732)" ref="211"/>
      <ColorMapEntry rgb="255,58,58" transparent="false" sourceValue="[22.175732,22.280334)" value="[22.175732,22.280334)" ref="212"/>
      <ColorMapEntry rgb="255,66,66" transparent="false" sourceValue="[22.280334,22.384937)" value="[22.280334,22.384937)" ref="213"/>
      <ColorMapEntry rgb="255,73,73" transparent="false" sourceValue="[22.384937,22.489540)" value="[22.384937,22.489540)" ref="214"/>
      <ColorMapEntry rgb="255,80,80" transparent="false" sourceValue="[22.489540,22.594141)" value="[22.489540,22.594141)" ref="215"/>
      <ColorMapEntry rgb="255,87,87" transparent="false" sourceValue="[22.594141,22.698744)" value="[22.594141,22.698744)" ref="216"/>
      <ColorMapEntry rgb="255,95,95" transparent="false" sourceValue="[22.698744,22.803347)" value="[22.698744,22.803347)" ref="217"/>
      <ColorMapEntry rgb="255,102,102" transparent="false" sourceValue="[22.803347,22.907949)" value="[22.803347,22.907949)" ref="218"/>
      <ColorMapEntry rgb="255,109,109" transparent="false" sourceValue="[22.907949,23.012552)" value="[22.907949,23.012552)" ref="219"/>
      <ColorMapEntry rgb="255,117,117" transparent="false" sourceValue="[23.012552,23.117155)" value="[23.012552,23.117155)" ref="220"/>
      <ColorMapEntry rgb="255,124,124" transparent="false" sourceValue="[23.117155,23.221756)" value="[23.117155,23.221756)" ref="221"/>
      <ColorMapEntry rgb="255,131,131" transparent="false" sourceValue="[23.221756,23.326359)" value="[23.221756,23.326359)" ref="222"/>
      <ColorMapEntry rgb="255,138,138" transparent="false" sourceValue="[23.326359,23.430962)" value="[23.326359,23.430962)" ref="223"/>
      <ColorMapEntry rgb="255,146,146" transparent="false" sourceValue="[23.430962,23.535564)" value="[23.430962,23.535564)" ref="224"/>
      <ColorMapEntry rgb="255,153,153" transparent="false" sourceValue="[23.535564,23.640167)" value="[23.535564,23.640167)" ref="225"/>
      <ColorMapEntry rgb="255,160,160" transparent="false" sourceValue="[23.640167,23.744770)" value="[23.640167,23.744770)" ref="226"/>
      <ColorMapEntry rgb="255,168,168" transparent="false" sourceValue="[23.744770,23.849371)" value="[23.744770,23.849371)" ref="227"/>
      <ColorMapEntry rgb="255,175,175" transparent="false" sourceValue="[23.849371,23.953974)" value="[23.849371,23.953974)" ref="228"/>
      <ColorMapEntry rgb="255,182,182" transparent="false" sourceValue="[23.953974,24.058577)" value="[23.953974,24.058577)" ref="229"/>
      <ColorMapEntry rgb="255,189,189" transparent="false" sourceValue="[24.058577,24.163179)" value="[24.058577,24.163179)" ref="230"/>
      <ColorMapEntry rgb="255,197,197" transparent="false" sourceValue="[24.163179,24.267782)" value="[24.163179,24.267782)" ref="231"/>
      <ColorMapEntry rgb="255,204,204" transparent="false" sourceValue="[24.267782,24.372385)" value="[24.267782,24.372385)" ref="232"/>
      <ColorMapEntry rgb="255,211,211" transparent="false" sourceValue="[24.372385,24.476988)" value="[24.372385,24.476988)" ref="233"/>
      <ColorMapEntry rgb="255,219,219" transparent="false" sourceValue="[24.476988,24.581589)" value="[24.476988,24.581589)" ref="234"/>
      <ColorMapEntry rgb="255,226,226" transparent="false" sourceValue="[24.581589,24.686192)" value="[24.581589,24.686192)" ref="235"/>
      <ColorMapEntry rgb="255,233,233" transparent="false" sourceValue="[24.686192,24.790794)" value="[24.686192,24.790794)" ref="236"/>
      <ColorMapEntry rgb="255,240,240" transparent="false" sourceValue="[24.790794,24.895397)" value="[24.790794,24.895397)" ref="237"/>
      <ColorMapEntry rgb="255,248,248" transparent="false" sourceValue="[24.895397,25.000000)" value="[24.895397,25.000000)" ref="238"/>
      <ColorMapEntry rgb="255,255,255" transparent="false" sourceValue="[25.000000,100.000000]" value="[25.000000,100.000000]" ref="239"/>
    </Entries>
    <Legend type="continuous" minLabel="0.0" maxLabel="&#8805; 25.0">
      <LegendEntry rgb="17,17,17" tooltip="0.000 – 0.105" id="0"/>
      <LegendEntry rgb="128,0,128" tooltip="0.105 – 0.209" id="1"/>
      <LegendEntry rgb="133,0,133" tooltip="0.209 – 0.314" id="2"/>
      <LegendEntry rgb="138,0,138" tooltip="0.314 – 0.418" id="3"/>
      <LegendEntry rgb="143,0,143" tooltip="0.418 – 0.523" id="4"/>
      <LegendEntry rgb="149,0,149" tooltip="0.523 – 0.628" id="5"/>
      <LegendEntry rgb="154,0,154" tooltip="0.628 – 0.732" id="6"/>
      <LegendEntry rgb="159,0,159" tooltip="0.732 – 0.837" id="7"/>
      <LegendEntry rgb="164,0,164" tooltip="0.837 – 0.941" id="8"/>
      <LegendEntry rgb="170,0,170" tooltip="0.941 – 1.046" id="9"/>
      <LegendEntry rgb="175,0,175" tooltip="1.046 – 1.151" id="10"/>
      <LegendEntry rgb="181,0,181" tooltip="1.151 – 1.255" showTick="true" id="11"/>
      <LegendEntry rgb="186,0,186" tooltip="1.255 – 1.36" id="12"/>
      <LegendEntry rgb="191,0,191" tooltip="1.36 – 1.464" id="13"/>
      <LegendEntry rgb="196,0,196" tooltip="1.464 – 1.569" id="14"/>
      <LegendEntry rgb="202,0,202" tooltip="1.569 – 1.674" id="15"/>
      <LegendEntry rgb="207,0,207" tooltip="1.674 – 1.778" id="16"/>
      <LegendEntry rgb="213,0,213" tooltip="1.778 – 1.883" id="17"/>
      <LegendEntry rgb="218,0,218" tooltip="1.883 – 1.987" id="18"/>
      <LegendEntry rgb="223,0,223" tooltip="1.987 – 2.092" id="19"/>
      <LegendEntry rgb="228,0,228" tooltip="2.092 – 2.197" id="20"/>
      <LegendEntry rgb="234,0,234" tooltip="2.197 – 2.301" id="21"/>
      <LegendEntry rgb="239,0,239" tooltip="2.301 – 2.406" id="22"/>
      <LegendEntry rgb="244,0,244" tooltip="2.406 – 2.51" showTick="true" showLabel="true" label="2.5" id="23"/>
      <LegendEntry rgb="255,0,255" tooltip="2.51 – 2.615" id="24"/>
      <LegendEntry rgb="248,0,255" tooltip="2.615 – 2.72" id="25"/>
      <LegendEntry rgb="241,0,255" tooltip="2.72 – 2.824" id="26"/>
      <LegendEntry rgb="234,0,255" tooltip="2.824 – 2.929" id="27"/>
      <LegendEntry rgb="227,0,255" tooltip="2.929 – 3.033" id="28"/>
      <LegendEntry rgb="220,0,255" tooltip="3.033 – 3.138" id="29"/>
      <LegendEntry rgb="212,0,255" tooltip="3.138 – 3.243" id="30"/>
      <LegendEntry rgb="205,0,255" tooltip="3.243 – 3.347" id="31"/>
      <LegendEntry rgb="198,0,255" tooltip="3.347 – 3.452" id="32"/>
      <LegendEntry rgb="191,0,255" tooltip="3.452 – 3.556" id="33"/>
      <LegendEntry rgb="184,0,255" tooltip="3.556 – 3.661" id="34"/>
      <LegendEntry rgb="177,0,255" tooltip="3.661 – 3.766" showTick="true" id="35"/>
      <LegendEntry rgb="170,0,255" tooltip="3.766 – 3.87" id="36"/>
      <LegendEntry rgb="163,0,255" tooltip="3.87 – 3.975" id="37"/>
      <LegendEntry rgb="156,0,255" tooltip="3.975 – 4.079" id="38"/>
      <LegendEntry rgb="149,0,255" tooltip="4.079 – 4.184" id="39"/>
      <LegendEntry rgb="142,0,255" tooltip="4.184 – 4.289" id="40"/>
      <LegendEntry rgb="135,0,255" tooltip="4.289 – 4.393" id="41"/>
      <LegendEntry rgb="127,0,255" tooltip="4.393 – 4.498" id="42"/>
      <LegendEntry rgb="120,0,255" tooltip="4.498 – 4.603" id="43"/>
      <LegendEntry rgb="113,0,255" tooltip="4.603 – 4.707" id="44"/>
      <LegendEntry rgb="106,0,255" tooltip="4.707 – 4.812" id="45"/>
      <LegendEntry rgb="99,0,255" tooltip="4.812 – 4.916" id="46"/>
      <LegendEntry rgb="92,0,255" tooltip="4.916 – 5.021" showTick="true" showLabel="true" label="5.0" id="47"/>
      <LegendEntry rgb="85,0,255" tooltip="5.021 – 5.126" id="48"/>
      <LegendEntry rgb="78,0,255" tooltip="5.126 – 5.23" id="49"/>
      <LegendEntry rgb="71,0,255" tooltip="5.23 – 5.335" id="50"/>
      <LegendEntry rgb="64,0,255" tooltip="5.335 – 5.439" id="51"/>
      <LegendEntry rgb="57,0,255" tooltip="5.439 – 5.544" id="52"/>
      <LegendEntry rgb="50,0,255" tooltip="5.544 – 5.649" id="53"/>
      <LegendEntry rgb="42,0,255" tooltip="5.649 – 5.753" id="54"/>
      <LegendEntry rgb="35,0,255" tooltip="5.753 – 5.858" id="55"/>
      <LegendEntry rgb="28,0,255" tooltip="5.858 – 5.962" id="56"/>
      <LegendEntry rgb="21,0,255" tooltip="5.962 – 6.067" id="57"/>
      <LegendEntry rgb="14,0,255" tooltip="6.067 – 6.172" id="58"/>
      <LegendEntry rgb="7,0,255" tooltip="6.172 – 6.276" showTick="true" id="59"/>
      <LegendEntry rgb="0,0,255" tooltip="6.276 – 6.381" id="60"/>
      <LegendEntry rgb="0,7,255" tooltip="6.381 – 6.485" id="61"/>
      <LegendEntry rgb="0,14,255" tooltip="6.485 – 6.59" id="62"/>
      <LegendEntry rgb="0,21,255" tooltip="6.59 – 6.695" id="63"/>
      <LegendEntry rgb="0,28,255" tooltip="6.695 – 6.799" id="64"/>
      <LegendEntry rgb="0,35,255" tooltip="6.799 – 6.904" id="65"/>
      <LegendEntry rgb="0,43,255" tooltip="6.904 – 7.008" id="66"/>
      <LegendEntry rgb="0,50,255" tooltip="7.008 – 7.113" id="67"/>
      <LegendEntry rgb="0,57,255" tooltip="7.113 – 7.218" id="68"/>
      <LegendEntry rgb="0,64,255" tooltip="7.218 – 7.322" id="69"/>
      <LegendEntry rgb="0,71,255" tooltip="7.322 – 7.427" id="70"/>
      <LegendEntry rgb="0,78,255" tooltip="7.427 – 7.531" showTick="true" showLabel="true" label="7.5" id="71"/>
      <LegendEntry rgb="0,85,255" tooltip="7.531 – 7.636" id="72"/>
      <LegendEntry rgb="0,92,255" tooltip="7.636 – 7.741" id="73"/>
      <LegendEntry rgb="0,99,255" tooltip="7.741 – 7.845" id="74"/>
      <LegendEntry rgb="0,106,255" tooltip="7.845 – 7.95" id="75"/>
      <LegendEntry rgb="0,113,255" tooltip="7.95 – 8.054" id="76"/>
      <LegendEntry rgb="0,120,255" tooltip="8.054 – 8.159" id="77"/>
      <LegendEntry rgb="0,128,255" tooltip="8.159 – 8.264" id="78"/>
      <LegendEntry rgb="0,135,255" tooltip="8.264 – 8.368" id="79"/>
      <LegendEntry rgb="0,142,255" tooltip="8.368 – 8.473" id="80"/>
      <LegendEntry rgb="0,149,255" tooltip="8.473 – 8.577" id="81"/>
      <LegendEntry rgb="0,156,255" tooltip="8.577 – 8.682" id="82"/>
      <LegendEntry rgb="0,163,255" tooltip="8.682 – 8.787" showTick="true" id="83"/>
      <LegendEntry rgb="0,170,255" tooltip="8.787 – 8.891" id="84"/>
      <LegendEntry rgb="0,177,255" tooltip="8.891 – 8.996" id="85"/>
      <LegendEntry rgb="0,184,255" tooltip="8.996 – 9.1" id="86"/>
      <LegendEntry rgb="0,191,255" tooltip="9.1 – 9.205" id="87"/>
      <LegendEntry rgb="0,198,255" tooltip="9.205 – 9.31" id="88"/>
      <LegendEntry rgb="0,205,255" tooltip="9.31 – 9.414" id="89"/>
      <LegendEntry rgb="0,213,255" tooltip="9.414 – 9.519" id="90"/>
      <LegendEntry rgb="0,220,255" tooltip="9.519 – 9.623" id="91"/>
      <LegendEntry rgb="0,227,255" tooltip="9.623 – 9.728" id="92"/>
      <LegendEntry rgb="0,234,255" tooltip="9.728 – 9.833" id="93"/>
      <LegendEntry rgb="0,241,255" tooltip="9.833 – 9.937" id="94"/>
      <LegendEntry rgb="0,248,255" tooltip="9.937 – 10.042" showTick="true" showLabel="true" label="10.0" id="95"/>
      <LegendEntry rgb="0,255,255" tooltip="10.042 – 10.146" id="96"/>
      <LegendEntry rgb="0,253,248" tooltip="10.146 – 10.251" id="97"/>
      <LegendEntry rgb="0,250,241" tooltip="10.251 – 10.356" id="98"/>
      <LegendEntry rgb="0,248,234" tooltip="10.356 – 10.46" id="99"/>
      <LegendEntry rgb="0,246,227" tooltip="10.46 – 10.565" id="100"/>
      <LegendEntry rgb="0,243,220" tooltip="10.565 – 10.669" id="101"/>
      <LegendEntry rgb="0,241,212" tooltip="10.669 – 10.774" id="102"/>
      <LegendEntry rgb="0,238,205" tooltip="10.774 – 10.879" id="103"/>
      <LegendEntry rgb="0,236,198" tooltip="10.879 – 10.983" id="104"/>
      <LegendEntry rgb="0,234,191" tooltip="10.983 – 11.088" id="105"/>
      <LegendEntry rgb="0,231,184" tooltip="11.088 – 11.192" id="106"/>
      <LegendEntry rgb="0,229,177" tooltip="11.192 – 11.297" showTick="true" id="107"/>
      <LegendEntry rgb="0,227,170" tooltip="11.297 – 11.402" id="108"/>
      <LegendEntry rgb="0,224,163" tooltip="11.402 – 11.506" id="109"/>
      <LegendEntry rgb="0,222,156" tooltip="11.506 – 11.611" id="110"/>
      <LegendEntry rgb="0,220,149" tooltip="11.611 – 11.715" id="111"/>
      <LegendEntry rgb="0,217,142" tooltip="11.715 – 11.82" id="112"/>
      <LegendEntry rgb="0,215,135" tooltip="11.82 – 11.925" id="113"/>
      <LegendEntry rgb="0,212,127" tooltip="11.925 – 12.029" id="114"/>
      <LegendEntry rgb="0,210,120" tooltip="12.029 – 12.134" id="115"/>
      <LegendEntry rgb="0,208,113" tooltip="12.134 – 12.238" id="116"/>
      <LegendEntry rgb="0,205,106" tooltip="12.238 – 12.343" id="117"/>
      <LegendEntry rgb="0,203,99" tooltip="12.343 – 12.448" id="118"/>
      <LegendEntry rgb="0,201,92" tooltip="12.448 – 12.552" showTick="true" showLabel="true" label="12.5" id="119"/>
      <LegendEntry rgb="0,198,85" tooltip="12.552 – 12.657" id="120"/>
      <LegendEntry rgb="0,196,78" tooltip="12.657 – 12.762" id="121"/>
      <LegendEntry rgb="0,194,71" tooltip="12.762 – 12.866" id="122"/>
      <LegendEntry rgb="0,191,64" tooltip="12.866 – 12.971" id="123"/>
      <LegendEntry rgb="0,189,57" tooltip="12.971 – 13.075" id="124"/>
      <LegendEntry rgb="0,187,50" tooltip="13.075 – 13.18" id="125"/>
      <LegendEntry rgb="0,184,42" tooltip="13.18 – 13.285" id="126"/>
      <LegendEntry rgb="0,182,35" tooltip="13.285 – 13.389" id="127"/>
      <LegendEntry rgb="0,179,28" tooltip="13.389 – 13.494" id="128"/>
      <LegendEntry rgb="0,177,21" tooltip="13.494 – 13.598" id="129"/>
      <LegendEntry rgb="0,175,14" tooltip="13.598 – 13.703" id="130"/>
      <LegendEntry rgb="0,172,7" tooltip="13.703 – 13.808" showTick="true" id="131"/>
      <LegendEntry rgb="0,170,0" tooltip="13.808 – 13.912" id="132"/>
      <LegendEntry rgb="7,172,0" tooltip="13.912 – 14.017" id="133"/>
      <LegendEntry rgb="14,175,0" tooltip="14.017 – 14.121" id="134"/>
      <LegendEntry rgb="21,177,0" tooltip="14.121 – 14.226" id="135"/>
      <LegendEntry rgb="28,179,0" tooltip="14.226 – 14.331" id="136"/>
      <LegendEntry rgb="35,182,0" tooltip="14.331 – 14.435" id="137"/>
      <LegendEntry rgb="43,184,0" tooltip="14.435 – 14.54" id="138"/>
      <LegendEntry rgb="50,187,0" tooltip="14.54 – 14.644" id="139"/>
      <LegendEntry rgb="57,189,0" tooltip="14.644 – 14.749" id="140"/>
      <LegendEntry rgb="64,191,0" tooltip="14.749 – 14.854" id="141"/>
      <LegendEntry rgb="71,194,0" tooltip="14.854 – 14.958" id="142"/>
      <LegendEntry rgb="78,196,0" tooltip="14.958 – 15.063" showTick="true" showLabel="true" label="15.0" id="143"/>
      <LegendEntry rgb="85,198,0" tooltip="15.063 – 15.167" id="144"/>
      <LegendEntry rgb="92,201,0" tooltip="15.167 – 15.272" id="145"/>
      <LegendEntry rgb="99,203,0" tooltip="15.272 – 15.377" id="146"/>
      <LegendEntry rgb="106,205,0" tooltip="15.377 – 15.481" id="147"/>
      <LegendEntry rgb="113,208,0" tooltip="15.481 – 15.586" id="148"/>
      <LegendEntry rgb="120,210,0" tooltip="15.586 – 15.69" id="149"/>
      <LegendEntry rgb="128,213,0" tooltip="15.69 – 15.795" id="150"/>
      <LegendEntry rgb="135,215,0" tooltip="15.795 – 15.9" id="151"/>
      <LegendEntry rgb="142,217,0" tooltip="15.9 – 16.004" id="152"/>
      <LegendEntry rgb="149,220,0" tooltip="16.004 – 16.109" id="153"/>
      <LegendEntry rgb="156,222,0" tooltip="16.109 – 16.213" id="154"/>
      <LegendEntry rgb="163,224,0" tooltip="16.213 – 16.318" showTick="true" id="155"/>
      <LegendEntry rgb="170,227,0" tooltip="16.318 – 16.423" id="156"/>
      <LegendEntry rgb="177,229,0" tooltip="16.423 – 16.527" id="157"/>
      <LegendEntry rgb="184,231,0" tooltip="16.527 – 16.632" id="158"/>
      <LegendEntry rgb="191,234,0" tooltip="16.632 – 16.736" id="159"/>
      <LegendEntry rgb="198,236,0" tooltip="16.736 – 16.841" id="160"/>
      <LegendEntry rgb="205,238,0" tooltip="16.841 – 16.946" id="161"/>
      <LegendEntry rgb="213,241,0" tooltip="16.946 – 17.05" id="162"/>
      <LegendEntry rgb="220,243,0" tooltip="17.05 – 17.155" id="163"/>
      <LegendEntry rgb="227,246,0" tooltip="17.155 – 17.259" id="164"/>
      <LegendEntry rgb="234,248,0" tooltip="17.259 – 17.364" id="165"/>
      <LegendEntry rgb="241,250,0" tooltip="17.364 – 17.469" id="166"/>
      <LegendEntry rgb="248,253,0" tooltip="17.469 – 17.573" showTick="true" showLabel="true" label="17.5" id="167"/>
      <LegendEntry rgb="255,255,0" tooltip="17.573 – 17.678" id="168"/>
      <LegendEntry rgb="255,248,0" tooltip="17.678 – 17.782" id="169"/>
      <LegendEntry rgb="255,241,0" tooltip="17.782 – 17.887" id="170"/>
      <LegendEntry rgb="255,234,0" tooltip="17.887 – 17.992" id="171"/>
      <LegendEntry rgb="255,227,0" tooltip="17.992 – 18.096" id="172"/>
      <LegendEntry rgb="255,220,0" tooltip="18.096 – 18.201" id="173"/>
      <LegendEntry rgb="255,212,0" tooltip="18.201 – 18.305" id="174"/>
      <LegendEntry rgb="255,205,0" tooltip="18.305 – 18.41" id="175"/>
      <LegendEntry rgb="255,198,0" tooltip="18.41 – 18.515" id="176"/>
      <LegendEntry rgb="255,191,0" tooltip="18.515 – 18.619" id="177"/>
      <LegendEntry rgb="255,184,0" tooltip="18.619 – 18.724" id="178"/>
      <LegendEntry rgb="255,177,0" tooltip="18.724 – 18.828" showTick="true" id="179"/>
      <LegendEntry rgb="255,170,0" tooltip="18.828 – 18.933" id="180"/>
      <LegendEntry rgb="255,163,0" tooltip="18.933 – 19.038" id="181"/>
      <LegendEntry rgb="255,156,0" tooltip="19.038 – 19.142" id="182"/>
      <LegendEntry rgb="255,149,0" tooltip="19.142 – 19.247" id="183"/>
      <LegendEntry rgb="255,142,0" tooltip="19.247 – 19.351" id="184"/>
      <LegendEntry rgb="255,135,0" tooltip="19.351 – 19.456" id="185"/>
      <LegendEntry rgb="255,127,0" tooltip="19.456 – 19.561" id="186"/>
      <LegendEntry rgb="255,120,0" tooltip="19.561 – 19.665" id="187"/>
      <LegendEntry rgb="255,113,0" tooltip="19.665 – 19.77" id="188"/>
      <LegendEntry rgb="255,106,0" tooltip="19.77 – 19.874" id="189"/>
      <LegendEntry rgb="255,99,0" tooltip="19.874 – 19.979" id="190"/>
      <LegendEntry rgb="255,92,0" tooltip="19.979 – 20.084" showTick="true" showLabel="true" label="20.0" id="191"/>
      <LegendEntry rgb="255,85,0" tooltip="20.084 – 20.188" id="192"/>
      <LegendEntry rgb="255,78,0" tooltip="20.188 – 20.293" id="193"/>
      <LegendEntry rgb="255,71,0" tooltip="20.293 – 20.397" id="194"/>
      <LegendEntry rgb="255,64,0" tooltip="20.397 – 20.502" id="195"/>
      <LegendEntry rgb="255,57,0" tooltip="20.502 – 20.607" id="196"/>
      <LegendEntry rgb="255,50,0" tooltip="20.607 – 20.711" id="197"/>
      <LegendEntry rgb="255,42,0" tooltip="20.711 – 20.816" id="198"/>
      <LegendEntry rgb="255,35,0" tooltip="20.816 – 20.921" id="199"/>
      <LegendEntry rgb="255,28,0" tooltip="20.921 – 21.025" id="200"/>
      <LegendEntry rgb="255,21,0" tooltip="21.025 – 21.13" id="201"/>
      <LegendEntry rgb="255,14,0" tooltip="21.13 – 21.234" id="202"/>
      <LegendEntry rgb="255,7,0" tooltip="21.234 – 21.339" showTick="true" id="203"/>
      <LegendEntry rgb="255,0,0" tooltip="21.339 – 21.444" id="204"/>
      <LegendEntry rgb="255,7,7" tooltip="21.444 – 21.548" id="205"/>
      <LegendEntry rgb="255,15,15" tooltip="21.548 – 21.653" id="206"/>
      <LegendEntry rgb="255,22,22" tooltip="21.653 – 21.757" id="207"/>
      <LegendEntry rgb="255,29,29" tooltip="21.757 – 21.862" id="208"/>
      <LegendEntry rgb="255,36,36" tooltip="21.862 – 21.967" id="209"/>
      <LegendEntry rgb="255,44,44" tooltip="21.967 – 22.071" id="210"/>
      <LegendEntry rgb="255,51,51" tooltip="22.071 – 22.176" id="211"/>
      <LegendEntry rgb="255,58,58" tooltip="22.176 – 22.28" id="212"/>
      <LegendEntry rgb="255,66,66" tooltip="22.28 – 22.385" id="213"/>
      <LegendEntry rgb="255,73,73" tooltip="22.385 – 22.49" id="214"/>
      <LegendEntry rgb="255,80,80" tooltip="22.49 – 22.594" showTick="true" showLabel="true" label="22.5" id="215"/>
      <LegendEntry rgb="255,87,87" tooltip="22.594 – 22.699" id="216"/>
      <LegendEntry rgb="255,95,95" tooltip="22.699 – 22.803" id="217"/>
      <LegendEntry rgb="255,102,102" tooltip="22.803 – 22.908" id="218"/>
      <LegendEntry rgb="255,109,109" tooltip="22.908 – 23.013" id="219"/>
      <LegendEntry rgb="255,117,117" tooltip="23.013 – 23.117" id="220"/>
      <LegendEntry rgb="255,124,124" tooltip="23.117 – 23.222" id="221"/>
      <LegendEntry rgb="255,131,131" tooltip="23.222 – 23.326" id="222"/>
      <LegendEntry rgb="255,138,138" tooltip="23.326 – 23.431" id="223"/>
      <LegendEntry rgb="255,146,146" tooltip="23.431 – 23.536" id="224"/>
      <LegendEntry rgb="255,153,153" tooltip="23.536 – 23.64" id="225"/>
      <LegendEntry rgb="255,160,160" tooltip="23.64 – 23.745" id="226"/>
      <LegendEntry rgb="255,168,168" tooltip="23.745 – 23.849" showTick="true" id="227"/>
      <LegendEntry rgb="255,175,175" tooltip="23.849 – 23.954" id="228"/>
      <LegendEntry rgb="255,182,182" tooltip="23.954 – 24.059" id="229"/>
      <LegendEntry rgb="255,189,189" tooltip="24.059 – 24.163" id="230"/>
      <LegendEntry rgb="255,197,197" tooltip="24.163 – 24.268" id="231"/>
      <LegendEntry rgb="255,204,204" tooltip="24.268 – 24.372" id="232"/>
      <LegendEntry rgb="255,211,211" tooltip="24.372 – 24.477" id="233"/>
      <LegendEntry rgb="255,219,219" tooltip="24.477 – 24.582" id="234"/>
      <LegendEntry rgb="255,226,226" tooltip="24.582 – 24.686" id="235"/>
      <LegendEntry rgb="255,233,233" tooltip="24.686 – 24.791" id="236"/>
      <LegendEntry rgb="255,240,240" tooltip="24.791 – 24.895" id="237"/>
      <LegendEntry rgb="255,248,248" tooltip="24.895 – 25.000" id="238"/>
      <LegendEntry rgb="255,255,255" tooltip="&#8805; 25.000" id="239"/>
    </Legend>
  </ColorMap>
  <ColorMap title="No Data">
    <Entries>
      <ColorMapEntry rgb="0,0,0" transparent="true" nodata="true" ref="240"/>
    </Entries>
    <Legend type="classification">
      <LegendEntry rgb="0,0,0" tooltip="Fill" id="240"/>
    </Legend>
  </ColorMap>
</ColorMaps>
