<?xml version="1.0" encoding="UTF-8"?>
<ColorMaps xmlns:xsi="http://www.w3.org/2001/XMLSchema-instance"
          xsi:noNamespaceSchemaLocation="http://gibs.earthdata.nasa.gov/schemas/ColorMap_v1.3.xsd">
  <ColorMap title="No Data">
    <Entries>
      <ColorMapEntry rgb="0,0,0" transparent="true" sourceValue="[-9999]" value="[-9999]" nodata="true" ref="0"/>
    </Entries>
    <Legend type="classification">
      <LegendEntry rgb="0,0,0" tooltip="No Data" id="0"/>
    </Legend>
  </ColorMap>
  <ColorMap title="Net Ecosystem CO2 Exchange" units="gC/m²d">
    <Entries>
      <ColorMapEntry rgb="0,51,119" transparent="false" sourceValue="(-INF,-2.000)" value="(-INF,-2.000)" ref="1"/>
      <ColorMapEntry rgb="0,51,111" transparent="false" sourceValue="[-2.000,-1.984)" value="[-2.000,-1.984)" ref="2"/>
      <ColorMapEntry rgb="0,51,103" transparent="false" sourceValue="[-1.984,-1.969)" value="[-1.984,-1.969)" ref="3"/>
      <ColorMapEntry rgb="0,51,95" transparent="false" sourceValue="[-1.969,-1.953)" value="[-1.969,-1.953)" ref="4"/>
      <ColorMapEntry rgb="0,51,87" transparent="false" sourceValue="[-1.953,-1.937)" value="[-1.953,-1.937)" ref="5"/>
      <ColorMapEntry rgb="0,51,79" transparent="false" sourceValue="[-1.937,-1.921)" value="[-1.937,-1.921)" ref="6"/>
      <ColorMapEntry rgb="0,51,71" transparent="false" sourceValue="[-1.921,-1.905)" value="[-1.921,-1.905)" ref="7"/>
      <ColorMapEntry rgb="0,51,63" transparent="false" sourceValue="[-1.905,-1.890)" value="[-1.905,-1.890)" ref="8"/>
      <ColorMapEntry rgb="0,51,55" transparent="false" sourceValue="[-1.890,-1.874)" value="[-1.890,-1.874)" ref="9"/>
      <ColorMapEntry rgb="0,51,47" transparent="false" sourceValue="[-1.874,-1.858)" value="[-1.874,-1.858)" ref="10"/>
      <ColorMapEntry rgb="0,51,39" transparent="false" sourceValue="[-1.858,-1.842)" value="[-1.858,-1.842)" ref="11"/>
      <ColorMapEntry rgb="0,51,31" transparent="false" sourceValue="[-1.842,-1.826)" value="[-1.842,-1.826)" ref="12"/>
      <ColorMapEntry rgb="0,52,26" transparent="false" sourceValue="[-1.826,-1.810)" value="[-1.826,-1.810)" ref="13"/>
      <ColorMapEntry rgb="0,56,32" transparent="false" sourceValue="[-1.810,-1.795)" value="[-1.810,-1.795)" ref="14"/>
      <ColorMapEntry rgb="0,60,37" transparent="false" sourceValue="[-1.795,-1.779)" value="[-1.795,-1.779)" ref="15"/>
      <ColorMapEntry rgb="0,64,42" transparent="false" sourceValue="[-1.779,-1.763)" value="[-1.779,-1.763)" ref="16"/>
      <ColorMapEntry rgb="0,68,48" transparent="false" sourceValue="[-1.763,-1.747)" value="[-1.763,-1.747)" ref="17"/>
      <ColorMapEntry rgb="0,72,53" transparent="false" sourceValue="[-1.747,-1.731)" value="[-1.747,-1.731)" ref="18"/>
      <ColorMapEntry rgb="0,76,58" transparent="false" sourceValue="[-1.731,-1.716)" value="[-1.731,-1.716)" ref="19"/>
      <ColorMapEntry rgb="0,80,64" transparent="false" sourceValue="[-1.716,-1.700)" value="[-1.716,-1.700)" ref="20"/>
      <ColorMapEntry rgb="0,84,69" transparent="false" sourceValue="[-1.700,-1.684)" value="[-1.700,-1.684)" ref="21"/>
      <ColorMapEntry rgb="0,88,74" transparent="false" sourceValue="[-1.684,-1.668)" value="[-1.684,-1.668)" ref="22"/>
      <ColorMapEntry rgb="0,92,80" transparent="false" sourceValue="[-1.668,-1.652)" value="[-1.668,-1.652)" ref="23"/>
      <ColorMapEntry rgb="0,96,85" transparent="false" sourceValue="[-1.652,-1.637)" value="[-1.652,-1.637)" ref="24"/>
      <ColorMapEntry rgb="0,100,90" transparent="false" sourceValue="[-1.637,-1.621)" value="[-1.637,-1.621)" ref="25"/>
      <ColorMapEntry rgb="0,104,96" transparent="false" sourceValue="[-1.621,-1.605)" value="[-1.621,-1.605)" ref="26"/>
      <ColorMapEntry rgb="0,108,101" transparent="false" sourceValue="[-1.605,-1.589)" value="[-1.605,-1.589)" ref="27"/>
      <ColorMapEntry rgb="0,112,106" transparent="false" sourceValue="[-1.589,-1.573)" value="[-1.589,-1.573)" ref="28"/>
      <ColorMapEntry rgb="0,116,112" transparent="false" sourceValue="[-1.573,-1.557)" value="[-1.573,-1.557)" ref="29"/>
      <ColorMapEntry rgb="0,120,117" transparent="false" sourceValue="[-1.557,-1.542)" value="[-1.557,-1.542)" ref="30"/>
      <ColorMapEntry rgb="0,124,122" transparent="false" sourceValue="[-1.542,-1.526)" value="[-1.542,-1.526)" ref="31"/>
      <ColorMapEntry rgb="0,127,126" transparent="false" sourceValue="[-1.526,-1.510)" value="[-1.526,-1.510)" ref="32"/>
      <ColorMapEntry rgb="2,126,121" transparent="false" sourceValue="[-1.510,-1.494)" value="[-1.510,-1.494)" ref="33"/>
      <ColorMapEntry rgb="4,125,116" transparent="false" sourceValue="[-1.494,-1.478)" value="[-1.494,-1.478)" ref="34"/>
      <ColorMapEntry rgb="6,124,111" transparent="false" sourceValue="[-1.478,-1.463)" value="[-1.478,-1.463)" ref="35"/>
      <ColorMapEntry rgb="8,123,106" transparent="false" sourceValue="[-1.463,-1.447)" value="[-1.463,-1.447)" ref="36"/>
      <ColorMapEntry rgb="10,122,101" transparent="false" sourceValue="[-1.447,-1.431)" value="[-1.447,-1.431)" ref="37"/>
      <ColorMapEntry rgb="12,121,96" transparent="false" sourceValue="[-1.431,-1.415)" value="[-1.431,-1.415)" ref="38"/>
      <ColorMapEntry rgb="14,120,91" transparent="false" sourceValue="[-1.415,-1.399)" value="[-1.415,-1.399)" ref="39"/>
      <ColorMapEntry rgb="16,119,86" transparent="false" sourceValue="[-1.399,-1.384)" value="[-1.399,-1.384)" ref="40"/>
      <ColorMapEntry rgb="18,118,81" transparent="false" sourceValue="[-1.384,-1.368)" value="[-1.384,-1.368)" ref="41"/>
      <ColorMapEntry rgb="20,117,76" transparent="false" sourceValue="[-1.368,-1.352)" value="[-1.368,-1.352)" ref="42"/>
      <ColorMapEntry rgb="22,116,71" transparent="false" sourceValue="[-1.352,-1.336)" value="[-1.352,-1.336)" ref="43"/>
      <ColorMapEntry rgb="24,115,66" transparent="false" sourceValue="[-1.336,-1.320)" value="[-1.336,-1.320)" ref="44"/>
      <ColorMapEntry rgb="26,114,61" transparent="false" sourceValue="[-1.320,-1.305)" value="[-1.320,-1.305)" ref="45"/>
      <ColorMapEntry rgb="28,113,56" transparent="false" sourceValue="[-1.305,-1.289)" value="[-1.305,-1.289)" ref="46"/>
      <ColorMapEntry rgb="30,112,51" transparent="false" sourceValue="[-1.289,-1.273)" value="[-1.289,-1.273)" ref="47"/>
      <ColorMapEntry rgb="32,111,46" transparent="false" sourceValue="[-1.273,-1.257)" value="[-1.273,-1.257)" ref="48"/>
      <ColorMapEntry rgb="34,110,41" transparent="false" sourceValue="[-1.257,-1.241)" value="[-1.257,-1.241)" ref="49"/>
      <ColorMapEntry rgb="36,109,36" transparent="false" sourceValue="[-1.241,-1.225)" value="[-1.241,-1.225)" ref="50"/>
      <ColorMapEntry rgb="38,108,31" transparent="false" sourceValue="[-1.225,-1.210)" value="[-1.225,-1.210)" ref="51"/>
      <ColorMapEntry rgb="40,107,26" transparent="false" sourceValue="[-1.210,-1.194)" value="[-1.210,-1.194)" ref="52"/>
      <ColorMapEntry rgb="42,106,21" transparent="false" sourceValue="[-1.194,-1.178)" value="[-1.194,-1.178)" ref="53"/>
      <ColorMapEntry rgb="44,105,16" transparent="false" sourceValue="[-1.178,-1.162)" value="[-1.178,-1.162)" ref="54"/>
      <ColorMapEntry rgb="46,104,11" transparent="false" sourceValue="[-1.162,-1.146)" value="[-1.162,-1.146)" ref="55"/>
      <ColorMapEntry rgb="48,103,6" transparent="false" sourceValue="[-1.146,-1.131)" value="[-1.146,-1.131)" ref="56"/>
      <ColorMapEntry rgb="50,102,1" transparent="false" sourceValue="[-1.131,-1.115)" value="[-1.131,-1.115)" ref="57"/>
      <ColorMapEntry rgb="49,105,0" transparent="false" sourceValue="[-1.115,-1.099)" value="[-1.115,-1.099)" ref="58"/>
      <ColorMapEntry rgb="47,111,0" transparent="false" sourceValue="[-1.099,-1.083)" value="[-1.099,-1.083)" ref="59"/>
      <ColorMapEntry rgb="45,117,0" transparent="false" sourceValue="[-1.083,-1.067)" value="[-1.083,-1.067)" ref="60"/>
      <ColorMapEntry rgb="43,123,0" transparent="false" sourceValue="[-1.067,-1.052)" value="[-1.067,-1.052)" ref="61"/>
      <ColorMapEntry rgb="41,129,0" transparent="false" sourceValue="[-1.052,-1.036)" value="[-1.052,-1.036)" ref="62"/>
      <ColorMapEntry rgb="39,135,0" transparent="false" sourceValue="[-1.036,-1.020)" value="[-1.036,-1.020)" ref="63"/>
      <ColorMapEntry rgb="37,141,0" transparent="false" sourceValue="[-1.020,-1.004)" value="[-1.020,-1.004)" ref="64"/>
      <ColorMapEntry rgb="35,147,0" transparent="false" sourceValue="[-1.004,-0.988)" value="[-1.004,-0.988)" ref="65"/>
      <ColorMapEntry rgb="33,153,0" transparent="false" sourceValue="[-0.988,-0.972)" value="[-0.988,-0.972)" ref="66"/>
      <ColorMapEntry rgb="31,159,0" transparent="false" sourceValue="[-0.972,-0.957)" value="[-0.972,-0.957)" ref="67"/>
      <ColorMapEntry rgb="29,165,0" transparent="false" sourceValue="[-0.957,-0.941)" value="[-0.957,-0.941)" ref="68"/>
      <ColorMapEntry rgb="27,171,0" transparent="false" sourceValue="[-0.941,-0.925)" value="[-0.941,-0.925)" ref="69"/>
      <ColorMapEntry rgb="25,177,0" transparent="false" sourceValue="[-0.925,-0.909)" value="[-0.925,-0.909)" ref="70"/>
      <ColorMapEntry rgb="23,183,0" transparent="false" sourceValue="[-0.909,-0.893)" value="[-0.909,-0.893)" ref="71"/>
      <ColorMapEntry rgb="21,189,0" transparent="false" sourceValue="[-0.893,-0.878)" value="[-0.893,-0.878)" ref="72"/>
      <ColorMapEntry rgb="19,195,0" transparent="false" sourceValue="[-0.878,-0.862)" value="[-0.878,-0.862)" ref="73"/>
      <ColorMapEntry rgb="17,201,0" transparent="false" sourceValue="[-0.862,-0.846)" value="[-0.862,-0.846)" ref="74"/>
      <ColorMapEntry rgb="15,207,0" transparent="false" sourceValue="[-0.846,-0.830)" value="[-0.846,-0.830)" ref="75"/>
      <ColorMapEntry rgb="13,213,0" transparent="false" sourceValue="[-0.830,-0.814)" value="[-0.830,-0.814)" ref="76"/>
      <ColorMapEntry rgb="11,219,0" transparent="false" sourceValue="[-0.814,-0.799)" value="[-0.814,-0.799)" ref="77"/>
      <ColorMapEntry rgb="9,225,0" transparent="false" sourceValue="[-0.799,-0.783)" value="[-0.799,-0.783)" ref="78"/>
      <ColorMapEntry rgb="7,231,0" transparent="false" sourceValue="[-0.783,-0.767)" value="[-0.783,-0.767)" ref="79"/>
      <ColorMapEntry rgb="5,237,0" transparent="false" sourceValue="[-0.767,-0.751)" value="[-0.767,-0.751)" ref="80"/>
      <ColorMapEntry rgb="3,243,0" transparent="false" sourceValue="[-0.751,-0.735)" value="[-0.751,-0.735)" ref="81"/>
      <ColorMapEntry rgb="1,249,0" transparent="false" sourceValue="[-0.735,-0.719)" value="[-0.735,-0.719)" ref="82"/>
      <ColorMapEntry rgb="1,254,0" transparent="false" sourceValue="[-0.719,-0.704)" value="[-0.719,-0.704)" ref="83"/>
      <ColorMapEntry rgb="10,253,0" transparent="false" sourceValue="[-0.704,-0.688)" value="[-0.704,-0.688)" ref="84"/>
      <ColorMapEntry rgb="19,252,0" transparent="false" sourceValue="[-0.688,-0.672)" value="[-0.688,-0.672)" ref="85"/>
      <ColorMapEntry rgb="28,251,0" transparent="false" sourceValue="[-0.672,-0.656)" value="[-0.672,-0.656)" ref="86"/>
      <ColorMapEntry rgb="37,250,0" transparent="false" sourceValue="[-0.656,-0.640)" value="[-0.656,-0.640)" ref="87"/>
      <ColorMapEntry rgb="46,249,0" transparent="false" sourceValue="[-0.640,-0.625)" value="[-0.640,-0.625)" ref="88"/>
      <ColorMapEntry rgb="55,248,0" transparent="false" sourceValue="[-0.625,-0.609)" value="[-0.625,-0.609)" ref="89"/>
      <ColorMapEntry rgb="64,247,0" transparent="false" sourceValue="[-0.609,-0.593)" value="[-0.609,-0.593)" ref="90"/>
      <ColorMapEntry rgb="73,246,0" transparent="false" sourceValue="[-0.593,-0.577)" value="[-0.593,-0.577)" ref="91"/>
      <ColorMapEntry rgb="82,245,0" transparent="false" sourceValue="[-0.577,-0.561)" value="[-0.577,-0.561)" ref="92"/>
      <ColorMapEntry rgb="91,244,0" transparent="false" sourceValue="[-0.561,-0.546)" value="[-0.561,-0.546)" ref="93"/>
      <ColorMapEntry rgb="100,243,0" transparent="false" sourceValue="[-0.546,-0.530)" value="[-0.546,-0.530)" ref="94"/>
      <ColorMapEntry rgb="109,242,0" transparent="false" sourceValue="[-0.530,-0.514)" value="[-0.530,-0.514)" ref="95"/>
      <ColorMapEntry rgb="118,241,0" transparent="false" sourceValue="[-0.514,-0.498)" value="[-0.514,-0.498)" ref="96"/>
      <ColorMapEntry rgb="127,240,0" transparent="false" sourceValue="[-0.498,-0.482)" value="[-0.498,-0.482)" ref="97"/>
      <ColorMapEntry rgb="136,239,0" transparent="false" sourceValue="[-0.482,-0.467)" value="[-0.482,-0.467)" ref="98"/>
      <ColorMapEntry rgb="145,238,0" transparent="false" sourceValue="[-0.467,-0.451)" value="[-0.467,-0.451)" ref="99"/>
      <ColorMapEntry rgb="154,237,0" transparent="false" sourceValue="[-0.451,-0.435)" value="[-0.451,-0.435)" ref="100"/>
      <ColorMapEntry rgb="163,236,0" transparent="false" sourceValue="[-0.435,-0.419)" value="[-0.435,-0.419)" ref="101"/>
      <ColorMapEntry rgb="172,235,0" transparent="false" sourceValue="[-0.419,-0.403)" value="[-0.419,-0.403)" ref="102"/>
      <ColorMapEntry rgb="181,234,0" transparent="false" sourceValue="[-0.403,-0.387)" value="[-0.403,-0.387)" ref="103"/>
      <ColorMapEntry rgb="190,233,0" transparent="false" sourceValue="[-0.387,-0.372)" value="[-0.387,-0.372)" ref="104"/>
      <ColorMapEntry rgb="199,232,0" transparent="false" sourceValue="[-0.372,-0.356)" value="[-0.372,-0.356)" ref="105"/>
      <ColorMapEntry rgb="208,231,0" transparent="false" sourceValue="[-0.356,-0.340)" value="[-0.356,-0.340)" ref="106"/>
      <ColorMapEntry rgb="217,230,0" transparent="false" sourceValue="[-0.340,-0.324)" value="[-0.340,-0.324)" ref="107"/>
      <ColorMapEntry rgb="226,229,0" transparent="false" sourceValue="[-0.324,-0.308)" value="[-0.324,-0.308)" ref="108"/>
      <ColorMapEntry rgb="230,230,5" transparent="false" sourceValue="[-0.308,-0.293)" value="[-0.308,-0.293)" ref="109"/>
      <ColorMapEntry rgb="231,231,15" transparent="false" sourceValue="[-0.293,-0.277)" value="[-0.293,-0.277)" ref="110"/>
      <ColorMapEntry rgb="233,233,24" transparent="false" sourceValue="[-0.277,-0.261)" value="[-0.277,-0.261)" ref="111"/>
      <ColorMapEntry rgb="234,234,33" transparent="false" sourceValue="[-0.261,-0.245)" value="[-0.261,-0.245)" ref="112"/>
      <ColorMapEntry rgb="235,235,43" transparent="false" sourceValue="[-0.245,-0.229)" value="[-0.245,-0.229)" ref="113"/>
      <ColorMapEntry rgb="236,236,52" transparent="false" sourceValue="[-0.229,-0.214)" value="[-0.229,-0.214)" ref="114"/>
      <ColorMapEntry rgb="238,238,61" transparent="false" sourceValue="[-0.214,-0.198)" value="[-0.214,-0.198)" ref="115"/>
      <ColorMapEntry rgb="239,239,71" transparent="false" sourceValue="[-0.198,-0.182)" value="[-0.198,-0.182)" ref="116"/>
      <ColorMapEntry rgb="241,241,80" transparent="false" sourceValue="[-0.182,-0.166)" value="[-0.182,-0.166)" ref="117"/>
      <ColorMapEntry rgb="242,242,89" transparent="false" sourceValue="[-0.166,-0.150)" value="[-0.166,-0.150)" ref="118"/>
      <ColorMapEntry rgb="243,243,99" transparent="false" sourceValue="[-0.150,-0.134)" value="[-0.150,-0.134)" ref="119"/>
      <ColorMapEntry rgb="245,245,108" transparent="false" sourceValue="[-0.134,-0.119)" value="[-0.134,-0.119)" ref="120"/>
      <ColorMapEntry rgb="246,246,117" transparent="false" sourceValue="[-0.119,-0.103)" value="[-0.119,-0.103)" ref="121"/>
      <ColorMapEntry rgb="247,247,127" transparent="false" sourceValue="[-0.103,-0.087)" value="[-0.103,-0.087)" ref="122"/>
      <ColorMapEntry rgb="249,249,136" transparent="false" sourceValue="[-0.087,-0.071)" value="[-0.087,-0.071)" ref="123"/>
      <ColorMapEntry rgb="250,250,145" transparent="false" sourceValue="[-0.071,-0.055)" value="[-0.071,-0.055)" ref="124"/>
      <ColorMapEntry rgb="251,251,155" transparent="false" sourceValue="[-0.055,-0.040)" value="[-0.055,-0.040)" ref="125"/>
      <ColorMapEntry rgb="253,253,164" transparent="false" sourceValue="[-0.040,-0.024)" value="[-0.040,-0.024)" ref="126"/>
      <ColorMapEntry rgb="254,254,173" transparent="false" sourceValue="[-0.024,-0.008)" value="[-0.024,-0.008)" ref="127"/>
      <ColorMapEntry rgb="255,251,174" transparent="false" sourceValue="[-0.008,0.008)" value="[-0.008,0.008)" ref="128"/>
      <ColorMapEntry rgb="255,243,166" transparent="false" sourceValue="[0.008,0.024)" value="[0.008,0.024)" ref="129"/>
      <ColorMapEntry rgb="255,235,158" transparent="false" sourceValue="[0.024,0.039)" value="[0.024,0.039)" ref="130"/>
      <ColorMapEntry rgb="255,227,150" transparent="false" sourceValue="[0.039,0.055)" value="[0.039,0.055)" ref="131"/>
      <ColorMapEntry rgb="255,219,142" transparent="false" sourceValue="[0.055,0.071)" value="[0.055,0.071)" ref="132"/>
      <ColorMapEntry rgb="255,211,134" transparent="false" sourceValue="[0.071,0.087)" value="[0.071,0.087)" ref="133"/>
      <ColorMapEntry rgb="255,203,126" transparent="false" sourceValue="[0.087,0.103)" value="[0.087,0.103)" ref="134"/>
      <ColorMapEntry rgb="255,195,118" transparent="false" sourceValue="[0.103,0.118)" value="[0.103,0.118)" ref="135"/>
      <ColorMapEntry rgb="255,187,110" transparent="false" sourceValue="[0.118,0.134)" value="[0.118,0.134)" ref="136"/>
      <ColorMapEntry rgb="255,179,102" transparent="false" sourceValue="[0.134,0.150)" value="[0.134,0.150)" ref="137"/>
      <ColorMapEntry rgb="255,171,94" transparent="false" sourceValue="[0.150,0.166)" value="[0.150,0.166)" ref="138"/>
      <ColorMapEntry rgb="255,163,86" transparent="false" sourceValue="[0.166,0.182)" value="[0.166,0.182)" ref="139"/>
      <ColorMapEntry rgb="255,155,78" transparent="false" sourceValue="[0.182,0.198)" value="[0.182,0.198)" ref="140"/>
      <ColorMapEntry rgb="255,147,73" transparent="false" sourceValue="[0.198,0.213)" value="[0.198,0.213)" ref="141"/>
      <ColorMapEntry rgb="255,139,69" transparent="false" sourceValue="[0.213,0.229)" value="[0.213,0.229)" ref="142"/>
      <ColorMapEntry rgb="255,131,65" transparent="false" sourceValue="[0.229,0.245)" value="[0.229,0.245)" ref="143"/>
      <ColorMapEntry rgb="255,122,61" transparent="false" sourceValue="[0.245,0.261)" value="[0.245,0.261)" ref="144"/>
      <ColorMapEntry rgb="255,114,57" transparent="false" sourceValue="[0.261,0.277)" value="[0.261,0.277)" ref="145"/>
      <ColorMapEntry rgb="255,106,53" transparent="false" sourceValue="[0.277,0.292)" value="[0.277,0.292)" ref="146"/>
      <ColorMapEntry rgb="255,98,49" transparent="false" sourceValue="[0.292,0.308)" value="[0.292,0.308)" ref="147"/>
      <ColorMapEntry rgb="255,91,45" transparent="false" sourceValue="[0.308,0.324)" value="[0.308,0.324)" ref="148"/>
      <ColorMapEntry rgb="255,83,41" transparent="false" sourceValue="[0.324,0.340)" value="[0.324,0.340)" ref="149"/>
      <ColorMapEntry rgb="255,75,37" transparent="false" sourceValue="[0.340,0.356)" value="[0.340,0.356)" ref="150"/>
      <ColorMapEntry rgb="255,67,33" transparent="false" sourceValue="[0.356,0.371)" value="[0.356,0.371)" ref="151"/>
      <ColorMapEntry rgb="255,58,29" transparent="false" sourceValue="[0.371,0.387)" value="[0.371,0.387)" ref="152"/>
      <ColorMapEntry rgb="255,51,25" transparent="false" sourceValue="[0.387,0.403)" value="[0.387,0.403)" ref="153"/>
      <ColorMapEntry rgb="255,43,21" transparent="false" sourceValue="[0.403,0.419)" value="[0.403,0.419)" ref="154"/>
      <ColorMapEntry rgb="255,34,17" transparent="false" sourceValue="[0.419,0.435)" value="[0.419,0.435)" ref="155"/>
      <ColorMapEntry rgb="255,27,13" transparent="false" sourceValue="[0.435,0.451)" value="[0.435,0.451)" ref="156"/>
      <ColorMapEntry rgb="255,18,9" transparent="false" sourceValue="[0.451,0.466)" value="[0.451,0.466)" ref="157"/>
      <ColorMapEntry rgb="255,10,5" transparent="false" sourceValue="[0.466,0.482)" value="[0.466,0.482)" ref="158"/>
      <ColorMapEntry rgb="255,3,1" transparent="false" sourceValue="[0.482,0.498)" value="[0.482,0.498)" ref="159"/>
      <ColorMapEntry rgb="253,0,1" transparent="false" sourceValue="[0.498,0.514)" value="[0.498,0.514)" ref="160"/>
      <ColorMapEntry rgb="250,1,4" transparent="false" sourceValue="[0.514,0.530)" value="[0.514,0.530)" ref="161"/>
      <ColorMapEntry rgb="247,2,7" transparent="false" sourceValue="[0.530,0.545)" value="[0.530,0.545)" ref="162"/>
      <ColorMapEntry rgb="244,3,10" transparent="false" sourceValue="[0.545,0.561)" value="[0.545,0.561)" ref="163"/>
      <ColorMapEntry rgb="241,4,13" transparent="false" sourceValue="[0.561,0.577)" value="[0.561,0.577)" ref="164"/>
      <ColorMapEntry rgb="238,5,16" transparent="false" sourceValue="[0.577,0.593)" value="[0.577,0.593)" ref="165"/>
      <ColorMapEntry rgb="235,6,19" transparent="false" sourceValue="[0.593,0.609)" value="[0.593,0.609)" ref="166"/>
      <ColorMapEntry rgb="232,7,22" transparent="false" sourceValue="[0.609,0.624)" value="[0.609,0.624)" ref="167"/>
      <ColorMapEntry rgb="229,8,25" transparent="false" sourceValue="[0.624,0.640)" value="[0.624,0.640)" ref="168"/>
      <ColorMapEntry rgb="226,9,28" transparent="false" sourceValue="[0.640,0.656)" value="[0.640,0.656)" ref="169"/>
      <ColorMapEntry rgb="223,10,31" transparent="false" sourceValue="[0.656,0.672)" value="[0.656,0.672)" ref="170"/>
      <ColorMapEntry rgb="220,11,34" transparent="false" sourceValue="[0.672,0.688)" value="[0.672,0.688)" ref="171"/>
      <ColorMapEntry rgb="217,12,37" transparent="false" sourceValue="[0.688,0.703)" value="[0.688,0.703)" ref="172"/>
      <ColorMapEntry rgb="214,13,40" transparent="false" sourceValue="[0.703,0.719)" value="[0.703,0.719)" ref="173"/>
      <ColorMapEntry rgb="211,14,43" transparent="false" sourceValue="[0.719,0.735)" value="[0.719,0.735)" ref="174"/>
      <ColorMapEntry rgb="208,15,46" transparent="false" sourceValue="[0.735,0.751)" value="[0.735,0.751)" ref="175"/>
      <ColorMapEntry rgb="205,16,49" transparent="false" sourceValue="[0.751,0.767)" value="[0.751,0.767)" ref="176"/>
      <ColorMapEntry rgb="202,17,52" transparent="false" sourceValue="[0.767,0.783)" value="[0.767,0.783)" ref="177"/>
      <ColorMapEntry rgb="199,18,55" transparent="false" sourceValue="[0.783,0.798)" value="[0.783,0.798)" ref="178"/>
      <ColorMapEntry rgb="196,19,58" transparent="false" sourceValue="[0.798,0.814)" value="[0.798,0.814)" ref="179"/>
      <ColorMapEntry rgb="193,20,61" transparent="false" sourceValue="[0.814,0.830)" value="[0.814,0.830)" ref="180"/>
      <ColorMapEntry rgb="190,21,64" transparent="false" sourceValue="[0.830,0.846)" value="[0.830,0.846)" ref="181"/>
      <ColorMapEntry rgb="187,22,67" transparent="false" sourceValue="[0.846,0.862)" value="[0.846,0.862)" ref="182"/>
      <ColorMapEntry rgb="184,23,70" transparent="false" sourceValue="[0.862,0.877)" value="[0.862,0.877)" ref="183"/>
      <ColorMapEntry rgb="181,24,73" transparent="false" sourceValue="[0.877,0.893)" value="[0.877,0.893)" ref="184"/>
      <ColorMapEntry rgb="178,25,76" transparent="false" sourceValue="[0.893,0.909)" value="[0.893,0.909)" ref="185"/>
      <ColorMapEntry rgb="181,25,79" transparent="false" sourceValue="[0.909,0.925)" value="[0.909,0.925)" ref="186"/>
      <ColorMapEntry rgb="184,25,82" transparent="false" sourceValue="[0.925,0.941)" value="[0.925,0.941)" ref="187"/>
      <ColorMapEntry rgb="187,25,85" transparent="false" sourceValue="[0.941,0.956)" value="[0.941,0.956)" ref="188"/>
      <ColorMapEntry rgb="190,25,88" transparent="false" sourceValue="[0.956,0.972)" value="[0.956,0.972)" ref="189"/>
      <ColorMapEntry rgb="193,25,91" transparent="false" sourceValue="[0.972,0.988)" value="[0.972,0.988)" ref="190"/>
      <ColorMapEntry rgb="196,25,94" transparent="false" sourceValue="[0.988,1.004)" value="[0.988,1.004)" ref="191"/>
      <ColorMapEntry rgb="199,25,97" transparent="false" sourceValue="[1.004,1.020)" value="[1.004,1.020)" ref="192"/>
      <ColorMapEntry rgb="202,25,100" transparent="false" sourceValue="[1.020,1.036)" value="[1.020,1.036)" ref="193"/>
      <ColorMapEntry rgb="205,25,103" transparent="false" sourceValue="[1.036,1.051)" value="[1.036,1.051)" ref="194"/>
      <ColorMapEntry rgb="208,25,106" transparent="false" sourceValue="[1.051,1.067)" value="[1.051,1.067)" ref="195"/>
      <ColorMapEntry rgb="211,25,109" transparent="false" sourceValue="[1.067,1.083)" value="[1.067,1.083)" ref="196"/>
      <ColorMapEntry rgb="214,25,112" transparent="false" sourceValue="[1.083,1.099)" value="[1.083,1.099)" ref="197"/>
      <ColorMapEntry rgb="217,25,115" transparent="false" sourceValue="[1.099,1.115)" value="[1.099,1.115)" ref="198"/>
      <ColorMapEntry rgb="220,25,118" transparent="false" sourceValue="[1.115,1.130)" value="[1.115,1.130)" ref="199"/>
      <ColorMapEntry rgb="223,25,121" transparent="false" sourceValue="[1.130,1.146)" value="[1.130,1.146)" ref="200"/>
      <ColorMapEntry rgb="226,25,124" transparent="false" sourceValue="[1.146,1.162)" value="[1.146,1.162)" ref="201"/>
      <ColorMapEntry rgb="229,25,127" transparent="false" sourceValue="[1.162,1.178)" value="[1.162,1.178)" ref="202"/>
      <ColorMapEntry rgb="232,25,130" transparent="false" sourceValue="[1.178,1.194)" value="[1.178,1.194)" ref="203"/>
      <ColorMapEntry rgb="235,25,133" transparent="false" sourceValue="[1.194,1.209)" value="[1.194,1.209)" ref="204"/>
      <ColorMapEntry rgb="238,25,136" transparent="false" sourceValue="[1.209,1.225)" value="[1.209,1.225)" ref="205"/>
      <ColorMapEntry rgb="241,25,139" transparent="false" sourceValue="[1.225,1.241)" value="[1.225,1.241)" ref="206"/>
      <ColorMapEntry rgb="244,25,142" transparent="false" sourceValue="[1.241,1.257)" value="[1.241,1.257)" ref="207"/>
      <ColorMapEntry rgb="247,25,145" transparent="false" sourceValue="[1.257,1.273)" value="[1.257,1.273)" ref="208"/>
      <ColorMapEntry rgb="250,25,148" transparent="false" sourceValue="[1.273,1.289)" value="[1.273,1.289)" ref="209"/>
      <ColorMapEntry rgb="253,25,151" transparent="false" sourceValue="[1.289,1.304)" value="[1.289,1.304)" ref="210"/>
      <ColorMapEntry rgb="250,24,151" transparent="false" sourceValue="[1.304,1.320)" value="[1.304,1.320)" ref="211"/>
      <ColorMapEntry rgb="243,23,148" transparent="false" sourceValue="[1.320,1.336)" value="[1.320,1.336)" ref="212"/>
      <ColorMapEntry rgb="236,22,145" transparent="false" sourceValue="[1.336,1.352)" value="[1.336,1.352)" ref="213"/>
      <ColorMapEntry rgb="229,21,142" transparent="false" sourceValue="[1.352,1.368)" value="[1.352,1.368)" ref="214"/>
      <ColorMapEntry rgb="222,20,139" transparent="false" sourceValue="[1.368,1.383)" value="[1.368,1.383)" ref="215"/>
      <ColorMapEntry rgb="215,19,136" transparent="false" sourceValue="[1.383,1.399)" value="[1.383,1.399)" ref="216"/>
      <ColorMapEntry rgb="208,18,133" transparent="false" sourceValue="[1.399,1.415)" value="[1.399,1.415)" ref="217"/>
      <ColorMapEntry rgb="201,17,130" transparent="false" sourceValue="[1.415,1.431)" value="[1.415,1.431)" ref="218"/>
      <ColorMapEntry rgb="194,16,127" transparent="false" sourceValue="[1.431,1.447)" value="[1.431,1.447)" ref="219"/>
      <ColorMapEntry rgb="187,15,124" transparent="false" sourceValue="[1.447,1.462)" value="[1.447,1.462)" ref="220"/>
      <ColorMapEntry rgb="180,14,121" transparent="false" sourceValue="[1.462,1.478)" value="[1.462,1.478)" ref="221"/>
      <ColorMapEntry rgb="173,13,118" transparent="false" sourceValue="[1.478,1.494)" value="[1.478,1.494)" ref="222"/>
      <ColorMapEntry rgb="166,12,115" transparent="false" sourceValue="[1.494,1.510)" value="[1.494,1.510)" ref="223"/>
      <ColorMapEntry rgb="159,11,112" transparent="false" sourceValue="[1.510,1.526)" value="[1.510,1.526)" ref="224"/>
      <ColorMapEntry rgb="152,10,109" transparent="false" sourceValue="[1.526,1.541)" value="[1.526,1.541)" ref="225"/>
      <ColorMapEntry rgb="145,9,106" transparent="false" sourceValue="[1.541,1.557)" value="[1.541,1.557)" ref="226"/>
      <ColorMapEntry rgb="138,8,103" transparent="false" sourceValue="[1.557,1.573)" value="[1.557,1.573)" ref="227"/>
      <ColorMapEntry rgb="131,7,100" transparent="false" sourceValue="[1.573,1.589)" value="[1.573,1.589)" ref="228"/>
      <ColorMapEntry rgb="124,6,97" transparent="false" sourceValue="[1.589,1.605)" value="[1.589,1.605)" ref="229"/>
      <ColorMapEntry rgb="117,5,94" transparent="false" sourceValue="[1.605,1.621)" value="[1.605,1.621)" ref="230"/>
      <ColorMapEntry rgb="110,4,91" transparent="false" sourceValue="[1.621,1.636)" value="[1.621,1.636)" ref="231"/>
      <ColorMapEntry rgb="103,3,88" transparent="false" sourceValue="[1.636,1.652)" value="[1.636,1.652)" ref="232"/>
      <ColorMapEntry rgb="96,2,85" transparent="false" sourceValue="[1.652,1.668)" value="[1.652,1.668)" ref="233"/>
      <ColorMapEntry rgb="89,1,82" transparent="false" sourceValue="[1.668,1.684)" value="[1.668,1.684)" ref="234"/>
      <ColorMapEntry rgb="82,0,79" transparent="false" sourceValue="[1.684,1.700)" value="[1.684,1.700)" ref="235"/>
      <ColorMapEntry rgb="76,0,77" transparent="false" sourceValue="[1.700,1.715)" value="[1.700,1.715)" ref="236"/>
      <ColorMapEntry rgb="77,1,85" transparent="false" sourceValue="[1.715,1.731)" value="[1.715,1.731)" ref="237"/>
      <ColorMapEntry rgb="79,2,93" transparent="false" sourceValue="[1.731,1.747)" value="[1.731,1.747)" ref="238"/>
      <ColorMapEntry rgb="80,4,101" transparent="false" sourceValue="[1.747,1.763)" value="[1.747,1.763)" ref="239"/>
      <ColorMapEntry rgb="81,5,109" transparent="false" sourceValue="[1.763,1.779)" value="[1.763,1.779)" ref="240"/>
      <ColorMapEntry rgb="83,6,117" transparent="false" sourceValue="[1.779,1.794)" value="[1.779,1.794)" ref="241"/>
      <ColorMapEntry rgb="84,8,125" transparent="false" sourceValue="[1.794,1.810)" value="[1.794,1.810)" ref="242"/>
      <ColorMapEntry rgb="86,9,133" transparent="false" sourceValue="[1.810,1.826)" value="[1.810,1.826)" ref="243"/>
      <ColorMapEntry rgb="87,10,141" transparent="false" sourceValue="[1.826,1.842)" value="[1.826,1.842)" ref="244"/>
      <ColorMapEntry rgb="88,12,149" transparent="false" sourceValue="[1.842,1.858)" value="[1.842,1.858)" ref="245"/>
      <ColorMapEntry rgb="90,13,157" transparent="false" sourceValue="[1.858,1.874)" value="[1.858,1.874)" ref="246"/>
      <ColorMapEntry rgb="91,14,165" transparent="false" sourceValue="[1.874,1.889)" value="[1.874,1.889)" ref="247"/>
      <ColorMapEntry rgb="92,16,173" transparent="false" sourceValue="[1.889,1.905)" value="[1.889,1.905)" ref="248"/>
      <ColorMapEntry rgb="94,17,181" transparent="false" sourceValue="[1.905,1.921)" value="[1.905,1.921)" ref="249"/>
      <ColorMapEntry rgb="95,18,189" transparent="false" sourceValue="[1.921,1.937)" value="[1.921,1.937)" ref="250"/>
      <ColorMapEntry rgb="96,20,197" transparent="false" sourceValue="[1.937,1.953)" value="[1.937,1.953)" ref="251"/>
      <ColorMapEntry rgb="98,21,205" transparent="false" sourceValue="[1.953,1.968)" value="[1.953,1.968)" ref="252"/>
      <ColorMapEntry rgb="99,22,213" transparent="false" sourceValue="[1.968,1.984)" value="[1.968,1.984)" ref="253"/>
      <ColorMapEntry rgb="100,24,221" transparent="false" sourceValue="[1.984,2.000)" value="[1.984,2.000)" ref="254"/>
      <ColorMapEntry rgb="102,25,229" transparent="false" sourceValue="[2.000,+INF)" value="[2.000,+INF)" ref="255"/>
    </Entries>
    <Legend type="continuous" minLabel="&lt; -2.0" maxLabel="&#8805; 2.0">
      <LegendEntry rgb="0,51,119" tooltip="&lt; -2.000" id="1"/>
      <LegendEntry rgb="0,51,111" tooltip="-2.000 – -1.984" id="2"/>
      <LegendEntry rgb="0,51,103" tooltip="-1.984 – -1.969" id="3"/>
      <LegendEntry rgb="0,51,95" tooltip="-1.969 – -1.953" id="4"/>
      <LegendEntry rgb="0,51,87" tooltip="-1.953 – -1.937" id="5"/>
      <LegendEntry rgb="0,51,79" tooltip="-1.937 – -1.921" id="6"/>
      <LegendEntry rgb="0,51,71" tooltip="-1.921 – -1.905" id="7"/>
      <LegendEntry rgb="0,51,63" tooltip="-1.905 – -1.890" id="8"/>
      <LegendEntry rgb="0,51,55" tooltip="-1.890 – -1.874" id="9"/>
      <LegendEntry rgb="0,51,47" tooltip="-1.874 – -1.858" id="10"/>
      <LegendEntry rgb="0,51,39" tooltip="-1.858 – -1.842" id="11"/>
      <LegendEntry rgb="0,51,31" tooltip="-1.842 – -1.826" id="12"/>
      <LegendEntry rgb="0,52,26" tooltip="-1.826 – -1.810" id="13"/>
      <LegendEntry rgb="0,56,32" tooltip="-1.810 – -1.795" id="14"/>
      <LegendEntry rgb="0,60,37" tooltip="-1.795 – -1.779" id="15"/>
      <LegendEntry rgb="0,64,42" tooltip="-1.779 – -1.763" id="16"/>
      <LegendEntry rgb="0,68,48" tooltip="-1.763 – -1.747" id="17"/>
      <LegendEntry rgb="0,72,53" tooltip="-1.747 – -1.731" id="18"/>
      <LegendEntry rgb="0,76,58" tooltip="-1.731 – -1.716" id="19"/>
      <LegendEntry rgb="0,80,64" tooltip="-1.716 – -1.700" id="20"/>
      <LegendEntry rgb="0,84,69" tooltip="-1.700 – -1.684" id="21"/>
      <LegendEntry rgb="0,88,74" tooltip="-1.684 – -1.668" id="22"/>
      <LegendEntry rgb="0,92,80" tooltip="-1.668 – -1.652" id="23"/>
      <LegendEntry rgb="0,96,85" tooltip="-1.652 – -1.637" id="24"/>
      <LegendEntry rgb="0,100,90" tooltip="-1.637 – -1.621" id="25"/>
      <LegendEntry rgb="0,104,96" tooltip="-1.621 – -1.605" id="26"/>
      <LegendEntry rgb="0,108,101" tooltip="-1.605 – -1.589" id="27"/>
      <LegendEntry rgb="0,112,106" tooltip="-1.589 – -1.573" id="28"/>
      <LegendEntry rgb="0,116,112" tooltip="-1.573 – -1.557" id="29"/>
      <LegendEntry rgb="0,120,117" tooltip="-1.557 – -1.542" id="30"/>
      <LegendEntry rgb="0,124,122" tooltip="-1.542 – -1.526" id="31"/>
      <LegendEntry rgb="0,127,126" tooltip="-1.526 – -1.510" id="32"/>
      <LegendEntry rgb="2,126,121" tooltip="-1.510 – -1.494" showTick="true" id="33"/>
      <LegendEntry rgb="4,125,116" tooltip="-1.494 – -1.478" id="34"/>
      <LegendEntry rgb="6,124,111" tooltip="-1.478 – -1.463" id="35"/>
      <LegendEntry rgb="8,123,106" tooltip="-1.463 – -1.447" id="36"/>
      <LegendEntry rgb="10,122,101" tooltip="-1.447 – -1.431" id="37"/>
      <LegendEntry rgb="12,121,96" tooltip="-1.431 – -1.415" id="38"/>
      <LegendEntry rgb="14,120,91" tooltip="-1.415 – -1.399" id="39"/>
      <LegendEntry rgb="16,119,86" tooltip="-1.399 – -1.384" id="40"/>
      <LegendEntry rgb="18,118,81" tooltip="-1.384 – -1.368" id="41"/>
      <LegendEntry rgb="20,117,76" tooltip="-1.368 – -1.352" id="42"/>
      <LegendEntry rgb="22,116,71" tooltip="-1.352 – -1.336" id="43"/>
      <LegendEntry rgb="24,115,66" tooltip="-1.336 – -1.320" id="44"/>
      <LegendEntry rgb="26,114,61" tooltip="-1.320 – -1.305" id="45"/>
      <LegendEntry rgb="28,113,56" tooltip="-1.305 – -1.289" id="46"/>
      <LegendEntry rgb="30,112,51" tooltip="-1.289 – -1.273" id="47"/>
      <LegendEntry rgb="32,111,46" tooltip="-1.273 – -1.257" id="48"/>
      <LegendEntry rgb="34,110,41" tooltip="-1.257 – -1.241" id="49"/>
      <LegendEntry rgb="36,109,36" tooltip="-1.241 – -1.225" id="50"/>
      <LegendEntry rgb="38,108,31" tooltip="-1.225 – -1.210" id="51"/>
      <LegendEntry rgb="40,107,26" tooltip="-1.210 – -1.194" id="52"/>
      <LegendEntry rgb="42,106,21" tooltip="-1.194 – -1.178" id="53"/>
      <LegendEntry rgb="44,105,16" tooltip="-1.178 – -1.162" id="54"/>
      <LegendEntry rgb="46,104,11" tooltip="-1.162 – -1.146" id="55"/>
      <LegendEntry rgb="48,103,6" tooltip="-1.146 – -1.131" id="56"/>
      <LegendEntry rgb="50,102,1" tooltip="-1.131 – -1.115" id="57"/>
      <LegendEntry rgb="49,105,0" tooltip="-1.115 – -1.099" id="58"/>
      <LegendEntry rgb="47,111,0" tooltip="-1.099 – -1.083" id="59"/>
      <LegendEntry rgb="45,117,0" tooltip="-1.083 – -1.067" id="60"/>
      <LegendEntry rgb="43,123,0" tooltip="-1.067 – -1.052" id="61"/>
      <LegendEntry rgb="41,129,0" tooltip="-1.052 – -1.036" id="62"/>
      <LegendEntry rgb="39,135,0" tooltip="-1.036 – -1.020" id="63"/>
      <LegendEntry rgb="37,141,0" tooltip="-1.020 – -1.004" id="64"/>
      <LegendEntry rgb="35,147,0" tooltip="-1.004 – -0.988" showTick="true" showLabel="true" label="-1.0" id="65"/>
      <LegendEntry rgb="33,153,0" tooltip="-0.988 – -0.972" id="66"/>
      <LegendEntry rgb="31,159,0" tooltip="-0.972 – -0.957" id="67"/>
      <LegendEntry rgb="29,165,0" tooltip="-0.957 – -0.941" id="68"/>
      <LegendEntry rgb="27,171,0" tooltip="-0.941 – -0.925" id="69"/>
      <LegendEntry rgb="25,177,0" tooltip="-0.925 – -0.909" id="70"/>
      <LegendEntry rgb="23,183,0" tooltip="-0.909 – -0.893" id="71"/>
      <LegendEntry rgb="21,189,0" tooltip="-0.893 – -0.878" id="72"/>
      <LegendEntry rgb="19,195,0" tooltip="-0.878 – -0.862" id="73"/>
      <LegendEntry rgb="17,201,0" tooltip="-0.862 – -0.846" id="74"/>
      <LegendEntry rgb="15,207,0" tooltip="-0.846 – -0.830" id="75"/>
      <LegendEntry rgb="13,213,0" tooltip="-0.830 – -0.814" id="76"/>
      <LegendEntry rgb="11,219,0" tooltip="-0.814 – -0.799" id="77"/>
      <LegendEntry rgb="9,225,0" tooltip="-0.799 – -0.783" id="78"/>
      <LegendEntry rgb="7,231,0" tooltip="-0.783 – -0.767" id="79"/>
      <LegendEntry rgb="5,237,0" tooltip="-0.767 – -0.751" id="80"/>
      <LegendEntry rgb="3,243,0" tooltip="-0.751 – -0.735" id="81"/>
      <LegendEntry rgb="1,249,0" tooltip="-0.735 – -0.719" id="82"/>
      <LegendEntry rgb="1,254,0" tooltip="-0.719 – -0.704" id="83"/>
      <LegendEntry rgb="10,253,0" tooltip="-0.704 – -0.688" id="84"/>
      <LegendEntry rgb="19,252,0" tooltip="-0.688 – -0.672" id="85"/>
      <LegendEntry rgb="28,251,0" tooltip="-0.672 – -0.656" id="86"/>
      <LegendEntry rgb="37,250,0" tooltip="-0.656 – -0.640" id="87"/>
      <LegendEntry rgb="46,249,0" tooltip="-0.640 – -0.625" id="88"/>
      <LegendEntry rgb="55,248,0" tooltip="-0.625 – -0.609" id="89"/>
      <LegendEntry rgb="64,247,0" tooltip="-0.609 – -0.593" id="90"/>
      <LegendEntry rgb="73,246,0" tooltip="-0.593 – -0.577" id="91"/>
      <LegendEntry rgb="82,245,0" tooltip="-0.577 – -0.561" id="92"/>
      <LegendEntry rgb="91,244,0" tooltip="-0.561 – -0.546" id="93"/>
      <LegendEntry rgb="100,243,0" tooltip="-0.546 – -0.530" id="94"/>
      <LegendEntry rgb="109,242,0" tooltip="-0.530 – -0.514" id="95"/>
      <LegendEntry rgb="118,241,0" tooltip="-0.514 – -0.498" showTick="true" id="96"/>
      <LegendEntry rgb="127,240,0" tooltip="-0.498 – -0.482" id="97"/>
      <LegendEntry rgb="136,239,0" tooltip="-0.482 – -0.467" id="98"/>
      <LegendEntry rgb="145,238,0" tooltip="-0.467 – -0.451" id="99"/>
      <LegendEntry rgb="154,237,0" tooltip="-0.451 – -0.435" id="100"/>
      <LegendEntry rgb="163,236,0" tooltip="-0.435 – -0.419" id="101"/>
      <LegendEntry rgb="172,235,0" tooltip="-0.419 – -0.403" id="102"/>
      <LegendEntry rgb="181,234,0" tooltip="-0.403 – -0.387" id="103"/>
      <LegendEntry rgb="190,233,0" tooltip="-0.387 – -0.372" id="104"/>
      <LegendEntry rgb="199,232,0" tooltip="-0.372 – -0.356" id="105"/>
      <LegendEntry rgb="208,231,0" tooltip="-0.356 – -0.340" id="106"/>
      <LegendEntry rgb="217,230,0" tooltip="-0.340 – -0.324" id="107"/>
      <LegendEntry rgb="226,229,0" tooltip="-0.324 – -0.308" id="108"/>
      <LegendEntry rgb="230,230,5" tooltip="-0.308 – -0.293" id="109"/>
      <LegendEntry rgb="231,231,15" tooltip="-0.293 – -0.277" id="110"/>
      <LegendEntry rgb="233,233,24" tooltip="-0.277 – -0.261" id="111"/>
      <LegendEntry rgb="234,234,33" tooltip="-0.261 – -0.245" id="112"/>
      <LegendEntry rgb="235,235,43" tooltip="-0.245 – -0.229" id="113"/>
      <LegendEntry rgb="236,236,52" tooltip="-0.229 – -0.214" id="114"/>
      <LegendEntry rgb="238,238,61" tooltip="-0.214 – -0.198" id="115"/>
      <LegendEntry rgb="239,239,71" tooltip="-0.198 – -0.182" id="116"/>
      <LegendEntry rgb="241,241,80" tooltip="-0.182 – -0.166" id="117"/>
      <LegendEntry rgb="242,242,89" tooltip="-0.166 – -0.150" id="118"/>
      <LegendEntry rgb="243,243,99" tooltip="-0.150 – -0.134" id="119"/>
      <LegendEntry rgb="245,245,108" tooltip="-0.134 – -0.119" id="120"/>
      <LegendEntry rgb="246,246,117" tooltip="-0.119 – -0.103" id="121"/>
      <LegendEntry rgb="247,247,127" tooltip="-0.103 – -0.087" id="122"/>
      <LegendEntry rgb="249,249,136" tooltip="-0.087 – -0.071" id="123"/>
      <LegendEntry rgb="250,250,145" tooltip="-0.071 – -0.055" id="124"/>
      <LegendEntry rgb="251,251,155" tooltip="-0.055 – -0.040" id="125"/>
      <LegendEntry rgb="253,253,164" tooltip="-0.040 – -0.024" id="126"/>
      <LegendEntry rgb="254,254,173" tooltip="-0.024 – -0.008" id="127"/>
      <LegendEntry rgb="255,251,174" tooltip="-0.008 – 0.008" showTick="true" showLabel="true" label="0.0" id="128"/>
      <LegendEntry rgb="255,243,166" tooltip="0.008 – 0.024" id="129"/>
      <LegendEntry rgb="255,235,158" tooltip="0.024 – 0.039" id="130"/>
      <LegendEntry rgb="255,227,150" tooltip="0.039 – 0.055" id="131"/>
      <LegendEntry rgb="255,219,142" tooltip="0.055 – 0.071" id="132"/>
      <LegendEntry rgb="255,211,134" tooltip="0.071 – 0.087" id="133"/>
      <LegendEntry rgb="255,203,126" tooltip="0.087 – 0.103" id="134"/>
      <LegendEntry rgb="255,195,118" tooltip="0.103 – 0.118" id="135"/>
      <LegendEntry rgb="255,187,110" tooltip="0.118 – 0.134" id="136"/>
      <LegendEntry rgb="255,179,102" tooltip="0.134 – 0.150" id="137"/>
      <LegendEntry rgb="255,171,94" tooltip="0.150 – 0.166" id="138"/>
      <LegendEntry rgb="255,163,86" tooltip="0.166 – 0.182" id="139"/>
      <LegendEntry rgb="255,155,78" tooltip="0.182 – 0.198" id="140"/>
      <LegendEntry rgb="255,147,73" tooltip="0.198 – 0.213" id="141"/>
      <LegendEntry rgb="255,139,69" tooltip="0.213 – 0.229" id="142"/>
      <LegendEntry rgb="255,131,65" tooltip="0.229 – 0.245" id="143"/>
      <LegendEntry rgb="255,122,61" tooltip="0.245 – 0.261" id="144"/>
      <LegendEntry rgb="255,114,57" tooltip="0.261 – 0.277" id="145"/>
      <LegendEntry rgb="255,106,53" tooltip="0.277 – 0.292" id="146"/>
      <LegendEntry rgb="255,98,49" tooltip="0.292 – 0.308" id="147"/>
      <LegendEntry rgb="255,91,45" tooltip="0.308 – 0.324" id="148"/>
      <LegendEntry rgb="255,83,41" tooltip="0.324 – 0.340" id="149"/>
      <LegendEntry rgb="255,75,37" tooltip="0.340 – 0.356" id="150"/>
      <LegendEntry rgb="255,67,33" tooltip="0.356 – 0.371" id="151"/>
      <LegendEntry rgb="255,58,29" tooltip="0.371 – 0.387" id="152"/>
      <LegendEntry rgb="255,51,25" tooltip="0.387 – 0.403" id="153"/>
      <LegendEntry rgb="255,43,21" tooltip="0.403 – 0.419" id="154"/>
      <LegendEntry rgb="255,34,17" tooltip="0.419 – 0.435" id="155"/>
      <LegendEntry rgb="255,27,13" tooltip="0.435 – 0.451" id="156"/>
      <LegendEntry rgb="255,18,9" tooltip="0.451 – 0.466" id="157"/>
      <LegendEntry rgb="255,10,5" tooltip="0.466 – 0.482" id="158"/>
      <LegendEntry rgb="255,3,1" tooltip="0.482 – 0.498" id="159"/>
      <LegendEntry rgb="253,0,1" tooltip="0.498 – 0.514" showTick="true" id="160"/>
      <LegendEntry rgb="250,1,4" tooltip="0.514 – 0.530" id="161"/>
      <LegendEntry rgb="247,2,7" tooltip="0.530 – 0.545" id="162"/>
      <LegendEntry rgb="244,3,10" tooltip="0.545 – 0.561" id="163"/>
      <LegendEntry rgb="241,4,13" tooltip="0.561 – 0.577" id="164"/>
      <LegendEntry rgb="238,5,16" tooltip="0.577 – 0.593" id="165"/>
      <LegendEntry rgb="235,6,19" tooltip="0.593 – 0.609" id="166"/>
      <LegendEntry rgb="232,7,22" tooltip="0.609 – 0.624" id="167"/>
      <LegendEntry rgb="229,8,25" tooltip="0.624 – 0.640" id="168"/>
      <LegendEntry rgb="226,9,28" tooltip="0.640 – 0.656" id="169"/>
      <LegendEntry rgb="223,10,31" tooltip="0.656 – 0.672" id="170"/>
      <LegendEntry rgb="220,11,34" tooltip="0.672 – 0.688" id="171"/>
      <LegendEntry rgb="217,12,37" tooltip="0.688 – 0.703" id="172"/>
      <LegendEntry rgb="214,13,40" tooltip="0.703 – 0.719" id="173"/>
      <LegendEntry rgb="211,14,43" tooltip="0.719 – 0.735" id="174"/>
      <LegendEntry rgb="208,15,46" tooltip="0.735 – 0.751" id="175"/>
      <LegendEntry rgb="205,16,49" tooltip="0.751 – 0.767" id="176"/>
      <LegendEntry rgb="202,17,52" tooltip="0.767 – 0.783" id="177"/>
      <LegendEntry rgb="199,18,55" tooltip="0.783 – 0.798" id="178"/>
      <LegendEntry rgb="196,19,58" tooltip="0.798 – 0.814" id="179"/>
      <LegendEntry rgb="193,20,61" tooltip="0.814 – 0.830" id="180"/>
      <LegendEntry rgb="190,21,64" tooltip="0.830 – 0.846" id="181"/>
      <LegendEntry rgb="187,22,67" tooltip="0.846 – 0.862" id="182"/>
      <LegendEntry rgb="184,23,70" tooltip="0.862 – 0.877" id="183"/>
      <LegendEntry rgb="181,24,73" tooltip="0.877 – 0.893" id="184"/>
      <LegendEntry rgb="178,25,76" tooltip="0.893 – 0.909" id="185"/>
      <LegendEntry rgb="181,25,79" tooltip="0.909 – 0.925" id="186"/>
      <LegendEntry rgb="184,25,82" tooltip="0.925 – 0.941" id="187"/>
      <LegendEntry rgb="187,25,85" tooltip="0.941 – 0.956" id="188"/>
      <LegendEntry rgb="190,25,88" tooltip="0.956 – 0.972" id="189"/>
      <LegendEntry rgb="193,25,91" tooltip="0.972 – 0.988" id="190"/>
      <LegendEntry rgb="196,25,94" tooltip="0.988 – 1.004" showTick="true" showLabel="true" label="1.0" id="191"/>
      <LegendEntry rgb="199,25,97" tooltip="1.004 – 1.020" id="192"/>
      <LegendEntry rgb="202,25,100" tooltip="1.020 – 1.036" id="193"/>
      <LegendEntry rgb="205,25,103" tooltip="1.036 – 1.051" id="194"/>
      <LegendEntry rgb="208,25,106" tooltip="1.051 – 1.067" id="195"/>
      <LegendEntry rgb="211,25,109" tooltip="1.067 – 1.083" id="196"/>
      <LegendEntry rgb="214,25,112" tooltip="1.083 – 1.099" id="197"/>
      <LegendEntry rgb="217,25,115" tooltip="1.099 – 1.115" id="198"/>
      <LegendEntry rgb="220,25,118" tooltip="1.115 – 1.130" id="199"/>
      <LegendEntry rgb="223,25,121" tooltip="1.130 – 1.146" id="200"/>
      <LegendEntry rgb="226,25,124" tooltip="1.146 – 1.162" id="201"/>
      <LegendEntry rgb="229,25,127" tooltip="1.162 – 1.178" id="202"/>
      <LegendEntry rgb="232,25,130" tooltip="1.178 – 1.194" id="203"/>
      <LegendEntry rgb="235,25,133" tooltip="1.194 – 1.209" id="204"/>
      <LegendEntry rgb="238,25,136" tooltip="1.209 – 1.225" id="205"/>
      <LegendEntry rgb="241,25,139" tooltip="1.225 – 1.241" id="206"/>
      <LegendEntry rgb="244,25,142" tooltip="1.241 – 1.257" id="207"/>
      <LegendEntry rgb="247,25,145" tooltip="1.257 – 1.273" id="208"/>
      <LegendEntry rgb="250,25,148" tooltip="1.273 – 1.289" id="209"/>
      <LegendEntry rgb="253,25,151" tooltip="1.289 – 1.304" id="210"/>
      <LegendEntry rgb="250,24,151" tooltip="1.304 – 1.320" id="211"/>
      <LegendEntry rgb="243,23,148" tooltip="1.320 – 1.336" id="212"/>
      <LegendEntry rgb="236,22,145" tooltip="1.336 – 1.352" id="213"/>
      <LegendEntry rgb="229,21,142" tooltip="1.352 – 1.368" id="214"/>
      <LegendEntry rgb="222,20,139" tooltip="1.368 – 1.383" id="215"/>
      <LegendEntry rgb="215,19,136" tooltip="1.383 – 1.399" id="216"/>
      <LegendEntry rgb="208,18,133" tooltip="1.399 – 1.415" id="217"/>
      <LegendEntry rgb="201,17,130" tooltip="1.415 – 1.431" id="218"/>
      <LegendEntry rgb="194,16,127" tooltip="1.431 – 1.447" id="219"/>
      <LegendEntry rgb="187,15,124" tooltip="1.447 – 1.462" id="220"/>
      <LegendEntry rgb="180,14,121" tooltip="1.462 – 1.478" id="221"/>
      <LegendEntry rgb="173,13,118" tooltip="1.478 – 1.494" id="222"/>
      <LegendEntry rgb="166,12,115" tooltip="1.494 – 1.510" showTick="true" id="223"/>
      <LegendEntry rgb="159,11,112" tooltip="1.510 – 1.526" id="224"/>
      <LegendEntry rgb="152,10,109" tooltip="1.526 – 1.541" id="225"/>
      <LegendEntry rgb="145,9,106" tooltip="1.541 – 1.557" id="226"/>
      <LegendEntry rgb="138,8,103" tooltip="1.557 – 1.573" id="227"/>
      <LegendEntry rgb="131,7,100" tooltip="1.573 – 1.589" id="228"/>
      <LegendEntry rgb="124,6,97" tooltip="1.589 – 1.605" id="229"/>
      <LegendEntry rgb="117,5,94" tooltip="1.605 – 1.621" id="230"/>
      <LegendEntry rgb="110,4,91" tooltip="1.621 – 1.636" id="231"/>
      <LegendEntry rgb="103,3,88" tooltip="1.636 – 1.652" id="232"/>
      <LegendEntry rgb="96,2,85" tooltip="1.652 – 1.668" id="233"/>
      <LegendEntry rgb="89,1,82" tooltip="1.668 – 1.684" id="234"/>
      <LegendEntry rgb="82,0,79" tooltip="1.684 – 1.700" id="235"/>
      <LegendEntry rgb="76,0,77" tooltip="1.700 – 1.715" id="236"/>
      <LegendEntry rgb="77,1,85" tooltip="1.715 – 1.731" id="237"/>
      <LegendEntry rgb="79,2,93" tooltip="1.731 – 1.747" id="238"/>
      <LegendEntry rgb="80,4,101" tooltip="1.747 – 1.763" id="239"/>
      <LegendEntry rgb="81,5,109" tooltip="1.763 – 1.779" id="240"/>
      <LegendEntry rgb="83,6,117" tooltip="1.779 – 1.794" id="241"/>
      <LegendEntry rgb="84,8,125" tooltip="1.794 – 1.810" id="242"/>
      <LegendEntry rgb="86,9,133" tooltip="1.810 – 1.826" id="243"/>
      <LegendEntry rgb="87,10,141" tooltip="1.826 – 1.842" id="244"/>
      <LegendEntry rgb="88,12,149" tooltip="1.842 – 1.858" id="245"/>
      <LegendEntry rgb="90,13,157" tooltip="1.858 – 1.874" id="246"/>
      <LegendEntry rgb="91,14,165" tooltip="1.874 – 1.889" id="247"/>
      <LegendEntry rgb="92,16,173" tooltip="1.889 – 1.905" id="248"/>
      <LegendEntry rgb="94,17,181" tooltip="1.905 – 1.921" id="249"/>
      <LegendEntry rgb="95,18,189" tooltip="1.921 – 1.937" id="250"/>
      <LegendEntry rgb="96,20,197" tooltip="1.937 – 1.953" id="251"/>
      <LegendEntry rgb="98,21,205" tooltip="1.953 – 1.968" id="252"/>
      <LegendEntry rgb="99,22,213" tooltip="1.968 – 1.984" id="253"/>
      <LegendEntry rgb="100,24,221" tooltip="1.984 – 2.000" id="254"/>
      <LegendEntry rgb="102,25,229" tooltip="&#8805; 2.000" id="255"/>
    </Legend>
  </ColorMap>
</ColorMaps>
