<?xml version="1.0" encoding="UTF-8"?>
<ColorMaps xmlns:xsi="http://www.w3.org/2001/XMLSchema-instance"
          xsi:noNamespaceSchemaLocation="http://gibs.earthdata.nasa.gov/schemas/ColorMap_v1.3.xsd">
  <ColorMap title="No Data">
    <Entries>
      <ColorMapEntry rgb="0,0,0" transparent="true" nodata="true" ref="0" />
    </Entries>
    <Legend type="classification" >
      <LegendEntry rgb="0,0,0" tooltip="No Data" id="0" />
    </Legend>
  </ColorMap>
  <ColorMap title="Ozone" units="DU">
    <Entries>
      <ColorMapEntry rgb="1,25,89" transparent="false" sourceValue="[-INF,1.00e+02)" value="[-INF,1.00e+02)" ref="1" />
      <ColorMapEntry rgb="2,27,89" transparent="false" sourceValue="[1.00e+02,1.02e+02)" value="[1.00e+02,1.02e+02)" ref="2" />
      <ColorMapEntry rgb="3,28,90" transparent="false" sourceValue="[1.02e+02,1.03e+02)" value="[1.02e+02,1.03e+02)" ref="3" />
      <ColorMapEntry rgb="4,30,90" transparent="false" sourceValue="[1.03e+02,1.05e+02)" value="[1.03e+02,1.05e+02)" ref="4" />
      <ColorMapEntry rgb="5,31,90" transparent="false" sourceValue="[1.05e+02,1.06e+02)" value="[1.05e+02,1.06e+02)" ref="5" />
      <ColorMapEntry rgb="6,33,91" transparent="false" sourceValue="[1.06e+02,1.08e+02)" value="[1.06e+02,1.08e+02)" ref="6" />
      <ColorMapEntry rgb="7,34,91" transparent="false" sourceValue="[1.08e+02,1.09e+02)" value="[1.08e+02,1.09e+02)" ref="7" />
      <ColorMapEntry rgb="7,36,91" transparent="false" sourceValue="[1.09e+02,1.11e+02)" value="[1.09e+02,1.11e+02)" ref="8" />
      <ColorMapEntry rgb="8,37,91" transparent="false" sourceValue="[1.11e+02,1.13e+02)" value="[1.11e+02,1.13e+02)" ref="9" />
      <ColorMapEntry rgb="9,39,92" transparent="false" sourceValue="[1.13e+02,1.14e+02)" value="[1.13e+02,1.14e+02)" ref="10" />
      <ColorMapEntry rgb="10,40,92" transparent="false" sourceValue="[1.14e+02,1.16e+02)" value="[1.14e+02,1.16e+02)" ref="11" />
      <ColorMapEntry rgb="10,42,92" transparent="false" sourceValue="[1.16e+02,1.17e+02)" value="[1.16e+02,1.17e+02)" ref="12" />
      <ColorMapEntry rgb="11,43,92" transparent="false" sourceValue="[1.17e+02,1.19e+02)" value="[1.17e+02,1.19e+02)" ref="13" />
      <ColorMapEntry rgb="11,45,93" transparent="false" sourceValue="[1.19e+02,1.20e+02)" value="[1.19e+02,1.20e+02)" ref="14" />
      <ColorMapEntry rgb="12,46,93" transparent="false" sourceValue="[1.20e+02,1.22e+02)" value="[1.20e+02,1.22e+02)" ref="15" />
      <ColorMapEntry rgb="12,47,93" transparent="false" sourceValue="[1.22e+02,1.24e+02)" value="[1.22e+02,1.24e+02)" ref="16" />
      <ColorMapEntry rgb="13,49,93" transparent="false" sourceValue="[1.24e+02,1.25e+02)" value="[1.24e+02,1.25e+02)" ref="17" />
      <ColorMapEntry rgb="13,50,94" transparent="false" sourceValue="[1.25e+02,1.27e+02)" value="[1.25e+02,1.27e+02)" ref="18" />
      <ColorMapEntry rgb="13,51,94" transparent="false" sourceValue="[1.27e+02,1.28e+02)" value="[1.27e+02,1.28e+02)" ref="19" />
      <ColorMapEntry rgb="14,53,94" transparent="false" sourceValue="[1.28e+02,1.30e+02)" value="[1.28e+02,1.30e+02)" ref="20" />
      <ColorMapEntry rgb="14,54,94" transparent="false" sourceValue="[1.30e+02,1.31e+02)" value="[1.30e+02,1.31e+02)" ref="21" />
      <ColorMapEntry rgb="14,55,94" transparent="false" sourceValue="[1.31e+02,1.33e+02)" value="[1.31e+02,1.33e+02)" ref="22" />
      <ColorMapEntry rgb="15,56,95" transparent="false" sourceValue="[1.33e+02,1.35e+02)" value="[1.33e+02,1.35e+02)" ref="23" />
      <ColorMapEntry rgb="15,57,95" transparent="false" sourceValue="[1.35e+02,1.36e+02)" value="[1.35e+02,1.36e+02)" ref="24" />
      <ColorMapEntry rgb="15,59,95" transparent="false" sourceValue="[1.36e+02,1.38e+02)" value="[1.36e+02,1.38e+02)" ref="25" />
      <ColorMapEntry rgb="15,60,95" transparent="false" sourceValue="[1.38e+02,1.39e+02)" value="[1.38e+02,1.39e+02)" ref="26" />
      <ColorMapEntry rgb="16,61,95" transparent="false" sourceValue="[1.39e+02,1.41e+02)" value="[1.39e+02,1.41e+02)" ref="27" />
      <ColorMapEntry rgb="16,62,95" transparent="false" sourceValue="[1.41e+02,1.43e+02)" value="[1.41e+02,1.43e+02)" ref="28" />
      <ColorMapEntry rgb="16,63,96" transparent="false" sourceValue="[1.43e+02,1.44e+02)" value="[1.43e+02,1.44e+02)" ref="29" />
      <ColorMapEntry rgb="16,64,96" transparent="false" sourceValue="[1.44e+02,1.46e+02)" value="[1.44e+02,1.46e+02)" ref="30" />
      <ColorMapEntry rgb="17,65,96" transparent="false" sourceValue="[1.46e+02,1.47e+02)" value="[1.46e+02,1.47e+02)" ref="31" />
      <ColorMapEntry rgb="17,66,96" transparent="false" sourceValue="[1.47e+02,1.49e+02)" value="[1.47e+02,1.49e+02)" ref="32" />
      <ColorMapEntry rgb="17,67,96" transparent="false" sourceValue="[1.49e+02,1.50e+02)" value="[1.49e+02,1.50e+02)" ref="33" />
      <ColorMapEntry rgb="17,68,96" transparent="false" sourceValue="[1.50e+02,1.52e+02)" value="[1.50e+02,1.52e+02)" ref="34" />
      <ColorMapEntry rgb="18,69,97" transparent="false" sourceValue="[1.52e+02,1.54e+02)" value="[1.52e+02,1.54e+02)" ref="35" />
      <ColorMapEntry rgb="18,70,97" transparent="false" sourceValue="[1.54e+02,1.55e+02)" value="[1.54e+02,1.55e+02)" ref="36" />
      <ColorMapEntry rgb="18,71,97" transparent="false" sourceValue="[1.55e+02,1.57e+02)" value="[1.55e+02,1.57e+02)" ref="37" />
      <ColorMapEntry rgb="18,72,97" transparent="false" sourceValue="[1.57e+02,1.58e+02)" value="[1.57e+02,1.58e+02)" ref="38" />
      <ColorMapEntry rgb="19,73,97" transparent="false" sourceValue="[1.58e+02,1.60e+02)" value="[1.58e+02,1.60e+02)" ref="39" />
      <ColorMapEntry rgb="19,74,97" transparent="false" sourceValue="[1.60e+02,1.61e+02)" value="[1.60e+02,1.61e+02)" ref="40" />
      <ColorMapEntry rgb="19,75,97" transparent="false" sourceValue="[1.61e+02,1.63e+02)" value="[1.61e+02,1.63e+02)" ref="41" />
      <ColorMapEntry rgb="20,76,98" transparent="false" sourceValue="[1.63e+02,1.65e+02)" value="[1.63e+02,1.65e+02)" ref="42" />
      <ColorMapEntry rgb="20,77,98" transparent="false" sourceValue="[1.65e+02,1.66e+02)" value="[1.65e+02,1.66e+02)" ref="43" />
      <ColorMapEntry rgb="20,78,98" transparent="false" sourceValue="[1.66e+02,1.68e+02)" value="[1.66e+02,1.68e+02)" ref="44" />
      <ColorMapEntry rgb="21,79,98" transparent="false" sourceValue="[1.68e+02,1.69e+02)" value="[1.68e+02,1.69e+02)" ref="45" />
      <ColorMapEntry rgb="22,80,98" transparent="false" sourceValue="[1.69e+02,1.71e+02)" value="[1.69e+02,1.71e+02)" ref="46" />
      <ColorMapEntry rgb="22,81,98" transparent="false" sourceValue="[1.71e+02,1.72e+02)" value="[1.71e+02,1.72e+02)" ref="47" />
      <ColorMapEntry rgb="23,82,98" transparent="false" sourceValue="[1.72e+02,1.74e+02)" value="[1.72e+02,1.74e+02)" ref="48" />
      <ColorMapEntry rgb="23,83,98" transparent="false" sourceValue="[1.74e+02,1.76e+02)" value="[1.74e+02,1.76e+02)" ref="49" />
      <ColorMapEntry rgb="24,84,98" transparent="false" sourceValue="[1.76e+02,1.77e+02)" value="[1.76e+02,1.77e+02)" ref="50" />
      <ColorMapEntry rgb="24,85,98" transparent="false" sourceValue="[1.77e+02,1.79e+02)" value="[1.77e+02,1.79e+02)" ref="51" />
      <ColorMapEntry rgb="25,86,98" transparent="false" sourceValue="[1.79e+02,1.80e+02)" value="[1.79e+02,1.80e+02)" ref="52" />
      <ColorMapEntry rgb="25,87,98" transparent="false" sourceValue="[1.80e+02,1.82e+02)" value="[1.80e+02,1.82e+02)" ref="53" />
      <ColorMapEntry rgb="26,87,98" transparent="false" sourceValue="[1.82e+02,1.83e+02)" value="[1.82e+02,1.83e+02)" ref="54" />
      <ColorMapEntry rgb="27,88,98" transparent="false" sourceValue="[1.83e+02,1.85e+02)" value="[1.83e+02,1.85e+02)" ref="55" />
      <ColorMapEntry rgb="27,89,98" transparent="false" sourceValue="[1.85e+02,1.87e+02)" value="[1.85e+02,1.87e+02)" ref="56" />
      <ColorMapEntry rgb="28,90,98" transparent="false" sourceValue="[1.87e+02,1.88e+02)" value="[1.87e+02,1.88e+02)" ref="57" />
      <ColorMapEntry rgb="29,91,98" transparent="false" sourceValue="[1.88e+02,1.90e+02)" value="[1.88e+02,1.90e+02)" ref="58" />
      <ColorMapEntry rgb="30,92,98" transparent="false" sourceValue="[1.90e+02,1.91e+02)" value="[1.90e+02,1.91e+02)" ref="59" />
      <ColorMapEntry rgb="30,93,98" transparent="false" sourceValue="[1.91e+02,1.93e+02)" value="[1.91e+02,1.93e+02)" ref="60" />
      <ColorMapEntry rgb="31,93,97" transparent="false" sourceValue="[1.93e+02,1.94e+02)" value="[1.93e+02,1.94e+02)" ref="61" />
      <ColorMapEntry rgb="32,94,97" transparent="false" sourceValue="[1.94e+02,1.96e+02)" value="[1.94e+02,1.96e+02)" ref="62" />
      <ColorMapEntry rgb="33,95,97" transparent="false" sourceValue="[1.96e+02,1.98e+02)" value="[1.96e+02,1.98e+02)" ref="63" />
      <ColorMapEntry rgb="34,96,97" transparent="false" sourceValue="[1.98e+02,1.99e+02)" value="[1.98e+02,1.99e+02)" ref="64" />
      <ColorMapEntry rgb="35,96,96" transparent="false" sourceValue="[1.99e+02,2.01e+02)" value="[1.99e+02,2.01e+02)" ref="65" />
      <ColorMapEntry rgb="36,97,96" transparent="false" sourceValue="[2.01e+02,2.02e+02)" value="[2.01e+02,2.02e+02)" ref="66" />
      <ColorMapEntry rgb="37,98,96" transparent="false" sourceValue="[2.02e+02,2.04e+02)" value="[2.02e+02,2.04e+02)" ref="67" />
      <ColorMapEntry rgb="38,99,95" transparent="false" sourceValue="[2.04e+02,2.06e+02)" value="[2.04e+02,2.06e+02)" ref="68" />
      <ColorMapEntry rgb="39,99,95" transparent="false" sourceValue="[2.06e+02,2.07e+02)" value="[2.06e+02,2.07e+02)" ref="69" />
      <ColorMapEntry rgb="40,100,95" transparent="false" sourceValue="[2.07e+02,2.09e+02)" value="[2.07e+02,2.09e+02)" ref="70" />
      <ColorMapEntry rgb="42,101,94" transparent="false" sourceValue="[2.09e+02,2.10e+02)" value="[2.09e+02,2.10e+02)" ref="71" />
      <ColorMapEntry rgb="43,101,94" transparent="false" sourceValue="[2.10e+02,2.12e+02)" value="[2.10e+02,2.12e+02)" ref="72" />
      <ColorMapEntry rgb="44,102,93" transparent="false" sourceValue="[2.12e+02,2.13e+02)" value="[2.12e+02,2.13e+02)" ref="73" />
      <ColorMapEntry rgb="45,103,93" transparent="false" sourceValue="[2.13e+02,2.15e+02)" value="[2.13e+02,2.15e+02)" ref="74" />
      <ColorMapEntry rgb="47,103,92" transparent="false" sourceValue="[2.15e+02,2.17e+02)" value="[2.15e+02,2.17e+02)" ref="75" />
      <ColorMapEntry rgb="48,104,92" transparent="false" sourceValue="[2.17e+02,2.18e+02)" value="[2.17e+02,2.18e+02)" ref="76" />
      <ColorMapEntry rgb="49,105,91" transparent="false" sourceValue="[2.18e+02,2.20e+02)" value="[2.18e+02,2.20e+02)" ref="77" />
      <ColorMapEntry rgb="51,105,90" transparent="false" sourceValue="[2.20e+02,2.21e+02)" value="[2.20e+02,2.21e+02)" ref="78" />
      <ColorMapEntry rgb="52,106,90" transparent="false" sourceValue="[2.21e+02,2.23e+02)" value="[2.21e+02,2.23e+02)" ref="79" />
      <ColorMapEntry rgb="53,106,89" transparent="false" sourceValue="[2.23e+02,2.24e+02)" value="[2.23e+02,2.24e+02)" ref="80" />
      <ColorMapEntry rgb="55,107,88" transparent="false" sourceValue="[2.24e+02,2.26e+02)" value="[2.24e+02,2.26e+02)" ref="81" />
      <ColorMapEntry rgb="56,108,88" transparent="false" sourceValue="[2.26e+02,2.28e+02)" value="[2.26e+02,2.28e+02)" ref="82" />
      <ColorMapEntry rgb="58,108,87" transparent="false" sourceValue="[2.28e+02,2.29e+02)" value="[2.28e+02,2.29e+02)" ref="83" />
      <ColorMapEntry rgb="59,109,86" transparent="false" sourceValue="[2.29e+02,2.31e+02)" value="[2.29e+02,2.31e+02)" ref="84" />
      <ColorMapEntry rgb="60,109,86" transparent="false" sourceValue="[2.31e+02,2.32e+02)" value="[2.31e+02,2.32e+02)" ref="85" />
      <ColorMapEntry rgb="62,110,85" transparent="false" sourceValue="[2.32e+02,2.34e+02)" value="[2.32e+02,2.34e+02)" ref="86" />
      <ColorMapEntry rgb="63,110,84" transparent="false" sourceValue="[2.34e+02,2.35e+02)" value="[2.34e+02,2.35e+02)" ref="87" />
      <ColorMapEntry rgb="65,111,83" transparent="false" sourceValue="[2.35e+02,2.37e+02)" value="[2.35e+02,2.37e+02)" ref="88" />
      <ColorMapEntry rgb="66,111,82" transparent="false" sourceValue="[2.37e+02,2.39e+02)" value="[2.37e+02,2.39e+02)" ref="89" />
      <ColorMapEntry rgb="68,112,82" transparent="false" sourceValue="[2.39e+02,2.40e+02)" value="[2.39e+02,2.40e+02)" ref="90" />
      <ColorMapEntry rgb="69,112,81" transparent="false" sourceValue="[2.40e+02,2.42e+02)" value="[2.40e+02,2.42e+02)" ref="91" />
      <ColorMapEntry rgb="71,113,80" transparent="false" sourceValue="[2.42e+02,2.43e+02)" value="[2.42e+02,2.43e+02)" ref="92" />
      <ColorMapEntry rgb="72,113,79" transparent="false" sourceValue="[2.43e+02,2.45e+02)" value="[2.43e+02,2.45e+02)" ref="93" />
      <ColorMapEntry rgb="74,114,78" transparent="false" sourceValue="[2.45e+02,2.46e+02)" value="[2.45e+02,2.46e+02)" ref="94" />
      <ColorMapEntry rgb="76,114,77" transparent="false" sourceValue="[2.46e+02,2.48e+02)" value="[2.46e+02,2.48e+02)" ref="95" />
      <ColorMapEntry rgb="77,115,77" transparent="false" sourceValue="[2.48e+02,2.50e+02)" value="[2.48e+02,2.50e+02)" ref="96" />
      <ColorMapEntry rgb="79,115,76" transparent="false" sourceValue="[2.50e+02,2.51e+02)" value="[2.50e+02,2.51e+02)" ref="97" />
      <ColorMapEntry rgb="80,116,75" transparent="false" sourceValue="[2.51e+02,2.53e+02)" value="[2.51e+02,2.53e+02)" ref="98" />
      <ColorMapEntry rgb="82,116,74" transparent="false" sourceValue="[2.53e+02,2.54e+02)" value="[2.53e+02,2.54e+02)" ref="99" />
      <ColorMapEntry rgb="83,117,73" transparent="false" sourceValue="[2.54e+02,2.56e+02)" value="[2.54e+02,2.56e+02)" ref="100" />
      <ColorMapEntry rgb="85,117,72" transparent="false" sourceValue="[2.56e+02,2.57e+02)" value="[2.56e+02,2.57e+02)" ref="101" />
      <ColorMapEntry rgb="87,118,71" transparent="false" sourceValue="[2.57e+02,2.59e+02)" value="[2.57e+02,2.59e+02)" ref="102" />
      <ColorMapEntry rgb="88,118,70" transparent="false" sourceValue="[2.59e+02,2.61e+02)" value="[2.59e+02,2.61e+02)" ref="103" />
      <ColorMapEntry rgb="90,119,69" transparent="false" sourceValue="[2.61e+02,2.62e+02)" value="[2.61e+02,2.62e+02)" ref="104" />
      <ColorMapEntry rgb="91,119,69" transparent="false" sourceValue="[2.62e+02,2.64e+02)" value="[2.62e+02,2.64e+02)" ref="105" />
      <ColorMapEntry rgb="93,120,68" transparent="false" sourceValue="[2.64e+02,2.65e+02)" value="[2.64e+02,2.65e+02)" ref="106" />
      <ColorMapEntry rgb="95,120,67" transparent="false" sourceValue="[2.65e+02,2.67e+02)" value="[2.65e+02,2.67e+02)" ref="107" />
      <ColorMapEntry rgb="96,121,66" transparent="false" sourceValue="[2.67e+02,2.69e+02)" value="[2.67e+02,2.69e+02)" ref="108" />
      <ColorMapEntry rgb="98,121,65" transparent="false" sourceValue="[2.69e+02,2.70e+02)" value="[2.69e+02,2.70e+02)" ref="109" />
      <ColorMapEntry rgb="99,122,64" transparent="false" sourceValue="[2.70e+02,2.72e+02)" value="[2.70e+02,2.72e+02)" ref="110" />
      <ColorMapEntry rgb="101,122,63" transparent="false" sourceValue="[2.72e+02,2.73e+02)" value="[2.72e+02,2.73e+02)" ref="111" />
      <ColorMapEntry rgb="103,123,62" transparent="false" sourceValue="[2.73e+02,2.75e+02)" value="[2.73e+02,2.75e+02)" ref="112" />
      <ColorMapEntry rgb="104,123,62" transparent="false" sourceValue="[2.75e+02,2.76e+02)" value="[2.75e+02,2.76e+02)" ref="113" />
      <ColorMapEntry rgb="106,123,61" transparent="false" sourceValue="[2.76e+02,2.78e+02)" value="[2.76e+02,2.78e+02)" ref="114" />
      <ColorMapEntry rgb="108,124,60" transparent="false" sourceValue="[2.78e+02,2.80e+02)" value="[2.78e+02,2.80e+02)" ref="115" />
      <ColorMapEntry rgb="109,124,59" transparent="false" sourceValue="[2.80e+02,2.81e+02)" value="[2.80e+02,2.81e+02)" ref="116" />
      <ColorMapEntry rgb="111,125,58" transparent="false" sourceValue="[2.81e+02,2.83e+02)" value="[2.81e+02,2.83e+02)" ref="117" />
      <ColorMapEntry rgb="113,125,57" transparent="false" sourceValue="[2.83e+02,2.84e+02)" value="[2.83e+02,2.84e+02)" ref="118" />
      <ColorMapEntry rgb="115,126,56" transparent="false" sourceValue="[2.84e+02,2.86e+02)" value="[2.84e+02,2.86e+02)" ref="119" />
      <ColorMapEntry rgb="116,126,56" transparent="false" sourceValue="[2.86e+02,2.87e+02)" value="[2.86e+02,2.87e+02)" ref="120" />
      <ColorMapEntry rgb="118,127,55" transparent="false" sourceValue="[2.87e+02,2.89e+02)" value="[2.87e+02,2.89e+02)" ref="121" />
      <ColorMapEntry rgb="120,127,54" transparent="false" sourceValue="[2.89e+02,2.91e+02)" value="[2.89e+02,2.91e+02)" ref="122" />
      <ColorMapEntry rgb="121,128,53" transparent="false" sourceValue="[2.91e+02,2.92e+02)" value="[2.91e+02,2.92e+02)" ref="123" />
      <ColorMapEntry rgb="123,128,52" transparent="false" sourceValue="[2.92e+02,2.94e+02)" value="[2.92e+02,2.94e+02)" ref="124" />
      <ColorMapEntry rgb="125,129,52" transparent="false" sourceValue="[2.94e+02,2.95e+02)" value="[2.94e+02,2.95e+02)" ref="125" />
      <ColorMapEntry rgb="127,129,51" transparent="false" sourceValue="[2.95e+02,2.97e+02)" value="[2.95e+02,2.97e+02)" ref="126" />
      <ColorMapEntry rgb="130,130,49" transparent="false" sourceValue="[2.97e+02,2.98e+02)" value="[2.97e+02,2.98e+02)" ref="127" />
      <ColorMapEntry rgb="132,131,49" transparent="false" sourceValue="[2.98e+02,3.00e+02)" value="[2.98e+02,3.00e+02)" ref="128" />
      <ColorMapEntry rgb="134,131,48" transparent="false" sourceValue="[3.00e+02,3.02e+02)" value="[3.00e+02,3.02e+02)" ref="129" />
      <ColorMapEntry rgb="136,132,47" transparent="false" sourceValue="[3.02e+02,3.03e+02)" value="[3.02e+02,3.03e+02)" ref="130" />
      <ColorMapEntry rgb="138,132,47" transparent="false" sourceValue="[3.03e+02,3.05e+02)" value="[3.03e+02,3.05e+02)" ref="131" />
      <ColorMapEntry rgb="140,133,46" transparent="false" sourceValue="[3.05e+02,3.06e+02)" value="[3.05e+02,3.06e+02)" ref="132" />
      <ColorMapEntry rgb="142,133,46" transparent="false" sourceValue="[3.06e+02,3.08e+02)" value="[3.06e+02,3.08e+02)" ref="133" />
      <ColorMapEntry rgb="143,134,45" transparent="false" sourceValue="[3.08e+02,3.09e+02)" value="[3.08e+02,3.09e+02)" ref="134" />
      <ColorMapEntry rgb="145,134,45" transparent="false" sourceValue="[3.09e+02,3.11e+02)" value="[3.09e+02,3.11e+02)" ref="135" />
      <ColorMapEntry rgb="147,135,44" transparent="false" sourceValue="[3.11e+02,3.13e+02)" value="[3.11e+02,3.13e+02)" ref="136" />
      <ColorMapEntry rgb="149,135,44" transparent="false" sourceValue="[3.13e+02,3.14e+02)" value="[3.13e+02,3.14e+02)" ref="137" />
      <ColorMapEntry rgb="151,136,44" transparent="false" sourceValue="[3.14e+02,3.16e+02)" value="[3.14e+02,3.16e+02)" ref="138" />
      <ColorMapEntry rgb="153,136,44" transparent="false" sourceValue="[3.16e+02,3.17e+02)" value="[3.16e+02,3.17e+02)" ref="139" />
      <ColorMapEntry rgb="155,137,43" transparent="false" sourceValue="[3.17e+02,3.19e+02)" value="[3.17e+02,3.19e+02)" ref="140" />
      <ColorMapEntry rgb="157,137,43" transparent="false" sourceValue="[3.19e+02,3.20e+02)" value="[3.19e+02,3.20e+02)" ref="141" />
      <ColorMapEntry rgb="159,137,43" transparent="false" sourceValue="[3.20e+02,3.22e+02)" value="[3.20e+02,3.22e+02)" ref="142" />
      <ColorMapEntry rgb="161,138,43" transparent="false" sourceValue="[3.22e+02,3.24e+02)" value="[3.22e+02,3.24e+02)" ref="143" />
      <ColorMapEntry rgb="163,138,44" transparent="false" sourceValue="[3.24e+02,3.25e+02)" value="[3.24e+02,3.25e+02)" ref="144" />
      <ColorMapEntry rgb="165,139,44" transparent="false" sourceValue="[3.25e+02,3.27e+02)" value="[3.25e+02,3.27e+02)" ref="145" />
      <ColorMapEntry rgb="167,139,44" transparent="false" sourceValue="[3.27e+02,3.28e+02)" value="[3.27e+02,3.28e+02)" ref="146" />
      <ColorMapEntry rgb="169,140,44" transparent="false" sourceValue="[3.28e+02,3.30e+02)" value="[3.28e+02,3.30e+02)" ref="147" />
      <ColorMapEntry rgb="171,140,45" transparent="false" sourceValue="[3.30e+02,3.31e+02)" value="[3.30e+02,3.31e+02)" ref="148" />
      <ColorMapEntry rgb="173,140,45" transparent="false" sourceValue="[3.31e+02,3.33e+02)" value="[3.31e+02,3.33e+02)" ref="149" />
      <ColorMapEntry rgb="175,141,46" transparent="false" sourceValue="[3.33e+02,3.35e+02)" value="[3.33e+02,3.35e+02)" ref="150" />
      <ColorMapEntry rgb="177,141,47" transparent="false" sourceValue="[3.35e+02,3.36e+02)" value="[3.35e+02,3.36e+02)" ref="151" />
      <ColorMapEntry rgb="179,142,47" transparent="false" sourceValue="[3.36e+02,3.38e+02)" value="[3.36e+02,3.38e+02)" ref="152" />
      <ColorMapEntry rgb="181,142,48" transparent="false" sourceValue="[3.38e+02,3.39e+02)" value="[3.38e+02,3.39e+02)" ref="153" />
      <ColorMapEntry rgb="183,142,49" transparent="false" sourceValue="[3.39e+02,3.41e+02)" value="[3.39e+02,3.41e+02)" ref="154" />
      <ColorMapEntry rgb="185,143,50" transparent="false" sourceValue="[3.41e+02,3.43e+02)" value="[3.41e+02,3.43e+02)" ref="155" />
      <ColorMapEntry rgb="187,143,51" transparent="false" sourceValue="[3.43e+02,3.44e+02)" value="[3.43e+02,3.44e+02)" ref="156" />
      <ColorMapEntry rgb="189,143,52" transparent="false" sourceValue="[3.44e+02,3.46e+02)" value="[3.44e+02,3.46e+02)" ref="157" />
      <ColorMapEntry rgb="190,144,53" transparent="false" sourceValue="[3.46e+02,3.47e+02)" value="[3.46e+02,3.47e+02)" ref="158" />
      <ColorMapEntry rgb="192,144,54" transparent="false" sourceValue="[3.47e+02,3.49e+02)" value="[3.47e+02,3.49e+02)" ref="159" />
      <ColorMapEntry rgb="194,144,55" transparent="false" sourceValue="[3.49e+02,3.50e+02)" value="[3.49e+02,3.50e+02)" ref="160" />
      <ColorMapEntry rgb="196,145,56" transparent="false" sourceValue="[3.50e+02,3.52e+02)" value="[3.50e+02,3.52e+02)" ref="161" />
      <ColorMapEntry rgb="198,145,58" transparent="false" sourceValue="[3.52e+02,3.54e+02)" value="[3.52e+02,3.54e+02)" ref="162" />
      <ColorMapEntry rgb="200,145,59" transparent="false" sourceValue="[3.54e+02,3.55e+02)" value="[3.54e+02,3.55e+02)" ref="163" />
      <ColorMapEntry rgb="202,146,60" transparent="false" sourceValue="[3.55e+02,3.57e+02)" value="[3.55e+02,3.57e+02)" ref="164" />
      <ColorMapEntry rgb="203,146,62" transparent="false" sourceValue="[3.57e+02,3.58e+02)" value="[3.57e+02,3.58e+02)" ref="165" />
      <ColorMapEntry rgb="205,146,63" transparent="false" sourceValue="[3.58e+02,3.60e+02)" value="[3.58e+02,3.60e+02)" ref="166" />
      <ColorMapEntry rgb="207,147,64" transparent="false" sourceValue="[3.60e+02,3.61e+02)" value="[3.60e+02,3.61e+02)" ref="167" />
      <ColorMapEntry rgb="209,147,66" transparent="false" sourceValue="[3.61e+02,3.63e+02)" value="[3.61e+02,3.63e+02)" ref="168" />
      <ColorMapEntry rgb="210,147,67" transparent="false" sourceValue="[3.63e+02,3.65e+02)" value="[3.63e+02,3.65e+02)" ref="169" />
      <ColorMapEntry rgb="212,148,69" transparent="false" sourceValue="[3.65e+02,3.66e+02)" value="[3.65e+02,3.66e+02)" ref="170" />
      <ColorMapEntry rgb="214,148,70" transparent="false" sourceValue="[3.66e+02,3.68e+02)" value="[3.66e+02,3.68e+02)" ref="171" />
      <ColorMapEntry rgb="216,148,72" transparent="false" sourceValue="[3.68e+02,3.69e+02)" value="[3.68e+02,3.69e+02)" ref="172" />
      <ColorMapEntry rgb="217,149,74" transparent="false" sourceValue="[3.69e+02,3.71e+02)" value="[3.69e+02,3.71e+02)" ref="173" />
      <ColorMapEntry rgb="219,149,75" transparent="false" sourceValue="[3.71e+02,3.72e+02)" value="[3.71e+02,3.72e+02)" ref="174" />
      <ColorMapEntry rgb="221,149,77" transparent="false" sourceValue="[3.72e+02,3.74e+02)" value="[3.72e+02,3.74e+02)" ref="175" />
      <ColorMapEntry rgb="222,150,79" transparent="false" sourceValue="[3.74e+02,3.76e+02)" value="[3.74e+02,3.76e+02)" ref="176" />
      <ColorMapEntry rgb="224,150,81" transparent="false" sourceValue="[3.76e+02,3.77e+02)" value="[3.76e+02,3.77e+02)" ref="177" />
      <ColorMapEntry rgb="225,151,82" transparent="false" sourceValue="[3.77e+02,3.79e+02)" value="[3.77e+02,3.79e+02)" ref="178" />
      <ColorMapEntry rgb="227,151,84" transparent="false" sourceValue="[3.79e+02,3.80e+02)" value="[3.79e+02,3.80e+02)" ref="179" />
      <ColorMapEntry rgb="228,151,86" transparent="false" sourceValue="[3.80e+02,3.82e+02)" value="[3.80e+02,3.82e+02)" ref="180" />
      <ColorMapEntry rgb="230,152,88" transparent="false" sourceValue="[3.82e+02,3.83e+02)" value="[3.82e+02,3.83e+02)" ref="181" />
      <ColorMapEntry rgb="231,152,90" transparent="false" sourceValue="[3.83e+02,3.85e+02)" value="[3.83e+02,3.85e+02)" ref="182" />
      <ColorMapEntry rgb="233,153,92" transparent="false" sourceValue="[3.85e+02,3.87e+02)" value="[3.85e+02,3.87e+02)" ref="183" />
      <ColorMapEntry rgb="234,153,94" transparent="false" sourceValue="[3.87e+02,3.88e+02)" value="[3.87e+02,3.88e+02)" ref="184" />
      <ColorMapEntry rgb="235,154,96" transparent="false" sourceValue="[3.88e+02,3.90e+02)" value="[3.88e+02,3.90e+02)" ref="185" />
      <ColorMapEntry rgb="237,154,98" transparent="false" sourceValue="[3.90e+02,3.91e+02)" value="[3.90e+02,3.91e+02)" ref="186" />
      <ColorMapEntry rgb="238,155,100" transparent="false" sourceValue="[3.91e+02,3.93e+02)" value="[3.91e+02,3.93e+02)" ref="187" />
      <ColorMapEntry rgb="239,155,103" transparent="false" sourceValue="[3.93e+02,3.94e+02)" value="[3.93e+02,3.94e+02)" ref="188" />
      <ColorMapEntry rgb="240,156,105" transparent="false" sourceValue="[3.94e+02,3.96e+02)" value="[3.94e+02,3.96e+02)" ref="189" />
      <ColorMapEntry rgb="241,157,107" transparent="false" sourceValue="[3.96e+02,3.98e+02)" value="[3.96e+02,3.98e+02)" ref="190" />
      <ColorMapEntry rgb="242,157,109" transparent="false" sourceValue="[3.98e+02,3.99e+02)" value="[3.98e+02,3.99e+02)" ref="191" />
      <ColorMapEntry rgb="243,158,112" transparent="false" sourceValue="[3.99e+02,4.01e+02)" value="[3.99e+02,4.01e+02)" ref="192" />
      <ColorMapEntry rgb="244,159,114" transparent="false" sourceValue="[4.01e+02,4.02e+02)" value="[4.01e+02,4.02e+02)" ref="193" />
      <ColorMapEntry rgb="245,159,116" transparent="false" sourceValue="[4.02e+02,4.04e+02)" value="[4.02e+02,4.04e+02)" ref="194" />
      <ColorMapEntry rgb="246,160,119" transparent="false" sourceValue="[4.04e+02,4.06e+02)" value="[4.04e+02,4.06e+02)" ref="195" />
      <ColorMapEntry rgb="247,161,121" transparent="false" sourceValue="[4.06e+02,4.07e+02)" value="[4.06e+02,4.07e+02)" ref="196" />
      <ColorMapEntry rgb="248,161,123" transparent="false" sourceValue="[4.07e+02,4.09e+02)" value="[4.07e+02,4.09e+02)" ref="197" />
      <ColorMapEntry rgb="248,162,126" transparent="false" sourceValue="[4.09e+02,4.10e+02)" value="[4.09e+02,4.10e+02)" ref="198" />
      <ColorMapEntry rgb="249,163,128" transparent="false" sourceValue="[4.10e+02,4.12e+02)" value="[4.10e+02,4.12e+02)" ref="199" />
      <ColorMapEntry rgb="249,163,130" transparent="false" sourceValue="[4.12e+02,4.13e+02)" value="[4.12e+02,4.13e+02)" ref="200" />
      <ColorMapEntry rgb="250,164,133" transparent="false" sourceValue="[4.13e+02,4.15e+02)" value="[4.13e+02,4.15e+02)" ref="201" />
      <ColorMapEntry rgb="250,165,135" transparent="false" sourceValue="[4.15e+02,4.17e+02)" value="[4.15e+02,4.17e+02)" ref="202" />
      <ColorMapEntry rgb="251,166,137" transparent="false" sourceValue="[4.17e+02,4.18e+02)" value="[4.17e+02,4.18e+02)" ref="203" />
      <ColorMapEntry rgb="251,166,140" transparent="false" sourceValue="[4.18e+02,4.20e+02)" value="[4.18e+02,4.20e+02)" ref="204" />
      <ColorMapEntry rgb="252,167,142" transparent="false" sourceValue="[4.20e+02,4.21e+02)" value="[4.20e+02,4.21e+02)" ref="205" />
      <ColorMapEntry rgb="252,168,144" transparent="false" sourceValue="[4.21e+02,4.23e+02)" value="[4.21e+02,4.23e+02)" ref="206" />
      <ColorMapEntry rgb="252,169,147" transparent="false" sourceValue="[4.23e+02,4.24e+02)" value="[4.23e+02,4.24e+02)" ref="207" />
      <ColorMapEntry rgb="252,169,149" transparent="false" sourceValue="[4.24e+02,4.26e+02)" value="[4.24e+02,4.26e+02)" ref="208" />
      <ColorMapEntry rgb="253,170,151" transparent="false" sourceValue="[4.26e+02,4.28e+02)" value="[4.26e+02,4.28e+02)" ref="209" />
      <ColorMapEntry rgb="253,171,154" transparent="false" sourceValue="[4.28e+02,4.29e+02)" value="[4.28e+02,4.29e+02)" ref="210" />
      <ColorMapEntry rgb="253,172,156" transparent="false" sourceValue="[4.29e+02,4.31e+02)" value="[4.29e+02,4.31e+02)" ref="211" />
      <ColorMapEntry rgb="253,172,158" transparent="false" sourceValue="[4.31e+02,4.32e+02)" value="[4.31e+02,4.32e+02)" ref="212" />
      <ColorMapEntry rgb="253,173,160" transparent="false" sourceValue="[4.32e+02,4.34e+02)" value="[4.32e+02,4.34e+02)" ref="213" />
      <ColorMapEntry rgb="253,174,162" transparent="false" sourceValue="[4.34e+02,4.35e+02)" value="[4.34e+02,4.35e+02)" ref="214" />
      <ColorMapEntry rgb="253,175,165" transparent="false" sourceValue="[4.35e+02,4.37e+02)" value="[4.35e+02,4.37e+02)" ref="215" />
      <ColorMapEntry rgb="253,175,167" transparent="false" sourceValue="[4.37e+02,4.39e+02)" value="[4.37e+02,4.39e+02)" ref="216" />
      <ColorMapEntry rgb="253,176,169" transparent="false" sourceValue="[4.39e+02,4.40e+02)" value="[4.39e+02,4.40e+02)" ref="217" />
      <ColorMapEntry rgb="253,177,171" transparent="false" sourceValue="[4.40e+02,4.42e+02)" value="[4.40e+02,4.42e+02)" ref="218" />
      <ColorMapEntry rgb="253,178,173" transparent="false" sourceValue="[4.42e+02,4.43e+02)" value="[4.42e+02,4.43e+02)" ref="219" />
      <ColorMapEntry rgb="253,178,175" transparent="false" sourceValue="[4.43e+02,4.45e+02)" value="[4.43e+02,4.45e+02)" ref="220" />
      <ColorMapEntry rgb="253,179,177" transparent="false" sourceValue="[4.45e+02,4.46e+02)" value="[4.45e+02,4.46e+02)" ref="221" />
      <ColorMapEntry rgb="253,180,180" transparent="false" sourceValue="[4.46e+02,4.48e+02)" value="[4.46e+02,4.48e+02)" ref="222" />
      <ColorMapEntry rgb="253,180,182" transparent="false" sourceValue="[4.48e+02,4.50e+02)" value="[4.48e+02,4.50e+02)" ref="223" />
      <ColorMapEntry rgb="253,181,184" transparent="false" sourceValue="[4.50e+02,4.51e+02)" value="[4.50e+02,4.51e+02)" ref="224" />
      <ColorMapEntry rgb="253,182,186" transparent="false" sourceValue="[4.51e+02,4.53e+02)" value="[4.51e+02,4.53e+02)" ref="225" />
      <ColorMapEntry rgb="253,183,188" transparent="false" sourceValue="[4.53e+02,4.54e+02)" value="[4.53e+02,4.54e+02)" ref="226" />
      <ColorMapEntry rgb="253,183,190" transparent="false" sourceValue="[4.54e+02,4.56e+02)" value="[4.54e+02,4.56e+02)" ref="227" />
      <ColorMapEntry rgb="253,184,192" transparent="false" sourceValue="[4.56e+02,4.57e+02)" value="[4.56e+02,4.57e+02)" ref="228" />
      <ColorMapEntry rgb="253,185,194" transparent="false" sourceValue="[4.57e+02,4.59e+02)" value="[4.57e+02,4.59e+02)" ref="229" />
      <ColorMapEntry rgb="253,186,196" transparent="false" sourceValue="[4.59e+02,4.61e+02)" value="[4.59e+02,4.61e+02)" ref="230" />
      <ColorMapEntry rgb="253,186,199" transparent="false" sourceValue="[4.61e+02,4.62e+02)" value="[4.61e+02,4.62e+02)" ref="231" />
      <ColorMapEntry rgb="253,187,201" transparent="false" sourceValue="[4.62e+02,4.64e+02)" value="[4.62e+02,4.64e+02)" ref="232" />
      <ColorMapEntry rgb="253,188,203" transparent="false" sourceValue="[4.64e+02,4.65e+02)" value="[4.64e+02,4.65e+02)" ref="233" />
      <ColorMapEntry rgb="253,188,205" transparent="false" sourceValue="[4.65e+02,4.67e+02)" value="[4.65e+02,4.67e+02)" ref="234" />
      <ColorMapEntry rgb="252,189,207" transparent="false" sourceValue="[4.67e+02,4.69e+02)" value="[4.67e+02,4.69e+02)" ref="235" />
      <ColorMapEntry rgb="252,190,209" transparent="false" sourceValue="[4.69e+02,4.70e+02)" value="[4.69e+02,4.70e+02)" ref="236" />
      <ColorMapEntry rgb="252,191,211" transparent="false" sourceValue="[4.70e+02,4.72e+02)" value="[4.70e+02,4.72e+02)" ref="237" />
      <ColorMapEntry rgb="252,191,214" transparent="false" sourceValue="[4.72e+02,4.73e+02)" value="[4.72e+02,4.73e+02)" ref="238" />
      <ColorMapEntry rgb="252,192,216" transparent="false" sourceValue="[4.73e+02,4.75e+02)" value="[4.73e+02,4.75e+02)" ref="239" />
      <ColorMapEntry rgb="252,193,218" transparent="false" sourceValue="[4.75e+02,4.76e+02)" value="[4.75e+02,4.76e+02)" ref="240" />
      <ColorMapEntry rgb="252,194,220" transparent="false" sourceValue="[4.76e+02,4.78e+02)" value="[4.76e+02,4.78e+02)" ref="241" />
      <ColorMapEntry rgb="252,195,223" transparent="false" sourceValue="[4.78e+02,4.80e+02)" value="[4.78e+02,4.80e+02)" ref="242" />
      <ColorMapEntry rgb="252,195,225" transparent="false" sourceValue="[4.80e+02,4.81e+02)" value="[4.80e+02,4.81e+02)" ref="243" />
      <ColorMapEntry rgb="252,196,227" transparent="false" sourceValue="[4.81e+02,4.83e+02)" value="[4.81e+02,4.83e+02)" ref="244" />
      <ColorMapEntry rgb="252,197,229" transparent="false" sourceValue="[4.83e+02,4.84e+02)" value="[4.83e+02,4.84e+02)" ref="245" />
      <ColorMapEntry rgb="251,198,232" transparent="false" sourceValue="[4.84e+02,4.86e+02)" value="[4.84e+02,4.86e+02)" ref="246" />
      <ColorMapEntry rgb="251,198,234" transparent="false" sourceValue="[4.86e+02,4.87e+02)" value="[4.86e+02,4.87e+02)" ref="247" />
      <ColorMapEntry rgb="251,199,236" transparent="false" sourceValue="[4.87e+02,4.89e+02)" value="[4.87e+02,4.89e+02)" ref="248" />
      <ColorMapEntry rgb="251,200,239" transparent="false" sourceValue="[4.89e+02,4.91e+02)" value="[4.89e+02,4.91e+02)" ref="249" />
      <ColorMapEntry rgb="251,201,241" transparent="false" sourceValue="[4.91e+02,4.92e+02)" value="[4.91e+02,4.92e+02)" ref="250" />
      <ColorMapEntry rgb="251,202,243" transparent="false" sourceValue="[4.92e+02,4.94e+02)" value="[4.92e+02,4.94e+02)" ref="251" />
      <ColorMapEntry rgb="251,202,246" transparent="false" sourceValue="[4.94e+02,4.95e+02)" value="[4.94e+02,4.95e+02)" ref="252" />
      <ColorMapEntry rgb="250,203,248" transparent="false" sourceValue="[4.95e+02,4.97e+02)" value="[4.95e+02,4.97e+02)" ref="253" />
      <ColorMapEntry rgb="250,204,250" transparent="false" sourceValue="[4.97e+02,+INF)" value="[4.97e+02,+INF)" ref="254" />
    </Entries>
    <Legend type="continuous"  minLabel="&lt; 1.00e+02"  maxLabel="&gt;= 4.97e+02">
      <LegendEntry rgb="1,25,89" tooltip="&lt; 1.00e+02" id="1" />
      <LegendEntry rgb="2,27,89" tooltip="1.00e+02 – 1.02e+02" id="2" />
      <LegendEntry rgb="3,28,90" tooltip="1.02e+02 – 1.03e+02" id="3" />
      <LegendEntry rgb="4,30,90" tooltip="1.03e+02 – 1.05e+02" id="4" />
      <LegendEntry rgb="5,31,90" tooltip="1.05e+02 – 1.06e+02" id="5" />
      <LegendEntry rgb="6,33,91" tooltip="1.06e+02 – 1.08e+02" id="6" />
      <LegendEntry rgb="7,34,91" tooltip="1.08e+02 – 1.09e+02" id="7" />
      <LegendEntry rgb="7,36,91" tooltip="1.09e+02 – 1.11e+02" id="8" />
      <LegendEntry rgb="8,37,91" tooltip="1.11e+02 – 1.13e+02" id="9" />
      <LegendEntry rgb="9,39,92" tooltip="1.13e+02 – 1.14e+02" id="10" />
      <LegendEntry rgb="10,40,92" tooltip="1.14e+02 – 1.16e+02" id="11" />
      <LegendEntry rgb="10,42,92" tooltip="1.16e+02 – 1.17e+02" id="12" />
      <LegendEntry rgb="11,43,92" tooltip="1.17e+02 – 1.19e+02" id="13" />
      <LegendEntry rgb="11,45,93" tooltip="1.19e+02 – 1.20e+02" id="14" />
      <LegendEntry rgb="12,46,93" tooltip="1.20e+02 – 1.22e+02" id="15" />
      <LegendEntry rgb="12,47,93" tooltip="1.22e+02 – 1.24e+02" id="16" />
      <LegendEntry rgb="13,49,93" tooltip="1.24e+02 – 1.25e+02" id="17" />
      <LegendEntry rgb="13,50,94" tooltip="1.25e+02 – 1.27e+02" id="18" />
      <LegendEntry rgb="13,51,94" tooltip="1.27e+02 – 1.28e+02" id="19" />
      <LegendEntry rgb="14,53,94" tooltip="1.28e+02 – 1.30e+02" id="20" />
      <LegendEntry rgb="14,54,94" tooltip="1.30e+02 – 1.31e+02" id="21" />
      <LegendEntry rgb="14,55,94" tooltip="1.31e+02 – 1.33e+02" id="22" />
      <LegendEntry rgb="15,56,95" tooltip="1.33e+02 – 1.35e+02" id="23" />
      <LegendEntry rgb="15,57,95" tooltip="1.35e+02 – 1.36e+02" id="24" />
      <LegendEntry rgb="15,59,95" tooltip="1.36e+02 – 1.38e+02" id="25" />
      <LegendEntry rgb="15,60,95" tooltip="1.38e+02 – 1.39e+02" id="26" />
      <LegendEntry rgb="16,61,95" tooltip="1.39e+02 – 1.41e+02" id="27" />
      <LegendEntry rgb="16,62,95" tooltip="1.41e+02 – 1.43e+02" id="28" />
      <LegendEntry rgb="16,63,96" tooltip="1.43e+02 – 1.44e+02" id="29" />
      <LegendEntry rgb="16,64,96" tooltip="1.44e+02 – 1.46e+02" id="30" />
      <LegendEntry rgb="17,65,96" tooltip="1.46e+02 – 1.47e+02" id="31" />
      <LegendEntry rgb="17,66,96" tooltip="1.47e+02 – 1.49e+02" id="32" />
      <LegendEntry rgb="17,67,96" tooltip="1.49e+02 – 1.50e+02" id="33" />
      <LegendEntry rgb="17,68,96" tooltip="1.50e+02 – 1.52e+02" id="34" />
      <LegendEntry rgb="18,69,97" tooltip="1.52e+02 – 1.54e+02" id="35" />
      <LegendEntry rgb="18,70,97" tooltip="1.54e+02 – 1.55e+02" id="36" />
      <LegendEntry rgb="18,71,97" tooltip="1.55e+02 – 1.57e+02" id="37" />
      <LegendEntry rgb="18,72,97" tooltip="1.57e+02 – 1.58e+02" id="38" />
      <LegendEntry rgb="19,73,97" tooltip="1.58e+02 – 1.60e+02" id="39" />
      <LegendEntry rgb="19,74,97" tooltip="1.60e+02 – 1.61e+02" id="40" />
      <LegendEntry rgb="19,75,97" tooltip="1.61e+02 – 1.63e+02" id="41" />
      <LegendEntry rgb="20,76,98" tooltip="1.63e+02 – 1.65e+02" id="42" />
      <LegendEntry rgb="20,77,98" tooltip="1.65e+02 – 1.66e+02" id="43" />
      <LegendEntry rgb="20,78,98" tooltip="1.66e+02 – 1.68e+02" id="44" />
      <LegendEntry rgb="21,79,98" tooltip="1.68e+02 – 1.69e+02" id="45" />
      <LegendEntry rgb="22,80,98" tooltip="1.69e+02 – 1.71e+02" id="46" />
      <LegendEntry rgb="22,81,98" tooltip="1.71e+02 – 1.72e+02" id="47" />
      <LegendEntry rgb="23,82,98" tooltip="1.72e+02 – 1.74e+02" id="48" />
      <LegendEntry rgb="23,83,98" tooltip="1.74e+02 – 1.76e+02" id="49" />
      <LegendEntry rgb="24,84,98" tooltip="1.76e+02 – 1.77e+02" id="50" />
      <LegendEntry rgb="24,85,98" tooltip="1.77e+02 – 1.79e+02" id="51" />
      <LegendEntry rgb="25,86,98" tooltip="1.79e+02 – 1.80e+02" id="52" />
      <LegendEntry rgb="25,87,98" tooltip="1.80e+02 – 1.82e+02" id="53" />
      <LegendEntry rgb="26,87,98" tooltip="1.82e+02 – 1.83e+02" id="54" />
      <LegendEntry rgb="27,88,98" tooltip="1.83e+02 – 1.85e+02" id="55" />
      <LegendEntry rgb="27,89,98" tooltip="1.85e+02 – 1.87e+02" id="56" />
      <LegendEntry rgb="28,90,98" tooltip="1.87e+02 – 1.88e+02" id="57" />
      <LegendEntry rgb="29,91,98" tooltip="1.88e+02 – 1.90e+02" id="58" />
      <LegendEntry rgb="30,92,98" tooltip="1.90e+02 – 1.91e+02" id="59" />
      <LegendEntry rgb="30,93,98" tooltip="1.91e+02 – 1.93e+02" id="60" />
      <LegendEntry rgb="31,93,97" tooltip="1.93e+02 – 1.94e+02" id="61" />
      <LegendEntry rgb="32,94,97" tooltip="1.94e+02 – 1.96e+02" id="62" />
      <LegendEntry rgb="33,95,97" tooltip="1.96e+02 – 1.98e+02" id="63" />
      <LegendEntry rgb="34,96,97" tooltip="1.98e+02 – 1.99e+02" id="64" />
      <LegendEntry rgb="35,96,96" tooltip="1.99e+02 – 2.01e+02" id="65" />
      <LegendEntry rgb="36,97,96" tooltip="2.01e+02 – 2.02e+02" id="66" />
      <LegendEntry rgb="37,98,96" tooltip="2.02e+02 – 2.04e+02" id="67" />
      <LegendEntry rgb="38,99,95" tooltip="2.04e+02 – 2.06e+02" id="68" />
      <LegendEntry rgb="39,99,95" tooltip="2.06e+02 – 2.07e+02" id="69" />
      <LegendEntry rgb="40,100,95" tooltip="2.07e+02 – 2.09e+02" id="70" />
      <LegendEntry rgb="42,101,94" tooltip="2.09e+02 – 2.10e+02" id="71" />
      <LegendEntry rgb="43,101,94" tooltip="2.10e+02 – 2.12e+02" id="72" />
      <LegendEntry rgb="44,102,93" tooltip="2.12e+02 – 2.13e+02" id="73" />
      <LegendEntry rgb="45,103,93" tooltip="2.13e+02 – 2.15e+02" id="74" />
      <LegendEntry rgb="47,103,92" tooltip="2.15e+02 – 2.17e+02" showTick="true" id="75" />
      <LegendEntry rgb="48,104,92" tooltip="2.17e+02 – 2.18e+02" id="76" />
      <LegendEntry rgb="49,105,91" tooltip="2.18e+02 – 2.20e+02" id="77" />
      <LegendEntry rgb="51,105,90" tooltip="2.20e+02 – 2.21e+02" id="78" />
      <LegendEntry rgb="52,106,90" tooltip="2.21e+02 – 2.23e+02" id="79" />
      <LegendEntry rgb="53,106,89" tooltip="2.23e+02 – 2.24e+02" id="80" />
      <LegendEntry rgb="55,107,88" tooltip="2.24e+02 – 2.26e+02" id="81" />
      <LegendEntry rgb="56,108,88" tooltip="2.26e+02 – 2.28e+02" id="82" />
      <LegendEntry rgb="58,108,87" tooltip="2.28e+02 – 2.29e+02" id="83" />
      <LegendEntry rgb="59,109,86" tooltip="2.29e+02 – 2.31e+02" id="84" />
      <LegendEntry rgb="60,109,86" tooltip="2.31e+02 – 2.32e+02" id="85" />
      <LegendEntry rgb="62,110,85" tooltip="2.32e+02 – 2.34e+02" id="86" />
      <LegendEntry rgb="63,110,84" tooltip="2.34e+02 – 2.35e+02" id="87" />
      <LegendEntry rgb="65,111,83" tooltip="2.35e+02 – 2.37e+02" id="88" />
      <LegendEntry rgb="66,111,82" tooltip="2.37e+02 – 2.39e+02" id="89" />
      <LegendEntry rgb="68,112,82" tooltip="2.39e+02 – 2.40e+02" id="90" />
      <LegendEntry rgb="69,112,81" tooltip="2.40e+02 – 2.42e+02" id="91" />
      <LegendEntry rgb="71,113,80" tooltip="2.42e+02 – 2.43e+02" id="92" />
      <LegendEntry rgb="72,113,79" tooltip="2.43e+02 – 2.45e+02" id="93" />
      <LegendEntry rgb="74,114,78" tooltip="2.45e+02 – 2.46e+02" id="94" />
      <LegendEntry rgb="76,114,77" tooltip="2.46e+02 – 2.48e+02" id="95" />
      <LegendEntry rgb="77,115,77" tooltip="2.48e+02 – 2.50e+02" id="96" />
      <LegendEntry rgb="79,115,76" tooltip="2.50e+02 – 2.51e+02" id="97" />
      <LegendEntry rgb="80,116,75" tooltip="2.51e+02 – 2.53e+02" id="98" />
      <LegendEntry rgb="82,116,74" tooltip="2.53e+02 – 2.54e+02" id="99" />
      <LegendEntry rgb="83,117,73" tooltip="2.54e+02 – 2.56e+02" id="100" />
      <LegendEntry rgb="85,117,72" tooltip="2.56e+02 – 2.57e+02" id="101" />
      <LegendEntry rgb="87,118,71" tooltip="2.57e+02 – 2.59e+02" id="102" />
      <LegendEntry rgb="88,118,70" tooltip="2.59e+02 – 2.61e+02" id="103" />
      <LegendEntry rgb="90,119,69" tooltip="2.61e+02 – 2.62e+02" id="104" />
      <LegendEntry rgb="91,119,69" tooltip="2.62e+02 – 2.64e+02" id="105" />
      <LegendEntry rgb="93,120,68" tooltip="2.64e+02 – 2.65e+02" id="106" />
      <LegendEntry rgb="95,120,67" tooltip="2.65e+02 – 2.67e+02" id="107" />
      <LegendEntry rgb="96,121,66" tooltip="2.67e+02 – 2.69e+02" id="108" />
      <LegendEntry rgb="98,121,65" tooltip="2.69e+02 – 2.70e+02" id="109" />
      <LegendEntry rgb="99,122,64" tooltip="2.70e+02 – 2.72e+02" id="110" />
      <LegendEntry rgb="101,122,63" tooltip="2.72e+02 – 2.73e+02" id="111" />
      <LegendEntry rgb="103,123,62" tooltip="2.73e+02 – 2.75e+02" id="112" />
      <LegendEntry rgb="104,123,62" tooltip="2.75e+02 – 2.76e+02" id="113" />
      <LegendEntry rgb="106,123,61" tooltip="2.76e+02 – 2.78e+02" id="114" />
      <LegendEntry rgb="108,124,60" tooltip="2.78e+02 – 2.80e+02" id="115" />
      <LegendEntry rgb="109,124,59" tooltip="2.80e+02 – 2.81e+02" id="116" />
      <LegendEntry rgb="111,125,58" tooltip="2.81e+02 – 2.83e+02" id="117" />
      <LegendEntry rgb="113,125,57" tooltip="2.83e+02 – 2.84e+02" id="118" />
      <LegendEntry rgb="115,126,56" tooltip="2.84e+02 – 2.86e+02" id="119" />
      <LegendEntry rgb="116,126,56" tooltip="2.86e+02 – 2.87e+02" id="120" />
      <LegendEntry rgb="118,127,55" tooltip="2.87e+02 – 2.89e+02" id="121" />
      <LegendEntry rgb="120,127,54" tooltip="2.89e+02 – 2.91e+02" id="122" />
      <LegendEntry rgb="121,128,53" tooltip="2.91e+02 – 2.92e+02" id="123" />
      <LegendEntry rgb="123,128,52" tooltip="2.92e+02 – 2.94e+02" id="124" />
      <LegendEntry rgb="125,129,52" tooltip="2.94e+02 – 2.95e+02" id="125" />
      <LegendEntry rgb="127,129,51" tooltip="2.95e+02 – 2.97e+02" id="126" />
      <LegendEntry rgb="130,130,49" tooltip="2.97e+02 – 2.98e+02" id="127" />
      <LegendEntry rgb="132,131,49" tooltip="2.98e+02 – 3.00e+02" id="128" />
      <LegendEntry rgb="134,131,48" tooltip="3.00e+02 – 3.02e+02" showTick="true" showLabel="true" label="3.00e+02" id="129" />
      <LegendEntry rgb="136,132,47" tooltip="3.02e+02 – 3.03e+02" id="130" />
      <LegendEntry rgb="138,132,47" tooltip="3.03e+02 – 3.05e+02" id="131" />
      <LegendEntry rgb="140,133,46" tooltip="3.05e+02 – 3.06e+02" id="132" />
      <LegendEntry rgb="142,133,46" tooltip="3.06e+02 – 3.08e+02" id="133" />
      <LegendEntry rgb="143,134,45" tooltip="3.08e+02 – 3.09e+02" id="134" />
      <LegendEntry rgb="145,134,45" tooltip="3.09e+02 – 3.11e+02" id="135" />
      <LegendEntry rgb="147,135,44" tooltip="3.11e+02 – 3.13e+02" id="136" />
      <LegendEntry rgb="149,135,44" tooltip="3.13e+02 – 3.14e+02" id="137" />
      <LegendEntry rgb="151,136,44" tooltip="3.14e+02 – 3.16e+02" id="138" />
      <LegendEntry rgb="153,136,44" tooltip="3.16e+02 – 3.17e+02" id="139" />
      <LegendEntry rgb="155,137,43" tooltip="3.17e+02 – 3.19e+02" id="140" />
      <LegendEntry rgb="157,137,43" tooltip="3.19e+02 – 3.20e+02" id="141" />
      <LegendEntry rgb="159,137,43" tooltip="3.20e+02 – 3.22e+02" id="142" />
      <LegendEntry rgb="161,138,43" tooltip="3.22e+02 – 3.24e+02" id="143" />
      <LegendEntry rgb="163,138,44" tooltip="3.24e+02 – 3.25e+02" id="144" />
      <LegendEntry rgb="165,139,44" tooltip="3.25e+02 – 3.27e+02" id="145" />
      <LegendEntry rgb="167,139,44" tooltip="3.27e+02 – 3.28e+02" id="146" />
      <LegendEntry rgb="169,140,44" tooltip="3.28e+02 – 3.30e+02" id="147" />
      <LegendEntry rgb="171,140,45" tooltip="3.30e+02 – 3.31e+02" id="148" />
      <LegendEntry rgb="173,140,45" tooltip="3.31e+02 – 3.33e+02" id="149" />
      <LegendEntry rgb="175,141,46" tooltip="3.33e+02 – 3.35e+02" id="150" />
      <LegendEntry rgb="177,141,47" tooltip="3.35e+02 – 3.36e+02" id="151" />
      <LegendEntry rgb="179,142,47" tooltip="3.36e+02 – 3.38e+02" id="152" />
      <LegendEntry rgb="181,142,48" tooltip="3.38e+02 – 3.39e+02" id="153" />
      <LegendEntry rgb="183,142,49" tooltip="3.39e+02 – 3.41e+02" id="154" />
      <LegendEntry rgb="185,143,50" tooltip="3.41e+02 – 3.43e+02" id="155" />
      <LegendEntry rgb="187,143,51" tooltip="3.43e+02 – 3.44e+02" id="156" />
      <LegendEntry rgb="189,143,52" tooltip="3.44e+02 – 3.46e+02" id="157" />
      <LegendEntry rgb="190,144,53" tooltip="3.46e+02 – 3.47e+02" id="158" />
      <LegendEntry rgb="192,144,54" tooltip="3.47e+02 – 3.49e+02" id="159" />
      <LegendEntry rgb="194,144,55" tooltip="3.49e+02 – 3.50e+02" id="160" />
      <LegendEntry rgb="196,145,56" tooltip="3.50e+02 – 3.52e+02" id="161" />
      <LegendEntry rgb="198,145,58" tooltip="3.52e+02 – 3.54e+02" id="162" />
      <LegendEntry rgb="200,145,59" tooltip="3.54e+02 – 3.55e+02" id="163" />
      <LegendEntry rgb="202,146,60" tooltip="3.55e+02 – 3.57e+02" id="164" />
      <LegendEntry rgb="203,146,62" tooltip="3.57e+02 – 3.58e+02" id="165" />
      <LegendEntry rgb="205,146,63" tooltip="3.58e+02 – 3.60e+02" id="166" />
      <LegendEntry rgb="207,147,64" tooltip="3.60e+02 – 3.61e+02" id="167" />
      <LegendEntry rgb="209,147,66" tooltip="3.61e+02 – 3.63e+02" id="168" />
      <LegendEntry rgb="210,147,67" tooltip="3.63e+02 – 3.65e+02" id="169" />
      <LegendEntry rgb="212,148,69" tooltip="3.65e+02 – 3.66e+02" id="170" />
      <LegendEntry rgb="214,148,70" tooltip="3.66e+02 – 3.68e+02" id="171" />
      <LegendEntry rgb="216,148,72" tooltip="3.68e+02 – 3.69e+02" id="172" />
      <LegendEntry rgb="217,149,74" tooltip="3.69e+02 – 3.71e+02" id="173" />
      <LegendEntry rgb="219,149,75" tooltip="3.71e+02 – 3.72e+02" id="174" />
      <LegendEntry rgb="221,149,77" tooltip="3.72e+02 – 3.74e+02" id="175" />
      <LegendEntry rgb="222,150,79" tooltip="3.74e+02 – 3.76e+02" id="176" />
      <LegendEntry rgb="224,150,81" tooltip="3.76e+02 – 3.77e+02" id="177" />
      <LegendEntry rgb="225,151,82" tooltip="3.77e+02 – 3.79e+02" id="178" />
      <LegendEntry rgb="227,151,84" tooltip="3.79e+02 – 3.80e+02" id="179" />
      <LegendEntry rgb="228,151,86" tooltip="3.80e+02 – 3.82e+02" id="180" />
      <LegendEntry rgb="230,152,88" tooltip="3.82e+02 – 3.83e+02" id="181" />
      <LegendEntry rgb="231,152,90" tooltip="3.83e+02 – 3.85e+02" id="182" />
      <LegendEntry rgb="233,153,92" tooltip="3.85e+02 – 3.87e+02" id="183" />
      <LegendEntry rgb="234,153,94" tooltip="3.87e+02 – 3.88e+02" id="184" />
      <LegendEntry rgb="235,154,96" tooltip="3.88e+02 – 3.90e+02" id="185" />
      <LegendEntry rgb="237,154,98" tooltip="3.90e+02 – 3.91e+02" id="186" />
      <LegendEntry rgb="238,155,100" tooltip="3.91e+02 – 3.93e+02" id="187" />
      <LegendEntry rgb="239,155,103" tooltip="3.93e+02 – 3.94e+02" id="188" />
      <LegendEntry rgb="240,156,105" tooltip="3.94e+02 – 3.96e+02" id="189" />
      <LegendEntry rgb="241,157,107" tooltip="3.96e+02 – 3.98e+02" id="190" />
      <LegendEntry rgb="242,157,109" tooltip="3.98e+02 – 3.99e+02" id="191" />
      <LegendEntry rgb="243,158,112" tooltip="3.99e+02 – 4.01e+02" id="192" />
      <LegendEntry rgb="244,159,114" tooltip="4.01e+02 – 4.02e+02" id="193" />
      <LegendEntry rgb="245,159,116" tooltip="4.02e+02 – 4.04e+02" id="194" />
      <LegendEntry rgb="246,160,119" tooltip="4.04e+02 – 4.06e+02" id="195" />
      <LegendEntry rgb="247,161,121" tooltip="4.06e+02 – 4.07e+02" id="196" />
      <LegendEntry rgb="248,161,123" tooltip="4.07e+02 – 4.09e+02" id="197" />
      <LegendEntry rgb="248,162,126" tooltip="4.09e+02 – 4.10e+02" id="198" />
      <LegendEntry rgb="249,163,128" tooltip="4.10e+02 – 4.12e+02" showTick="true" id="199" />
      <LegendEntry rgb="249,163,130" tooltip="4.12e+02 – 4.13e+02" id="200" />
      <LegendEntry rgb="250,164,133" tooltip="4.13e+02 – 4.15e+02" id="201" />
      <LegendEntry rgb="250,165,135" tooltip="4.15e+02 – 4.17e+02" id="202" />
      <LegendEntry rgb="251,166,137" tooltip="4.17e+02 – 4.18e+02" id="203" />
      <LegendEntry rgb="251,166,140" tooltip="4.18e+02 – 4.20e+02" id="204" />
      <LegendEntry rgb="252,167,142" tooltip="4.20e+02 – 4.21e+02" id="205" />
      <LegendEntry rgb="252,168,144" tooltip="4.21e+02 – 4.23e+02" id="206" />
      <LegendEntry rgb="252,169,147" tooltip="4.23e+02 – 4.24e+02" id="207" />
      <LegendEntry rgb="252,169,149" tooltip="4.24e+02 – 4.26e+02" id="208" />
      <LegendEntry rgb="253,170,151" tooltip="4.26e+02 – 4.28e+02" id="209" />
      <LegendEntry rgb="253,171,154" tooltip="4.28e+02 – 4.29e+02" id="210" />
      <LegendEntry rgb="253,172,156" tooltip="4.29e+02 – 4.31e+02" id="211" />
      <LegendEntry rgb="253,172,158" tooltip="4.31e+02 – 4.32e+02" id="212" />
      <LegendEntry rgb="253,173,160" tooltip="4.32e+02 – 4.34e+02" id="213" />
      <LegendEntry rgb="253,174,162" tooltip="4.34e+02 – 4.35e+02" id="214" />
      <LegendEntry rgb="253,175,165" tooltip="4.35e+02 – 4.37e+02" id="215" />
      <LegendEntry rgb="253,175,167" tooltip="4.37e+02 – 4.39e+02" id="216" />
      <LegendEntry rgb="253,176,169" tooltip="4.39e+02 – 4.40e+02" id="217" />
      <LegendEntry rgb="253,177,171" tooltip="4.40e+02 – 4.42e+02" id="218" />
      <LegendEntry rgb="253,178,173" tooltip="4.42e+02 – 4.43e+02" id="219" />
      <LegendEntry rgb="253,178,175" tooltip="4.43e+02 – 4.45e+02" id="220" />
      <LegendEntry rgb="253,179,177" tooltip="4.45e+02 – 4.46e+02" id="221" />
      <LegendEntry rgb="253,180,180" tooltip="4.46e+02 – 4.48e+02" id="222" />
      <LegendEntry rgb="253,180,182" tooltip="4.48e+02 – 4.50e+02" id="223" />
      <LegendEntry rgb="253,181,184" tooltip="4.50e+02 – 4.51e+02" id="224" />
      <LegendEntry rgb="253,182,186" tooltip="4.51e+02 – 4.53e+02" id="225" />
      <LegendEntry rgb="253,183,188" tooltip="4.53e+02 – 4.54e+02" id="226" />
      <LegendEntry rgb="253,183,190" tooltip="4.54e+02 – 4.56e+02" id="227" />
      <LegendEntry rgb="253,184,192" tooltip="4.56e+02 – 4.57e+02" id="228" />
      <LegendEntry rgb="253,185,194" tooltip="4.57e+02 – 4.59e+02" id="229" />
      <LegendEntry rgb="253,186,196" tooltip="4.59e+02 – 4.61e+02" id="230" />
      <LegendEntry rgb="253,186,199" tooltip="4.61e+02 – 4.62e+02" id="231" />
      <LegendEntry rgb="253,187,201" tooltip="4.62e+02 – 4.64e+02" id="232" />
      <LegendEntry rgb="253,188,203" tooltip="4.64e+02 – 4.65e+02" id="233" />
      <LegendEntry rgb="253,188,205" tooltip="4.65e+02 – 4.67e+02" id="234" />
      <LegendEntry rgb="252,189,207" tooltip="4.67e+02 – 4.69e+02" id="235" />
      <LegendEntry rgb="252,190,209" tooltip="4.69e+02 – 4.70e+02" id="236" />
      <LegendEntry rgb="252,191,211" tooltip="4.70e+02 – 4.72e+02" id="237" />
      <LegendEntry rgb="252,191,214" tooltip="4.72e+02 – 4.73e+02" id="238" />
      <LegendEntry rgb="252,192,216" tooltip="4.73e+02 – 4.75e+02" id="239" />
      <LegendEntry rgb="252,193,218" tooltip="4.75e+02 – 4.76e+02" id="240" />
      <LegendEntry rgb="252,194,220" tooltip="4.76e+02 – 4.78e+02" id="241" />
      <LegendEntry rgb="252,195,223" tooltip="4.78e+02 – 4.80e+02" id="242" />
      <LegendEntry rgb="252,195,225" tooltip="4.80e+02 – 4.81e+02" id="243" />
      <LegendEntry rgb="252,196,227" tooltip="4.81e+02 – 4.83e+02" id="244" />
      <LegendEntry rgb="252,197,229" tooltip="4.83e+02 – 4.84e+02" id="245" />
      <LegendEntry rgb="251,198,232" tooltip="4.84e+02 – 4.86e+02" id="246" />
      <LegendEntry rgb="251,198,234" tooltip="4.86e+02 – 4.87e+02" id="247" />
      <LegendEntry rgb="251,199,236" tooltip="4.87e+02 – 4.89e+02" id="248" />
      <LegendEntry rgb="251,200,239" tooltip="4.89e+02 – 4.91e+02" id="249" />
      <LegendEntry rgb="251,201,241" tooltip="4.91e+02 – 4.92e+02" id="250" />
      <LegendEntry rgb="251,202,243" tooltip="4.92e+02 – 4.94e+02" id="251" />
      <LegendEntry rgb="251,202,246" tooltip="4.94e+02 – 4.95e+02" id="252" />
      <LegendEntry rgb="250,203,248" tooltip="4.95e+02 – 4.97e+02" id="253" />
      <LegendEntry rgb="250,204,250" tooltip="&gt;= 4.97e+02" id="254" />
    </Legend>
  </ColorMap>
</ColorMaps>
