{
  "layers": {
    "Himawari_AHI_Band3_Red_Visible_1km": {
      "description": "himawari/Himawari_AHI_Band3_Red_Visible_1km",
      "group": "overlays",
      "tags": "geostationary geo",
      "layergroup": "Geostationary",
      "product": "",
      "wrapX": true,
      "availability": {
        "rollingWindow": 30,
        "historicalRanges": [
          {
            "startDate": "2020-01-03",
            "endDate": "2020-01-04",
            "dateInterval": "10"
          }
        ]
      }
    }
  }
}