{
  "layers": {
    "OMPS_Aerosol_Index_PyroCumuloNimbus": {
      "id": "OMPS_Aerosol_Index_PyroCumuloNimbus",
      "title": "Aerosol Index (PyroCumuloNimbus)",
      "subtitle": "Suomi NPP / OMPS",
      "description": "omps/OMPS_Aerosol_Index_PyroCumuloNimbus",
      "tags": "ai PyroCb flammagenitus",
      "group": "overlays",
      "wrapadjacentdays": true,
      "layergroup": [
        "omps"
      ],
      "product": "OMPS_NPP_NMMIEAI_L2",
      "tracks": [
        "OrbitTracks_Suomi_NPP_Ascending"
      ],
      "daynight": [
        "day"
      ]
    }
  }
}