{
  "layers": {
      "CYGNSS_Orbit_Asc": {
          "id":       "CYGNSS_Orbit_Asc",
          "title":    "CYGNSS Orbital Track & Overpass Time (Ascending)",
          "subtitle": "CYGNSS / Space-Track.org",
          "description": "reference/orbits/CYGNSS_Orbit_Asc",
          "group":    "overlays",
          "format":   "image/png",
          "type":     "wms",
          "tileSize": [512, 512],
          "period":   "daily",
          "layergroup": [
            "reference",
            "reference_orbits"
          ],
          "track": "ascending",
          "startDate": "2018-12-01",

          "projections": {
            "geographic": {
                "source":   "GIBS:wms"
            }
          },

          "palette": {
              "id": "CYGNSS_Orbit_Asc",
              "immutable": true
          }
      }
  }
}
