{
  "layers": {
    "OrbitTracks_METOP-C_Ascending": {
      "id": "OrbitTracks_METOP-C_Ascending",
      "title": "MetOp-C - Orbit Track & Time",
      "subtitle": "MetOp-C / Space-Track.org",
      "description": "reference/orbits/OrbitTracks_METOP-C_Ascending",
      "group": "overlays",
      "format": "image/png",
      "type": "wms",
      "period": "daily",
      "layergroup": [
        "vector",
        "reference",
        "reference_orbits"
      ],
      "daynight": [
        "day"
      ],
      "track": "ascending",
      "startDate": "2018-11-07",
      "palette": {
        "id": "OrbitTracks_METOP-C_Ascending",
        "immutable": true
      },
      "tags": "tracks day",
      "vectorStyle": {
        "id": "OrbitTracks_METOP-C_Ascending",
        "antarctic": {
          "id": "OrbitTracks_METOP-C_Ascending_polar"
        },
        "arctic": {
          "id": "OrbitTracks_METOP-C_Ascending_polar"
        }
      },
      "clickDisabledFeatures": [
        "LineString"
      ],
      "modalShouldFollowClicks": true
    }
  }
}