{
  "layers": {
    "OrbitTracks_Calipso_Ascending": {
      "id": "OrbitTracks_Calipso_Ascending",
      "title": "CALIPSO - Orbit Track & Time",
      "subtitle": "CALIPSO / Space-Track.org",
      "description": "reference/orbits/OrbitTracks_Calipso_Ascending",
      "group": "overlays",
      "type": "vector",
      "period": "daily",
      "wrapadjacentdays": true,
      "layergroup": "Orbital Track",
      "daynight": [
        "day"
      ],
      "track": "ascending",
      "startDate": "2006-04-28",
      "palette": {
        "id": "OrbitTracks_Calipso_Ascending",
        "immutable": true
      },
      "tags": "tracks day vector",
      "clickDisabledFeatures": [
        "LineString"
      ],
      "vectorStyle": {
        "id": "OrbitTracks_Calipso_Ascending",
        "antarctic": {
          "id": "OrbitTracks_Calipso_Ascending_polar"
        },
        "arctic": {
          "id": "OrbitTracks_Calipso_Ascending_polar"
        }
      },
      "modalShouldFollowClicks": true,
      "breakPointLayer": {
        "id": "OrbitTracks_Calipso_Ascending",
        "type": "wms",
        "format": "image/png",
        "breakPointType": "max",
        "projections": {
          "geographic": {
            "source": "GIBS:wms",
            "resolutionBreakPoint": 0.017578125
          },
          "antarctic": {
            "resolutionBreakPoint": 2048,
            "source": "GIBS:wms:antarctic"
          },
          "arctic": {
            "resolutionBreakPoint": 2048,
            "source": "GIBS:wms:arctic"
          }
        }
      }
    }
  }
}